Workbook

Sheet Carga Web Cirugias
A1: Plantilla de carga web CRR - ingreso diario de pabellones | AM1: Plantilla de carga web CRR - ingreso diario de pabellones | AN1: Plantilla de carga web CRR - ingreso diario de pabellones | AO1: Plantilla de carga web CRR - ingreso diario de pabellones
A2: Obligatorio | B2: Obligatorio | C2: Obligatorio | D2: Obligatorio | E2: Obligatorio | F2: Obligatorio | G2: Opcional | H2: Obligatorio | I2: Opcional | J2: Automático | K2: Opcional | L2: Obligatorio | M2: Obligatorio | N2: Obligatorio | O2: Obligatorio primera cirugía | P2: Automático | Q2: Obligatorio si atraso primera hora | R2: Obligatorio si se realiza | S2: Obligatorio si se realiza | T2: Opcional | U2: Manual | V2: Manual | W2: Automático | X2: Automático | Y2: Automático | Z2: Automático | AA2: Obligatorio si recambio >15 min | AB2: Automático | AC2: Automático | AD2: Manual | AE2: Automático | AF2: Automático | AG2: Obligatorio si suspendido | AH2: Obligatorio si suspendido | AI2: Obligatorio si suspendido | AJ2: Opcional | AK2: Opcional | AL2: Opcional | AM2: Opcional | AN2: Opcional | AO2: Opcional | AP2: Automático | AQ2: Automático | AR2: Automático | AS2: Automático | AT2: Automático | AU2: Automático | AV2: Automático | AW2: Automático
A3: Fecha Quirofano | B3: Nombre | C3: Apellido | D3: Edad | E3: Descripción Intervención | F3: Especialidad | G3: Subespecialidad | H3: Codigo 1 | I3: Codigo 2 | J3: Categoria | K3: Anestesista | L3: Cirujano | M3: Quirofano | N3: Estado | O3: Ingreso Pabellon | P3: Clasificación ingreso 08:00-08:15 | Q3: Justificación Atraso Primera Hora | R3: Inicio Cirugia | S3: Termino Cirugia | T3: Salida Pabellon | U3: Inicio Funcionamiento Pabellon | V3: Termino Funcionamiento Pabellon | W3: Horario Funcionamiento Pabellon (Min) | X3: Ocupación Diaria Pabellón (%) | Y3: Tiempo recambio entre cirugías (Min) | Z3: Cumple recambio <=15 min | AA3: Justificación Recambio >15 Min | AB3: Demora Ingreso-Inicio Min | AC3: Duracion Cirugia Formula Min | AD3: Tiempo programado de cirugía en tabla (Min) | AE3: Diferencia Real - Programado Min | AF3: Asertividad | AG3: Causas Suspension | AH3: Motivo de Suspensión | AI3: Motivo Justificado | AJ3: Observaciones | AK3: Ingreso CMA ambulatorio | AL3: Hospitalizado posterior | AM3: Episodio | AN3: Diagnostico | AO3: Cirugia | AP3: Semana Inicio | AQ3: Semana Fin | AR3: Semana Lunes-Domingo | AS3: Mes Dashboard | AT3: Día Semana | AU3: ID Registro Dashboard | AV3: Validación Carga Dashboard | AW3: Detalle Suspensión Dashboard
J4: =IF(H4<>"",IFERROR(VLOOKUP(IFERROR(LEFT(H4,FIND("-",H4)-1),H4),'Catalogo MINSAL'!A:E,5,FALSE),""),IF(I4<>"",IFERROR(VLOOKUP(IFERROR(LEFT(I4,FIND("-",I4)-1),I4),'Catalogo MINSAL'!A:E,5,FALSE),""),"")) | P4: =IFERROR(IF(OR(O4="",A4="",M4=""),"",IF(SUMPRODUCT(($A$4:$A$500=A4)*($M$4:$M$500=M4)*($O$4:$O$500<>"")*(MOD($O$4:$O$500,1)<MOD(O4,1)))=0,IF(MOD(O4,1)<=TIME(8,15,0),"Ingreso adecuado primera hora","Atraso primera hora"),"No aplica")),"") | U4: =IFERROR(VLOOKUP(M4,'Horario Pabellones'!$A$4:$D$17,2,FALSE),"") | V4: =IFERROR(VLOOKUP(M4,'Horario Pabellones'!$A$4:$D$17,3,FALSE),"") | W4: =IFERROR(VLOOKUP(M4,'Horario Pabellones'!$A$4:$D$17,4,FALSE),"") | X4: =IFERROR(IF(OR(A4="",M4="",W4=""),"",(((_xludf.AGGREGATE(14,6,MOD($S$4:$S$500,1)/(($A$4:$A$500=A4)*($M$4:$M$500=M4)*($R$4:$R$500<>"")*($S$4:$S$500<>"")),1)-_xludf.AGGREGATE(15,6,MOD($R$4:$R$500,1)/(($A$4:$A$500=A4)*($M$4:$M$500=M4)*($R$4:$R$500<>"")*($S$4:$S$500<>"")),1))*1440)/60)/(W4/60)),"") | Y4: =IFERROR(IF(OR(O4="",A4="",M4=""),"",(IF(ISNUMBER(O4),MOD(O4,1),TIMEVALUE(O4))-LOOKUP(2,1/(($A$4:$A$500=A4)*($M$4:$M$500=M4)*($T$4:$T$500<>"")*($T$4:$T$500<IF(ISNUMBER(O4),MOD(O4,1),TIMEVALUE(O4)))),$T$4:$T$500))*1440),"") | Z4: =IFERROR(IF(Y4="","",IF(ROUND(Y4,0)<=15,"Cumple","No cumple")),"") | AB4: =IFERROR(IF(OR(O4="",R4=""),"",IF(IF(ISNUMBER(R4),MOD(R4,1),TIMEVALUE(R4))>=IF(ISNUMBER(O4),MOD(O4,1),TIMEVALUE(O4)),(IF(ISNUMBER(R4),MOD(R4,1),TIMEVALUE(R4))-IF(ISNUMBER(O4),MOD(O4,1),TIMEVALUE(O4)))*1440,(IF(ISNUMBER(R4),MOD(R4,1),TIMEVALUE(R4))+1-IF(ISNUMBER(O4),MOD(O4,1),TIMEVALUE(O4)))*1440)),"") | AC4: =IFERROR(IF(OR(R4="",S4=""),"",IF(IF(ISNUMBER(S4),MOD(S4,1),TIMEVALUE(S4))>=IF(ISNUMBER(R4),MOD(R4,1),TIMEVALUE(R4)),(IF(ISNUMBER(S4),MOD(S4,1),TIMEVALUE(S4))-IF(ISNUMBER(R4),MOD(R4,1),TIMEVALUE(R4)))*1440,(IF(ISNUMBER(S4),MOD(S4,1),TIMEVALUE(S4))+1-IF(ISNUMBER(R4),MOD(R4,1),TIMEVALUE(R4)))*1440)),"") | AE4: =IFERROR(IF(OR(AC4="",AD4=""),"",AC4-AD4),"") | AF4: =IFERROR(IF(AE4="","",IF(ROUND(AE4,0)>15,"Subestimacion",IF(ROUND(AE4,0)<-15,"Sobrestimacion","Asertivo"))),"") | AP4: =IF(A4="","",A4-WEEKDAY(A4,2)+1) | AQ4: =IF(AO4="","",AO4+6) | AR4: =IF(AO4="","","Semana "&TEXT(AO4,"dd-mm-yyyy")&" al "&TEXT(AP4,"dd-mm-yyyy")) | AS4: =IF(A4="","",TEXT(A4,"mmmm yyyy")) | AT4: =IF(A4="","",TEXT(A4,"dddd")) | AU4: =IF(A4="","","CRR-"&TEXT(A4,"yyyymmdd")&"-"&M4&"-"&TEXT(ROW()-3,"0000")) | AV4: =IF(A4="","",IF(OR(B4="",C4="",E4="",F4="",M4="",N4=""),"Revisar campos obligatorios",IF(AND(P4="Atraso primera hora",Q4=""),"Falta justificación atraso primera hora",IF(AND(Z4="No cumple",AA4=""),"Falta justificación recambio >15 min",IF(AND(ISNUMBER(SEARCH("suspend",N4)),OR(AG4="",AH4="")),"Falta causa/motivo suspensión","OK"))))) | AW4: =IF(N4="","",IF(ISNUMBER(SEARCH("suspend",N4)),IF(AND(AG4="",AH4=""),"Sin causa/motivo registrado",IF(AG4="",AH4,IF(AH4="",AG4,AG4&": "&AH4))),""))
J5: =IF(H5<>"",IFERROR(VLOOKUP(IFERROR(LEFT(H5,FIND("-",H5)-1),H5),'Catalogo MINSAL'!A:E,5,FALSE),""),IF(I5<>"",IFERROR(VLOOKUP(IFERROR(LEFT(I5,FIND("-",I5)-1),I5),'Catalogo MINSAL'!A:E,5,FALSE),""),"")) | P5: =IFERROR(IF(OR(O5="",A5="",M5=""),"",IF(SUMPRODUCT(($A$4:$A$500=A5)*($M$4:$M$500=M5)*($O$4:$O$500<>"")*(MOD($O$4:$O$500,1)<MOD(O5,1)))=0,IF(MOD(O5,1)<=TIME(8,15,0),"Ingreso adecuado primera hora","Atraso primera hora"),"No aplica")),"") | U5: =IFERROR(VLOOKUP(M5,'Horario Pabellones'!$A$4:$D$17,2,FALSE),"") | V5: =IFERROR(VLOOKUP(M5,'Horario Pabellones'!$A$4:$D$17,3,FALSE),"") | W5: =IFERROR(VLOOKUP(M5,'Horario Pabellones'!$A$4:$D$17,4,FALSE),"") | X5: =IFERROR(IF(OR(A5="",M5="",W5=""),"",(((_xludf.AGGREGATE(14,6,MOD($S$4:$S$500,1)/(($A$4:$A$500=A5)*($M$4:$M$500=M5)*($R$4:$R$500<>"")*($S$4:$S$500<>"")),1)-_xludf.AGGREGATE(15,6,MOD($R$4:$R$500,1)/(($A$4:$A$500=A5)*($M$4:$M$500=M5)*($R$4:$R$500<>"")*($S$4:$S$500<>"")),1))*1440)/60)/(W5/60)),"") | Y5: =IFERROR(IF(OR(O5="",A5="",M5=""),"",(IF(ISNUMBER(O5),MOD(O5,1),TIMEVALUE(O5))-LOOKUP(2,1/(($A$4:$A$500=A5)*($M$4:$M$500=M5)*($T$4:$T$500<>"")*($T$4:$T$500<IF(ISNUMBER(O5),MOD(O5,1),TIMEVALUE(O5)))),$T$4:$T$500))*1440),"") | Z5: =IFERROR(IF(Y5="","",IF(ROUND(Y5,0)<=15,"Cumple","No cumple")),"") | AB5: =IFERROR(IF(OR(O5="",R5=""),"",IF(IF(ISNUMBER(R5),MOD(R5,1),TIMEVALUE(R5))>=IF(ISNUMBER(O5),MOD(O5,1),TIMEVALUE(O5)),(IF(ISNUMBER(R5),MOD(R5,1),TIMEVALUE(R5))-IF(ISNUMBER(O5),MOD(O5,1),TIMEVALUE(O5)))*1440,(IF(ISNUMBER(R5),MOD(R5,1),TIMEVALUE(R5))+1-IF(ISNUMBER(O5),MOD(O5,1),TIMEVALUE(O5)))*1440)),"") | AC5: =IFERROR(IF(OR(R5="",S5=""),"",IF(IF(ISNUMBER(S5),MOD(S5,1),TIMEVALUE(S5))>=IF(ISNUMBER(R5),MOD(R5,1),TIMEVALUE(R5)),(IF(ISNUMBER(S5),MOD(S5,1),TIMEVALUE(S5))-IF(ISNUMBER(R5),MOD(R5,1),TIMEVALUE(R5)))*1440,(IF(ISNUMBER(S5),MOD(S5,1),TIMEVALUE(S5))+1-IF(ISNUMBER(R5),MOD(R5,1),TIMEVALUE(R5)))*1440)),"") | AE5: =IFERROR(IF(OR(AC5="",AD5=""),"",AC5-AD5),"") | AF5: =IFERROR(IF(AE5="","",IF(ROUND(AE5,0)>15,"Subestimacion",IF(ROUND(AE5,0)<-15,"Sobrestimacion","Asertivo"))),"") | AP5: =IF(A5="","",A5-WEEKDAY(A5,2)+1) | AQ5: =IF(AO5="","",AO5+6) | AR5: =IF(AO5="","","Semana "&TEXT(AO5,"dd-mm-yyyy")&" al "&TEXT(AP5,"dd-mm-yyyy")) | AS5: =IF(A5="","",TEXT(A5,"mmmm yyyy")) | AT5: =IF(A5="","",TEXT(A5,"dddd")) | AU5: =IF(A5="","","CRR-"&TEXT(A5,"yyyymmdd")&"-"&M5&"-"&TEXT(ROW()-3,"0000")) | AV5: =IF(A5="","",IF(OR(B5="",C5="",E5="",F5="",M5="",N5=""),"Revisar campos obligatorios",IF(AND(P5="Atraso primera hora",Q5=""),"Falta justificación atraso primera hora",IF(AND(Z5="No cumple",AA5=""),"Falta justificación recambio >15 min",IF(AND(ISNUMBER(SEARCH("suspend",N5)),OR(AG5="",AH5="")),"Falta causa/motivo suspensión","OK"))))) | AW5: =IF(N5="","",IF(ISNUMBER(SEARCH("suspend",N5)),IF(AND(AG5="",AH5=""),"Sin causa/motivo registrado",IF(AG5="",AH5,IF(AH5="",AG5,AG5&": "&AH5))),""))
J6: =IF(H6<>"",IFERROR(VLOOKUP(IFERROR(LEFT(H6,FIND("-",H6)-1),H6),'Catalogo MINSAL'!A:E,5,FALSE),""),IF(I6<>"",IFERROR(VLOOKUP(IFERROR(LEFT(I6,FIND("-",I6)-1),I6),'Catalogo MINSAL'!A:E,5,FALSE),""),"")) | P6: =IFERROR(IF(OR(O6="",A6="",M6=""),"",IF(SUMPRODUCT(($A$4:$A$500=A6)*($M$4:$M$500=M6)*($O$4:$O$500<>"")*(MOD($O$4:$O$500,1)<MOD(O6,1)))=0,IF(MOD(O6,1)<=TIME(8,15,0),"Ingreso adecuado primera hora","Atraso primera hora"),"No aplica")),"") | U6: =IFERROR(VLOOKUP(M6,'Horario Pabellones'!$A$4:$D$17,2,FALSE),"") | V6: =IFERROR(VLOOKUP(M6,'Horario Pabellones'!$A$4:$D$17,3,FALSE),"") | W6: =IFERROR(VLOOKUP(M6,'Horario Pabellones'!$A$4:$D$17,4,FALSE),"") | X6: =IFERROR(IF(OR(A6="",M6="",W6=""),"",(((_xludf.AGGREGATE(14,6,MOD($S$4:$S$500,1)/(($A$4:$A$500=A6)*($M$4:$M$500=M6)*($R$4:$R$500<>"")*($S$4:$S$500<>"")),1)-_xludf.AGGREGATE(15,6,MOD($R$4:$R$500,1)/(($A$4:$A$500=A6)*($M$4:$M$500=M6)*($R$4:$R$500<>"")*($S$4:$S$500<>"")),1))*1440)/60)/(W6/60)),"") | Y6: =IFERROR(IF(OR(O6="",A6="",M6=""),"",(IF(ISNUMBER(O6),MOD(O6,1),TIMEVALUE(O6))-LOOKUP(2,1/(($A$4:$A$500=A6)*($M$4:$M$500=M6)*($T$4:$T$500<>"")*($T$4:$T$500<IF(ISNUMBER(O6),MOD(O6,1),TIMEVALUE(O6)))),$T$4:$T$500))*1440),"") | Z6: =IFERROR(IF(Y6="","",IF(ROUND(Y6,0)<=15,"Cumple","No cumple")),"") | AB6: =IFERROR(IF(OR(O6="",R6=""),"",IF(IF(ISNUMBER(R6),MOD(R6,1),TIMEVALUE(R6))>=IF(ISNUMBER(O6),MOD(O6,1),TIMEVALUE(O6)),(IF(ISNUMBER(R6),MOD(R6,1),TIMEVALUE(R6))-IF(ISNUMBER(O6),MOD(O6,1),TIMEVALUE(O6)))*1440,(IF(ISNUMBER(R6),MOD(R6,1),TIMEVALUE(R6))+1-IF(ISNUMBER(O6),MOD(O6,1),TIMEVALUE(O6)))*1440)),"") | AC6: =IFERROR(IF(OR(R6="",S6=""),"",IF(IF(ISNUMBER(S6),MOD(S6,1),TIMEVALUE(S6))>=IF(ISNUMBER(R6),MOD(R6,1),TIMEVALUE(R6)),(IF(ISNUMBER(S6),MOD(S6,1),TIMEVALUE(S6))-IF(ISNUMBER(R6),MOD(R6,1),TIMEVALUE(R6)))*1440,(IF(ISNUMBER(S6),MOD(S6,1),TIMEVALUE(S6))+1-IF(ISNUMBER(R6),MOD(R6,1),TIMEVALUE(R6)))*1440)),"") | AE6: =IFERROR(IF(OR(AC6="",AD6=""),"",AC6-AD6),"") | AF6: =IFERROR(IF(AE6="","",IF(ROUND(AE6,0)>15,"Subestimacion",IF(ROUND(AE6,0)<-15,"Sobrestimacion","Asertivo"))),"") | AP6: =IF(A6="","",A6-WEEKDAY(A6,2)+1) | AQ6: =IF(AO6="","",AO6+6) | AR6: =IF(AO6="","","Semana "&TEXT(AO6,"dd-mm-yyyy")&" al "&TEXT(AP6,"dd-mm-yyyy")) | AS6: =IF(A6="","",TEXT(A6,"mmmm yyyy")) | AT6: =IF(A6="","",TEXT(A6,"dddd")) | AU6: =IF(A6="","","CRR-"&TEXT(A6,"yyyymmdd")&"-"&M6&"-"&TEXT(ROW()-3,"0000")) | AV6: =IF(A6="","",IF(OR(B6="",C6="",E6="",F6="",M6="",N6=""),"Revisar campos obligatorios",IF(AND(P6="Atraso primera hora",Q6=""),"Falta justificación atraso primera hora",IF(AND(Z6="No cumple",AA6=""),"Falta justificación recambio >15 min",IF(AND(ISNUMBER(SEARCH("suspend",N6)),OR(AG6="",AH6="")),"Falta causa/motivo suspensión","OK"))))) | AW6: =IF(N6="","",IF(ISNUMBER(SEARCH("suspend",N6)),IF(AND(AG6="",AH6=""),"Sin causa/motivo registrado",IF(AG6="",AH6,IF(AH6="",AG6,AG6&": "&AH6))),""))
J7: =IF(H7<>"",IFERROR(VLOOKUP(IFERROR(LEFT(H7,FIND("-",H7)-1),H7),'Catalogo MINSAL'!A:E,5,FALSE),""),IF(I7<>"",IFERROR(VLOOKUP(IFERROR(LEFT(I7,FIND("-",I7)-1),I7),'Catalogo MINSAL'!A:E,5,FALSE),""),"")) | P7: =IFERROR(IF(OR(O7="",A7="",M7=""),"",IF(SUMPRODUCT(($A$4:$A$500=A7)*($M$4:$M$500=M7)*($O$4:$O$500<>"")*(MOD($O$4:$O$500,1)<MOD(O7,1)))=0,IF(MOD(O7,1)<=TIME(8,15,0),"Ingreso adecuado primera hora","Atraso primera hora"),"No aplica")),"") | U7: =IFERROR(VLOOKUP(M7,'Horario Pabellones'!$A$4:$D$17,2,FALSE),"") | V7: =IFERROR(VLOOKUP(M7,'Horario Pabellones'!$A$4:$D$17,3,FALSE),"") | W7: =IFERROR(VLOOKUP(M7,'Horario Pabellones'!$A$4:$D$17,4,FALSE),"") | X7: =IFERROR(IF(OR(A7="",M7="",W7=""),"",(((_xludf.AGGREGATE(14,6,MOD($S$4:$S$500,1)/(($A$4:$A$500=A7)*($M$4:$M$500=M7)*($R$4:$R$500<>"")*($S$4:$S$500<>"")),1)-_xludf.AGGREGATE(15,6,MOD($R$4:$R$500,1)/(($A$4:$A$500=A7)*($M$4:$M$500=M7)*($R$4:$R$500<>"")*($S$4:$S$500<>"")),1))*1440)/60)/(W7/60)),"") | Y7: =IFERROR(IF(OR(O7="",A7="",M7=""),"",(IF(ISNUMBER(O7),MOD(O7,1),TIMEVALUE(O7))-LOOKUP(2,1/(($A$4:$A$500=A7)*($M$4:$M$500=M7)*($T$4:$T$500<>"")*($T$4:$T$500<IF(ISNUMBER(O7),MOD(O7,1),TIMEVALUE(O7)))),$T$4:$T$500))*1440),"") | Z7: =IFERROR(IF(Y7="","",IF(ROUND(Y7,0)<=15,"Cumple","No cumple")),"") | AB7: =IFERROR(IF(OR(O7="",R7=""),"",IF(IF(ISNUMBER(R7),MOD(R7,1),TIMEVALUE(R7))>=IF(ISNUMBER(O7),MOD(O7,1),TIMEVALUE(O7)),(IF(ISNUMBER(R7),MOD(R7,1),TIMEVALUE(R7))-IF(ISNUMBER(O7),MOD(O7,1),TIMEVALUE(O7)))*1440,(IF(ISNUMBER(R7),MOD(R7,1),TIMEVALUE(R7))+1-IF(ISNUMBER(O7),MOD(O7,1),TIMEVALUE(O7)))*1440)),"") | AC7: =IFERROR(IF(OR(R7="",S7=""),"",IF(IF(ISNUMBER(S7),MOD(S7,1),TIMEVALUE(S7))>=IF(ISNUMBER(R7),MOD(R7,1),TIMEVALUE(R7)),(IF(ISNUMBER(S7),MOD(S7,1),TIMEVALUE(S7))-IF(ISNUMBER(R7),MOD(R7,1),TIMEVALUE(R7)))*1440,(IF(ISNUMBER(S7),MOD(S7,1),TIMEVALUE(S7))+1-IF(ISNUMBER(R7),MOD(R7,1),TIMEVALUE(R7)))*1440)),"") | AE7: =IFERROR(IF(OR(AC7="",AD7=""),"",AC7-AD7),"") | AF7: =IFERROR(IF(AE7="","",IF(ROUND(AE7,0)>15,"Subestimacion",IF(ROUND(AE7,0)<-15,"Sobrestimacion","Asertivo"))),"") | AP7: =IF(A7="","",A7-WEEKDAY(A7,2)+1) | AQ7: =IF(AO7="","",AO7+6) | AR7: =IF(AO7="","","Semana "&TEXT(AO7,"dd-mm-yyyy")&" al "&TEXT(AP7,"dd-mm-yyyy")) | AS7: =IF(A7="","",TEXT(A7,"mmmm yyyy")) | AT7: =IF(A7="","",TEXT(A7,"dddd")) | AU7: =IF(A7="","","CRR-"&TEXT(A7,"yyyymmdd")&"-"&M7&"-"&TEXT(ROW()-3,"0000")) | AV7: =IF(A7="","",IF(OR(B7="",C7="",E7="",F7="",M7="",N7=""),"Revisar campos obligatorios",IF(AND(P7="Atraso primera hora",Q7=""),"Falta justificación atraso primera hora",IF(AND(Z7="No cumple",AA7=""),"Falta justificación recambio >15 min",IF(AND(ISNUMBER(SEARCH("suspend",N7)),OR(AG7="",AH7="")),"Falta causa/motivo suspensión","OK"))))) | AW7: =IF(N7="","",IF(ISNUMBER(SEARCH("suspend",N7)),IF(AND(AG7="",AH7=""),"Sin causa/motivo registrado",IF(AG7="",AH7,IF(AH7="",AG7,AG7&": "&AH7))),""))
J8: =IF(H8<>"",IFERROR(VLOOKUP(IFERROR(LEFT(H8,FIND("-",H8)-1),H8),'Catalogo MINSAL'!A:E,5,FALSE),""),IF(I8<>"",IFERROR(VLOOKUP(IFERROR(LEFT(I8,FIND("-",I8)-1),I8),'Catalogo MINSAL'!A:E,5,FALSE),""),"")) | P8: =IFERROR(IF(OR(O8="",A8="",M8=""),"",IF(SUMPRODUCT(($A$4:$A$500=A8)*($M$4:$M$500=M8)*($O$4:$O$500<>"")*(MOD($O$4:$O$500,1)<MOD(O8,1)))=0,IF(MOD(O8,1)<=TIME(8,15,0),"Ingreso adecuado primera hora","Atraso primera hora"),"No aplica")),"") | U8: =IFERROR(VLOOKUP(M8,'Horario Pabellones'!$A$4:$D$17,2,FALSE),"") | V8: =IFERROR(VLOOKUP(M8,'Horario Pabellones'!$A$4:$D$17,3,FALSE),"") | W8: =IFERROR(VLOOKUP(M8,'Horario Pabellones'!$A$4:$D$17,4,FALSE),"") | X8: =IFERROR(IF(OR(A8="",M8="",W8=""),"",(((_xludf.AGGREGATE(14,6,MOD($S$4:$S$500,1)/(($A$4:$A$500=A8)*($M$4:$M$500=M8)*($R$4:$R$500<>"")*($S$4:$S$500<>"")),1)-_xludf.AGGREGATE(15,6,MOD($R$4:$R$500,1)/(($A$4:$A$500=A8)*($M$4:$M$500=M8)*($R$4:$R$500<>"")*($S$4:$S$500<>"")),1))*1440)/60)/(W8/60)),"") | Y8: =IFERROR(IF(OR(O8="",A8="",M8=""),"",(IF(ISNUMBER(O8),MOD(O8,1),TIMEVALUE(O8))-LOOKUP(2,1/(($A$4:$A$500=A8)*($M$4:$M$500=M8)*($T$4:$T$500<>"")*($T$4:$T$500<IF(ISNUMBER(O8),MOD(O8,1),TIMEVALUE(O8)))),$T$4:$T$500))*1440),"") | Z8: =IFERROR(IF(Y8="","",IF(ROUND(Y8,0)<=15,"Cumple","No cumple")),"") | AB8: =IFERROR(IF(OR(O8="",R8=""),"",IF(IF(ISNUMBER(R8),MOD(R8,1),TIMEVALUE(R8))>=IF(ISNUMBER(O8),MOD(O8,1),TIMEVALUE(O8)),(IF(ISNUMBER(R8),MOD(R8,1),TIMEVALUE(R8))-IF(ISNUMBER(O8),MOD(O8,1),TIMEVALUE(O8)))*1440,(IF(ISNUMBER(R8),MOD(R8,1),TIMEVALUE(R8))+1-IF(ISNUMBER(O8),MOD(O8,1),TIMEVALUE(O8)))*1440)),"") | AC8: =IFERROR(IF(OR(R8="",S8=""),"",IF(IF(ISNUMBER(S8),MOD(S8,1),TIMEVALUE(S8))>=IF(ISNUMBER(R8),MOD(R8,1),TIMEVALUE(R8)),(IF(ISNUMBER(S8),MOD(S8,1),TIMEVALUE(S8))-IF(ISNUMBER(R8),MOD(R8,1),TIMEVALUE(R8)))*1440,(IF(ISNUMBER(S8),MOD(S8,1),TIMEVALUE(S8))+1-IF(ISNUMBER(R8),MOD(R8,1),TIMEVALUE(R8)))*1440)),"") | AE8: =IFERROR(IF(OR(AC8="",AD8=""),"",AC8-AD8),"") | AF8: =IFERROR(IF(AE8="","",IF(ROUND(AE8,0)>15,"Subestimacion",IF(ROUND(AE8,0)<-15,"Sobrestimacion","Asertivo"))),"") | AP8: =IF(A8="","",A8-WEEKDAY(A8,2)+1) | AQ8: =IF(AO8="","",AO8+6) | AR8: =IF(AO8="","","Semana "&TEXT(AO8,"dd-mm-yyyy")&" al "&TEXT(AP8,"dd-mm-yyyy")) | AS8: =IF(A8="","",TEXT(A8,"mmmm yyyy")) | AT8: =IF(A8="","",TEXT(A8,"dddd")) | AU8: =IF(A8="","","CRR-"&TEXT(A8,"yyyymmdd")&"-"&M8&"-"&TEXT(ROW()-3,"0000")) | AV8: =IF(A8="","",IF(OR(B8="",C8="",E8="",F8="",M8="",N8=""),"Revisar campos obligatorios",IF(AND(P8="Atraso primera hora",Q8=""),"Falta justificación atraso primera hora",IF(AND(Z8="No cumple",AA8=""),"Falta justificación recambio >15 min",IF(AND(ISNUMBER(SEARCH("suspend",N8)),OR(AG8="",AH8="")),"Falta causa/motivo suspensión","OK"))))) | AW8: =IF(N8="","",IF(ISNUMBER(SEARCH("suspend",N8)),IF(AND(AG8="",AH8=""),"Sin causa/motivo registrado",IF(AG8="",AH8,IF(AH8="",AG8,AG8&": "&AH8))),""))
J9: =IF(H9<>"",IFERROR(VLOOKUP(IFERROR(LEFT(H9,FIND("-",H9)-1),H9),'Catalogo MINSAL'!A:E,5,FALSE),""),IF(I9<>"",IFERROR(VLOOKUP(IFERROR(LEFT(I9,FIND("-",I9)-1),I9),'Catalogo MINSAL'!A:E,5,FALSE),""),"")) | P9: =IFERROR(IF(OR(O9="",A9="",M9=""),"",IF(SUMPRODUCT(($A$4:$A$500=A9)*($M$4:$M$500=M9)*($O$4:$O$500<>"")*(MOD($O$4:$O$500,1)<MOD(O9,1)))=0,IF(MOD(O9,1)<=TIME(8,15,0),"Ingreso adecuado primera hora","Atraso primera hora"),"No aplica")),"") | U9: =IFERROR(VLOOKUP(M9,'Horario Pabellones'!$A$4:$D$17,2,FALSE),"") | V9: =IFERROR(VLOOKUP(M9,'Horario Pabellones'!$A$4:$D$17,3,FALSE),"") | W9: =IFERROR(VLOOKUP(M9,'Horario Pabellones'!$A$4:$D$17,4,FALSE),"") | X9: =IFERROR(IF(OR(A9="",M9="",W9=""),"",(((_xludf.AGGREGATE(14,6,MOD($S$4:$S$500,1)/(($A$4:$A$500=A9)*($M$4:$M$500=M9)*($R$4:$R$500<>"")*($S$4:$S$500<>"")),1)-_xludf.AGGREGATE(15,6,MOD($R$4:$R$500,1)/(($A$4:$A$500=A9)*($M$4:$M$500=M9)*($R$4:$R$500<>"")*($S$4:$S$500<>"")),1))*1440)/60)/(W9/60)),"") | Y9: =IFERROR(IF(OR(O9="",A9="",M9=""),"",(IF(ISNUMBER(O9),MOD(O9,1),TIMEVALUE(O9))-LOOKUP(2,1/(($A$4:$A$500=A9)*($M$4:$M$500=M9)*($T$4:$T$500<>"")*($T$4:$T$500<IF(ISNUMBER(O9),MOD(O9,1),TIMEVALUE(O9)))),$T$4:$T$500))*1440),"") | Z9: =IFERROR(IF(Y9="","",IF(ROUND(Y9,0)<=15,"Cumple","No cumple")),"") | AB9: =IFERROR(IF(OR(O9="",R9=""),"",IF(IF(ISNUMBER(R9),MOD(R9,1),TIMEVALUE(R9))>=IF(ISNUMBER(O9),MOD(O9,1),TIMEVALUE(O9)),(IF(ISNUMBER(R9),MOD(R9,1),TIMEVALUE(R9))-IF(ISNUMBER(O9),MOD(O9,1),TIMEVALUE(O9)))*1440,(IF(ISNUMBER(R9),MOD(R9,1),TIMEVALUE(R9))+1-IF(ISNUMBER(O9),MOD(O9,1),TIMEVALUE(O9)))*1440)),"") | AC9: =IFERROR(IF(OR(R9="",S9=""),"",IF(IF(ISNUMBER(S9),MOD(S9,1),TIMEVALUE(S9))>=IF(ISNUMBER(R9),MOD(R9,1),TIMEVALUE(R9)),(IF(ISNUMBER(S9),MOD(S9,1),TIMEVALUE(S9))-IF(ISNUMBER(R9),MOD(R9,1),TIMEVALUE(R9)))*1440,(IF(ISNUMBER(S9),MOD(S9,1),TIMEVALUE(S9))+1-IF(ISNUMBER(R9),MOD(R9,1),TIMEVALUE(R9)))*1440)),"") | AE9: =IFERROR(IF(OR(AC9="",AD9=""),"",AC9-AD9),"") | AF9: =IFERROR(IF(AE9="","",IF(ROUND(AE9,0)>15,"Subestimacion",IF(ROUND(AE9,0)<-15,"Sobrestimacion","Asertivo"))),"") | AP9: =IF(A9="","",A9-WEEKDAY(A9,2)+1) | AQ9: =IF(AO9="","",AO9+6) | AR9: =IF(AO9="","","Semana "&TEXT(AO9,"dd-mm-yyyy")&" al "&TEXT(AP9,"dd-mm-yyyy")) | AS9: =IF(A9="","",TEXT(A9,"mmmm yyyy")) | AT9: =IF(A9="","",TEXT(A9,"dddd")) | AU9: =IF(A9="","","CRR-"&TEXT(A9,"yyyymmdd")&"-"&M9&"-"&TEXT(ROW()-3,"0000")) | AV9: =IF(A9="","",IF(OR(B9="",C9="",E9="",F9="",M9="",N9=""),"Revisar campos obligatorios",IF(AND(P9="Atraso primera hora",Q9=""),"Falta justificación atraso primera hora",IF(AND(Z9="No cumple",AA9=""),"Falta justificación recambio >15 min",IF(AND(ISNUMBER(SEARCH("suspend",N9)),OR(AG9="",AH9="")),"Falta causa/motivo suspensión","OK"))))) | AW9: =IF(N9="","",IF(ISNUMBER(SEARCH("suspend",N9)),IF(AND(AG9="",AH9=""),"Sin causa/motivo registrado",IF(AG9="",AH9,IF(AH9="",AG9,AG9&": "&AH9))),""))
J10: =IF(H10<>"",IFERROR(VLOOKUP(IFERROR(LEFT(H10,FIND("-",H10)-1),H10),'Catalogo MINSAL'!A:E,5,FALSE),""),IF(I10<>"",IFERROR(VLOOKUP(IFERROR(LEFT(I10,FIND("-",I10)-1),I10),'Catalogo MINSAL'!A:E,5,FALSE),""),"")) | P10: =IFERROR(IF(OR(O10="",A10="",M10=""),"",IF(SUMPRODUCT(($A$4:$A$500=A10)*($M$4:$M$500=M10)*($O$4:$O$500<>"")*(MOD($O$4:$O$500,1)<MOD(O10,1)))=0,IF(MOD(O10,1)<=TIME(8,15,0),"Ingreso adecuado primera hora","Atraso primera hora"),"No aplica")),"") | U10: =IFERROR(VLOOKUP(M10,'Horario Pabellones'!$A$4:$D$17,2,FALSE),"") | V10: =IFERROR(VLOOKUP(M10,'Horario Pabellones'!$A$4:$D$17,3,FALSE),"") | W10: =IFERROR(VLOOKUP(M10,'Horario Pabellones'!$A$4:$D$17,4,FALSE),"") | X10: =IFERROR(IF(OR(A10="",M10="",W10=""),"",(((_xludf.AGGREGATE(14,6,MOD($S$4:$S$500,1)/(($A$4:$A$500=A10)*($M$4:$M$500=M10)*($R$4:$R$500<>"")*($S$4:$S$500<>"")),1)-_xludf.AGGREGATE(15,6,MOD($R$4:$R$500,1)/(($A$4:$A$500=A10)*($M$4:$M$500=M10)*($R$4:$R$500<>"")*($S$4:$S$500<>"")),1))*1440)/60)/(W10/60)),"") | Y10: =IFERROR(IF(OR(O10="",A10="",M10=""),"",(IF(ISNUMBER(O10),MOD(O10,1),TIMEVALUE(O10))-LOOKUP(2,1/(($A$4:$A$500=A10)*($M$4:$M$500=M10)*($T$4:$T$500<>"")*($T$4:$T$500<IF(ISNUMBER(O10),MOD(O10,1),TIMEVALUE(O10)))),$T$4:$T$500))*1440),"") | Z10: =IFERROR(IF(Y10="","",IF(ROUND(Y10,0)<=15,"Cumple","No cumple")),"") | AB10: =IFERROR(IF(OR(O10="",R10=""),"",IF(IF(ISNUMBER(R10),MOD(R10,1),TIMEVALUE(R10))>=IF(ISNUMBER(O10),MOD(O10,1),TIMEVALUE(O10)),(IF(ISNUMBER(R10),MOD(R10,1),TIMEVALUE(R10))-IF(ISNUMBER(O10),MOD(O10,1),TIMEVALUE(O10)))*1440,(IF(ISNUMBER(R10),MOD(R10,1),TIMEVALUE(R10))+1-IF(ISNUMBER(O10),MOD(O10,1),TIMEVALUE(O10)))*1440)),"") | AC10: =IFERROR(IF(OR(R10="",S10=""),"",IF(IF(ISNUMBER(S10),MOD(S10,1),TIMEVALUE(S10))>=IF(ISNUMBER(R10),MOD(R10,1),TIMEVALUE(R10)),(IF(ISNUMBER(S10),MOD(S10,1),TIMEVALUE(S10))-IF(ISNUMBER(R10),MOD(R10,1),TIMEVALUE(R10)))*1440,(IF(ISNUMBER(S10),MOD(S10,1),TIMEVALUE(S10))+1-IF(ISNUMBER(R10),MOD(R10,1),TIMEVALUE(R10)))*1440)),"") | AE10: =IFERROR(IF(OR(AC10="",AD10=""),"",AC10-AD10),"") | AF10: =IFERROR(IF(AE10="","",IF(ROUND(AE10,0)>15,"Subestimacion",IF(ROUND(AE10,0)<-15,"Sobrestimacion","Asertivo"))),"") | AP10: =IF(A10="","",A10-WEEKDAY(A10,2)+1) | AQ10: =IF(AO10="","",AO10+6) | AR10: =IF(AO10="","","Semana "&TEXT(AO10,"dd-mm-yyyy")&" al "&TEXT(AP10,"dd-mm-yyyy")) | AS10: =IF(A10="","",TEXT(A10,"mmmm yyyy")) | AT10: =IF(A10="","",TEXT(A10,"dddd")) | AU10: =IF(A10="","","CRR-"&TEXT(A10,"yyyymmdd")&"-"&M10&"-"&TEXT(ROW()-3,"0000")) | AV10: =IF(A10="","",IF(OR(B10="",C10="",E10="",F10="",M10="",N10=""),"Revisar campos obligatorios",IF(AND(P10="Atraso primera hora",Q10=""),"Falta justificación atraso primera hora",IF(AND(Z10="No cumple",AA10=""),"Falta justificación recambio >15 min",IF(AND(ISNUMBER(SEARCH("suspend",N10)),OR(AG10="",AH10="")),"Falta causa/motivo suspensión","OK"))))) | AW10: =IF(N10="","",IF(ISNUMBER(SEARCH("suspend",N10)),IF(AND(AG10="",AH10=""),"Sin causa/motivo registrado",IF(AG10="",AH10,IF(AH10="",AG10,AG10&": "&AH10))),""))
J11: =IF(H11<>"",IFERROR(VLOOKUP(IFERROR(LEFT(H11,FIND("-",H11)-1),H11),'Catalogo MINSAL'!A:E,5,FALSE),""),IF(I11<>"",IFERROR(VLOOKUP(IFERROR(LEFT(I11,FIND("-",I11)-1),I11),'Catalogo MINSAL'!A:E,5,FALSE),""),"")) | P11: =IFERROR(IF(OR(O11="",A11="",M11=""),"",IF(SUMPRODUCT(($A$4:$A$500=A11)*($M$4:$M$500=M11)*($O$4:$O$500<>"")*(MOD($O$4:$O$500,1)<MOD(O11,1)))=0,IF(MOD(O11,1)<=TIME(8,15,0),"Ingreso adecuado primera hora","Atraso primera hora"),"No aplica")),"") | U11: =IFERROR(VLOOKUP(M11,'Horario Pabellones'!$A$4:$D$17,2,FALSE),"") | V11: =IFERROR(VLOOKUP(M11,'Horario Pabellones'!$A$4:$D$17,3,FALSE),"") | W11: =IFERROR(VLOOKUP(M11,'Horario Pabellones'!$A$4:$D$17,4,FALSE),"") | X11: =IFERROR(IF(OR(A11="",M11="",W11=""),"",(((_xludf.AGGREGATE(14,6,MOD($S$4:$S$500,1)/(($A$4:$A$500=A11)*($M$4:$M$500=M11)*($R$4:$R$500<>"")*($S$4:$S$500<>"")),1)-_xludf.AGGREGATE(15,6,MOD($R$4:$R$500,1)/(($A$4:$A$500=A11)*($M$4:$M$500=M11)*($R$4:$R$500<>"")*($S$4:$S$500<>"")),1))*1440)/60)/(W11/60)),"") | Y11: =IFERROR(IF(OR(O11="",A11="",M11=""),"",(IF(ISNUMBER(O11),MOD(O11,1),TIMEVALUE(O11))-LOOKUP(2,1/(($A$4:$A$500=A11)*($M$4:$M$500=M11)*($T$4:$T$500<>"")*($T$4:$T$500<IF(ISNUMBER(O11),MOD(O11,1),TIMEVALUE(O11)))),$T$4:$T$500))*1440),"") | Z11: =IFERROR(IF(Y11="","",IF(ROUND(Y11,0)<=15,"Cumple","No cumple")),"") | AB11: =IFERROR(IF(OR(O11="",R11=""),"",IF(IF(ISNUMBER(R11),MOD(R11,1),TIMEVALUE(R11))>=IF(ISNUMBER(O11),MOD(O11,1),TIMEVALUE(O11)),(IF(ISNUMBER(R11),MOD(R11,1),TIMEVALUE(R11))-IF(ISNUMBER(O11),MOD(O11,1),TIMEVALUE(O11)))*1440,(IF(ISNUMBER(R11),MOD(R11,1),TIMEVALUE(R11))+1-IF(ISNUMBER(O11),MOD(O11,1),TIMEVALUE(O11)))*1440)),"") | AC11: =IFERROR(IF(OR(R11="",S11=""),"",IF(IF(ISNUMBER(S11),MOD(S11,1),TIMEVALUE(S11))>=IF(ISNUMBER(R11),MOD(R11,1),TIMEVALUE(R11)),(IF(ISNUMBER(S11),MOD(S11,1),TIMEVALUE(S11))-IF(ISNUMBER(R11),MOD(R11,1),TIMEVALUE(R11)))*1440,(IF(ISNUMBER(S11),MOD(S11,1),TIMEVALUE(S11))+1-IF(ISNUMBER(R11),MOD(R11,1),TIMEVALUE(R11)))*1440)),"") | AE11: =IFERROR(IF(OR(AC11="",AD11=""),"",AC11-AD11),"") | AF11: =IFERROR(IF(AE11="","",IF(ROUND(AE11,0)>15,"Subestimacion",IF(ROUND(AE11,0)<-15,"Sobrestimacion","Asertivo"))),"") | AP11: =IF(A11="","",A11-WEEKDAY(A11,2)+1) | AQ11: =IF(AO11="","",AO11+6) | AR11: =IF(AO11="","","Semana "&TEXT(AO11,"dd-mm-yyyy")&" al "&TEXT(AP11,"dd-mm-yyyy")) | AS11: =IF(A11="","",TEXT(A11,"mmmm yyyy")) | AT11: =IF(A11="","",TEXT(A11,"dddd")) | AU11: =IF(A11="","","CRR-"&TEXT(A11,"yyyymmdd")&"-"&M11&"-"&TEXT(ROW()-3,"0000")) | AV11: =IF(A11="","",IF(OR(B11="",C11="",E11="",F11="",M11="",N11=""),"Revisar campos obligatorios",IF(AND(P11="Atraso primera hora",Q11=""),"Falta justificación atraso primera hora",IF(AND(Z11="No cumple",AA11=""),"Falta justificación recambio >15 min",IF(AND(ISNUMBER(SEARCH("suspend",N11)),OR(AG11="",AH11="")),"Falta causa/motivo suspensión","OK"))))) | AW11: =IF(N11="","",IF(ISNUMBER(SEARCH("suspend",N11)),IF(AND(AG11="",AH11=""),"Sin causa/motivo registrado",IF(AG11="",AH11,IF(AH11="",AG11,AG11&": "&AH11))),""))
J12: =IF(H12<>"",IFERROR(VLOOKUP(IFERROR(LEFT(H12,FIND("-",H12)-1),H12),'Catalogo MINSAL'!A:E,5,FALSE),""),IF(I12<>"",IFERROR(VLOOKUP(IFERROR(LEFT(I12,FIND("-",I12)-1),I12),'Catalogo MINSAL'!A:E,5,FALSE),""),"")) | P12: =IFERROR(IF(OR(O12="",A12="",M12=""),"",IF(SUMPRODUCT(($A$4:$A$500=A12)*($M$4:$M$500=M12)*($O$4:$O$500<>"")*(MOD($O$4:$O$500,1)<MOD(O12,1)))=0,IF(MOD(O12,1)<=TIME(8,15,0),"Ingreso adecuado primera hora","Atraso primera hora"),"No aplica")),"") | U12: =IFERROR(VLOOKUP(M12,'Horario Pabellones'!$A$4:$D$17,2,FALSE),"") | V12: =IFERROR(VLOOKUP(M12,'Horario Pabellones'!$A$4:$D$17,3,FALSE),"") | W12: =IFERROR(VLOOKUP(M12,'Horario Pabellones'!$A$4:$D$17,4,FALSE),"") | X12: =IFERROR(IF(OR(A12="",M12="",W12=""),"",(((_xludf.AGGREGATE(14,6,MOD($S$4:$S$500,1)/(($A$4:$A$500=A12)*($M$4:$M$500=M12)*($R$4:$R$500<>"")*($S$4:$S$500<>"")),1)-_xludf.AGGREGATE(15,6,MOD($R$4:$R$500,1)/(($A$4:$A$500=A12)*($M$4:$M$500=M12)*($R$4:$R$500<>"")*($S$4:$S$500<>"")),1))*1440)/60)/(W12/60)),"") | Y12: =IFERROR(IF(OR(O12="",A12="",M12=""),"",(IF(ISNUMBER(O12),MOD(O12,1),TIMEVALUE(O12))-LOOKUP(2,1/(($A$4:$A$500=A12)*($M$4:$M$500=M12)*($T$4:$T$500<>"")*($T$4:$T$500<IF(ISNUMBER(O12),MOD(O12,1),TIMEVALUE(O12)))),$T$4:$T$500))*1440),"") | Z12: =IFERROR(IF(Y12="","",IF(ROUND(Y12,0)<=15,"Cumple","No cumple")),"") | AB12: =IFERROR(IF(OR(O12="",R12=""),"",IF(IF(ISNUMBER(R12),MOD(R12,1),TIMEVALUE(R12))>=IF(ISNUMBER(O12),MOD(O12,1),TIMEVALUE(O12)),(IF(ISNUMBER(R12),MOD(R12,1),TIMEVALUE(R12))-IF(ISNUMBER(O12),MOD(O12,1),TIMEVALUE(O12)))*1440,(IF(ISNUMBER(R12),MOD(R12,1),TIMEVALUE(R12))+1-IF(ISNUMBER(O12),MOD(O12,1),TIMEVALUE(O12)))*1440)),"") | AC12: =IFERROR(IF(OR(R12="",S12=""),"",IF(IF(ISNUMBER(S12),MOD(S12,1),TIMEVALUE(S12))>=IF(ISNUMBER(R12),MOD(R12,1),TIMEVALUE(R12)),(IF(ISNUMBER(S12),MOD(S12,1),TIMEVALUE(S12))-IF(ISNUMBER(R12),MOD(R12,1),TIMEVALUE(R12)))*1440,(IF(ISNUMBER(S12),MOD(S12,1),TIMEVALUE(S12))+1-IF(ISNUMBER(R12),MOD(R12,1),TIMEVALUE(R12)))*1440)),"") | AE12: =IFERROR(IF(OR(AC12="",AD12=""),"",AC12-AD12),"") | AF12: =IFERROR(IF(AE12="","",IF(ROUND(AE12,0)>15,"Subestimacion",IF(ROUND(AE12,0)<-15,"Sobrestimacion","Asertivo"))),"") | AP12: =IF(A12="","",A12-WEEKDAY(A12,2)+1) | AQ12: =IF(AO12="","",AO12+6) | AR12: =IF(AO12="","","Semana "&TEXT(AO12,"dd-mm-yyyy")&" al "&TEXT(AP12,"dd-mm-yyyy")) | AS12: =IF(A12="","",TEXT(A12,"mmmm yyyy")) | AT12: =IF(A12="","",TEXT(A12,"dddd")) | AU12: =IF(A12="","","CRR-"&TEXT(A12,"yyyymmdd")&"-"&M12&"-"&TEXT(ROW()-3,"0000")) | AV12: =IF(A12="","",IF(OR(B12="",C12="",E12="",F12="",M12="",N12=""),"Revisar campos obligatorios",IF(AND(P12="Atraso primera hora",Q12=""),"Falta justificación atraso primera hora",IF(AND(Z12="No cumple",AA12=""),"Falta justificación recambio >15 min",IF(AND(ISNUMBER(SEARCH("suspend",N12)),OR(AG12="",AH12="")),"Falta causa/motivo suspensión","OK"))))) | AW12: =IF(N12="","",IF(ISNUMBER(SEARCH("suspend",N12)),IF(AND(AG12="",AH12=""),"Sin causa/motivo registrado",IF(AG12="",AH12,IF(AH12="",AG12,AG12&": "&AH12))),""))
J13: =IF(H13<>"",IFERROR(VLOOKUP(IFERROR(LEFT(H13,FIND("-",H13)-1),H13),'Catalogo MINSAL'!A:E,5,FALSE),""),IF(I13<>"",IFERROR(VLOOKUP(IFERROR(LEFT(I13,FIND("-",I13)-1),I13),'Catalogo MINSAL'!A:E,5,FALSE),""),"")) | P13: =IFERROR(IF(OR(O13="",A13="",M13=""),"",IF(SUMPRODUCT(($A$4:$A$500=A13)*($M$4:$M$500=M13)*($O$4:$O$500<>"")*(MOD($O$4:$O$500,1)<MOD(O13,1)))=0,IF(MOD(O13,1)<=TIME(8,15,0),"Ingreso adecuado primera hora","Atraso primera hora"),"No aplica")),"") | U13: =IFERROR(VLOOKUP(M13,'Horario Pabellones'!$A$4:$D$17,2,FALSE),"") | V13: =IFERROR(VLOOKUP(M13,'Horario Pabellones'!$A$4:$D$17,3,FALSE),"") | W13: =IFERROR(VLOOKUP(M13,'Horario Pabellones'!$A$4:$D$17,4,FALSE),"") | X13: =IFERROR(IF(OR(A13="",M13="",W13=""),"",(((_xludf.AGGREGATE(14,6,MOD($S$4:$S$500,1)/(($A$4:$A$500=A13)*($M$4:$M$500=M13)*($R$4:$R$500<>"")*($S$4:$S$500<>"")),1)-_xludf.AGGREGATE(15,6,MOD($R$4:$R$500,1)/(($A$4:$A$500=A13)*($M$4:$M$500=M13)*($R$4:$R$500<>"")*($S$4:$S$500<>"")),1))*1440)/60)/(W13/60)),"") | Y13: =IFERROR(IF(OR(O13="",A13="",M13=""),"",(IF(ISNUMBER(O13),MOD(O13,1),TIMEVALUE(O13))-LOOKUP(2,1/(($A$4:$A$500=A13)*($M$4:$M$500=M13)*($T$4:$T$500<>"")*($T$4:$T$500<IF(ISNUMBER(O13),MOD(O13,1),TIMEVALUE(O13)))),$T$4:$T$500))*1440),"") | Z13: =IFERROR(IF(Y13="","",IF(ROUND(Y13,0)<=15,"Cumple","No cumple")),"") | AB13: =IFERROR(IF(OR(O13="",R13=""),"",IF(IF(ISNUMBER(R13),MOD(R13,1),TIMEVALUE(R13))>=IF(ISNUMBER(O13),MOD(O13,1),TIMEVALUE(O13)),(IF(ISNUMBER(R13),MOD(R13,1),TIMEVALUE(R13))-IF(ISNUMBER(O13),MOD(O13,1),TIMEVALUE(O13)))*1440,(IF(ISNUMBER(R13),MOD(R13,1),TIMEVALUE(R13))+1-IF(ISNUMBER(O13),MOD(O13,1),TIMEVALUE(O13)))*1440)),"") | AC13: =IFERROR(IF(OR(R13="",S13=""),"",IF(IF(ISNUMBER(S13),MOD(S13,1),TIMEVALUE(S13))>=IF(ISNUMBER(R13),MOD(R13,1),TIMEVALUE(R13)),(IF(ISNUMBER(S13),MOD(S13,1),TIMEVALUE(S13))-IF(ISNUMBER(R13),MOD(R13,1),TIMEVALUE(R13)))*1440,(IF(ISNUMBER(S13),MOD(S13,1),TIMEVALUE(S13))+1-IF(ISNUMBER(R13),MOD(R13,1),TIMEVALUE(R13)))*1440)),"") | AE13: =IFERROR(IF(OR(AC13="",AD13=""),"",AC13-AD13),"") | AF13: =IFERROR(IF(AE13="","",IF(ROUND(AE13,0)>15,"Subestimacion",IF(ROUND(AE13,0)<-15,"Sobrestimacion","Asertivo"))),"") | AP13: =IF(A13="","",A13-WEEKDAY(A13,2)+1) | AQ13: =IF(AO13="","",AO13+6) | AR13: =IF(AO13="","","Semana "&TEXT(AO13,"dd-mm-yyyy")&" al "&TEXT(AP13,"dd-mm-yyyy")) | AS13: =IF(A13="","",TEXT(A13,"mmmm yyyy")) | AT13: =IF(A13="","",TEXT(A13,"dddd")) | AU13: =IF(A13="","","CRR-"&TEXT(A13,"yyyymmdd")&"-"&M13&"-"&TEXT(ROW()-3,"0000")) | AV13: =IF(A13="","",IF(OR(B13="",C13="",E13="",F13="",M13="",N13=""),"Revisar campos obligatorios",IF(AND(P13="Atraso primera hora",Q13=""),"Falta justificación atraso primera hora",IF(AND(Z13="No cumple",AA13=""),"Falta justificación recambio >15 min",IF(AND(ISNUMBER(SEARCH("suspend",N13)),OR(AG13="",AH13="")),"Falta causa/motivo suspensión","OK"))))) | AW13: =IF(N13="","",IF(ISNUMBER(SEARCH("suspend",N13)),IF(AND(AG13="",AH13=""),"Sin causa/motivo registrado",IF(AG13="",AH13,IF(AH13="",AG13,AG13&": "&AH13))),""))
A14: 46167 | B14: DIEGO ANDRES | C14: GONZALEZ | D14: 16a 0m 25d | E14: FRACTURA O PSEUDOARTROSIS ESCAFOIDES, TRAT. QUIR. CUALQ. TECN. | F14: SERVICIO DE TRAUMATOLOGIA | H14: 2104081-5 | J14: =IF(H14<>"",IFERROR(VLOOKUP(IFERROR(LEFT(H14,FIND("-",H14)-1),H14),'Catalogo MINSAL'!A:E,5,FALSE),""),IF(I14<>"",IFERROR(VLOOKUP(IFERROR(LEFT(I14,FIND("-",I14)-1),I14),'Catalogo MINSAL'!A:E,5,FALSE),""),"")) | K14: ALVARO RIDERELLI SANCHEZ | L14: Dr. Alexis Arredondo Torrales | M14: Quirofano 11 | N14: Atendido | O14: 0.36111111 | P14: =IFERROR(IF(OR(O14="",A14="",M14=""),"",IF(SUMPRODUCT(($A$4:$A$500=A14)*($M$4:$M$500=M14)*($O$4:$O$500<>"")*(MOD($O$4:$O$500,1)<MOD(O14,1)))=0,IF(MOD(O14,1)<=TIME(8,15,0),"Ingreso adecuado primera hora","Atraso primera hora"),"No aplica")),"") | R14: 0.38194444 | S14: 0.41666667 | T14: 0.42361111 | U14: =IFERROR(VLOOKUP(M14,'Horario Pabellones'!$A$4:$D$17,2,FALSE),"") | V14: =IFERROR(VLOOKUP(M14,'Horario Pabellones'!$A$4:$D$17,3,FALSE),"") | W14: =IFERROR(VLOOKUP(M14,'Horario Pabellones'!$A$4:$D$17,4,FALSE),"") | X14: =IFERROR(IF(OR(A14="",M14="",W14=""),"",(((_xludf.AGGREGATE(14,6,MOD($S$4:$S$500,1)/(($A$4:$A$500=A14)*($M$4:$M$500=M14)*($R$4:$R$500<>"")*($S$4:$S$500<>"")),1)-_xludf.AGGREGATE(15,6,MOD($R$4:$R$500,1)/(($A$4:$A$500=A14)*($M$4:$M$500=M14)*($R$4:$R$500<>"")*($S$4:$S$500<>"")),1))*1440)/60)/(W14/60)),"") | Y14: =IFERROR(IF(OR(O14="",A14="",M14=""),"",(IF(ISNUMBER(O14),MOD(O14,1),TIMEVALUE(O14))-LOOKUP(2,1/(($A$4:$A$500=A14)*($M$4:$M$500=M14)*($T$4:$T$500<>"")*($T$4:$T$500<IF(ISNUMBER(O14),MOD(O14,1),TIMEVALUE(O14)))),$T$4:$T$500))*1440),"") | Z14: =IFERROR(IF(Y14="","",IF(ROUND(Y14,0)<=15,"Cumple","No cumple")),"") | AB14: =IFERROR(IF(OR(O14="",R14=""),"",IF(IF(ISNUMBER(R14),MOD(R14,1),TIMEVALUE(R14))>=IF(ISNUMBER(O14),MOD(O14,1),TIMEVALUE(O14)),(IF(ISNUMBER(R14),MOD(R14,1),TIMEVALUE(R14))-IF(ISNUMBER(O14),MOD(O14,1),TIMEVALUE(O14)))*1440,(IF(ISNUMBER(R14),MOD(R14,1),TIMEVALUE(R14))+1-IF(ISNUMBER(O14),MOD(O14,1),TIMEVALUE(O14)))*1440)),"") | AC14: =IFERROR(IF(OR(R14="",S14=""),"",IF(IF(ISNUMBER(S14),MOD(S14,1),TIMEVALUE(S14))>=IF(ISNUMBER(R14),MOD(R14,1),TIMEVALUE(R14)),(IF(ISNUMBER(S14),MOD(S14,1),TIMEVALUE(S14))-IF(ISNUMBER(R14),MOD(R14,1),TIMEVALUE(R14)))*1440,(IF(ISNUMBER(S14),MOD(S14,1),TIMEVALUE(S14))+1-IF(ISNUMBER(R14),MOD(R14,1),TIMEVALUE(R14)))*1440)),"") | AD14: 90 | AE14: =IFERROR(IF(OR(AC14="",AD14=""),"",AC14-AD14),"") | AF14: =IFERROR(IF(AE14="","",IF(ROUND(AE14,0)>15,"Subestimacion",IF(ROUND(AE14,0)<-15,"Sobrestimacion","Asertivo"))),"") | AG14: Sin Suspensión | AM14: I0001187219 | AP14: =IF(A14="","",A14-WEEKDAY(A14,2)+1) | AQ14: =IF(AO14="","",AO14+6) | AR14: =IF(AO14="","","Semana "&TEXT(AO14,"dd-mm-yyyy")&" al "&TEXT(AP14,"dd-mm-yyyy")) | AS14: =IF(A14="","",TEXT(A14,"mmmm yyyy")) | AT14: =IF(A14="","",TEXT(A14,"dddd")) | AU14: =IF(A14="","","CRR-"&TEXT(A14,"yyyymmdd")&"-"&M14&"-"&TEXT(ROW()-3,"0000")) | AV14: =IF(A14="","",IF(OR(B14="",C14="",E14="",F14="",M14="",N14=""),"Revisar campos obligatorios",IF(AND(P14="Atraso primera hora",Q14=""),"Falta justificación atraso primera hora",IF(AND(Z14="No cumple",AA14=""),"Falta justificación recambio >15 min",IF(AND(ISNUMBER(SEARCH("suspend",N14)),OR(AG14="",AH14="")),"Falta causa/motivo suspensión","OK"))))) | AW14: =IF(N14="","",IF(ISNUMBER(SEARCH("suspend",N14)),IF(AND(AG14="",AH14=""),"Sin causa/motivo registrado",IF(AG14="",AH14,IF(AH14="",AG14,AG14&": "&AH14))),""))
A15: 46167 | B15: MÓNICA DEL CARMEN | C15: ROJAS | D15: 57a 11m 0d | E15: OSTEOSINTESIS RADIO, (CUALQUIER TECNICA) | F15: SERVICIO DE TRAUMATOLOGIA | H15: 2104085-6 | J15: =IF(H15<>"",IFERROR(VLOOKUP(IFERROR(LEFT(H15,FIND("-",H15)-1),H15),'Catalogo MINSAL'!A:E,5,FALSE),""),IF(I15<>"",IFERROR(VLOOKUP(IFERROR(LEFT(I15,FIND("-",I15)-1),I15),'Catalogo MINSAL'!A:E,5,FALSE),""),"")) | K15: ALVARO RIDERELLI SANCHEZ | L15: Dr. Alexis Arredondo Torrales | M15: Quirofano 11 | N15: Atendido | O15: 0.4375 | P15: =IFERROR(IF(OR(O15="",A15="",M15=""),"",IF(SUMPRODUCT(($A$4:$A$500=A15)*($M$4:$M$500=M15)*($O$4:$O$500<>"")*(MOD($O$4:$O$500,1)<MOD(O15,1)))=0,IF(MOD(O15,1)<=TIME(8,15,0),"Ingreso adecuado primera hora","Atraso primera hora"),"No aplica")),"") | R15: 0.46666667 | S15: 0.53472222 | T15: 0.54861111 | U15: =IFERROR(VLOOKUP(M15,'Horario Pabellones'!$A$4:$D$17,2,FALSE),"") | V15: =IFERROR(VLOOKUP(M15,'Horario Pabellones'!$A$4:$D$17,3,FALSE),"") | W15: =IFERROR(VLOOKUP(M15,'Horario Pabellones'!$A$4:$D$17,4,FALSE),"") | X15: =IFERROR(IF(OR(A15="",M15="",W15=""),"",(((_xludf.AGGREGATE(14,6,MOD($S$4:$S$500,1)/(($A$4:$A$500=A15)*($M$4:$M$500=M15)*($R$4:$R$500<>"")*($S$4:$S$500<>"")),1)-_xludf.AGGREGATE(15,6,MOD($R$4:$R$500,1)/(($A$4:$A$500=A15)*($M$4:$M$500=M15)*($R$4:$R$500<>"")*($S$4:$S$500<>"")),1))*1440)/60)/(W15/60)),"") | Y15: =IFERROR(IF(OR(O15="",A15="",M15=""),"",(IF(ISNUMBER(O15),MOD(O15,1),TIMEVALUE(O15))-LOOKUP(2,1/(($A$4:$A$500=A15)*($M$4:$M$500=M15)*($T$4:$T$500<>"")*($T$4:$T$500<IF(ISNUMBER(O15),MOD(O15,1),TIMEVALUE(O15)))),$T$4:$T$500))*1440),"") | Z15: =IFERROR(IF(Y15="","",IF(ROUND(Y15,0)<=15,"Cumple","No cumple")),"") | AB15: =IFERROR(IF(OR(O15="",R15=""),"",IF(IF(ISNUMBER(R15),MOD(R15,1),TIMEVALUE(R15))>=IF(ISNUMBER(O15),MOD(O15,1),TIMEVALUE(O15)),(IF(ISNUMBER(R15),MOD(R15,1),TIMEVALUE(R15))-IF(ISNUMBER(O15),MOD(O15,1),TIMEVALUE(O15)))*1440,(IF(ISNUMBER(R15),MOD(R15,1),TIMEVALUE(R15))+1-IF(ISNUMBER(O15),MOD(O15,1),TIMEVALUE(O15)))*1440)),"") | AC15: =IFERROR(IF(OR(R15="",S15=""),"",IF(IF(ISNUMBER(S15),MOD(S15,1),TIMEVALUE(S15))>=IF(ISNUMBER(R15),MOD(R15,1),TIMEVALUE(R15)),(IF(ISNUMBER(S15),MOD(S15,1),TIMEVALUE(S15))-IF(ISNUMBER(R15),MOD(R15,1),TIMEVALUE(R15)))*1440,(IF(ISNUMBER(S15),MOD(S15,1),TIMEVALUE(S15))+1-IF(ISNUMBER(R15),MOD(R15,1),TIMEVALUE(R15)))*1440)),"") | AD15: 60 | AE15: =IFERROR(IF(OR(AC15="",AD15=""),"",AC15-AD15),"") | AF15: =IFERROR(IF(AE15="","",IF(ROUND(AE15,0)>15,"Subestimacion",IF(ROUND(AE15,0)<-15,"Sobrestimacion","Asertivo"))),"") | AG15: Sin Suspensión | AM15: I0001187220 | AP15: =IF(A15="","",A15-WEEKDAY(A15,2)+1) | AQ15: =IF(AO15="","",AO15+6) | AR15: =IF(AO15="","","Semana "&TEXT(AO15,"dd-mm-yyyy")&" al "&TEXT(AP15,"dd-mm-yyyy")) | AS15: =IF(A15="","",TEXT(A15,"mmmm yyyy")) | AT15: =IF(A15="","",TEXT(A15,"dddd")) | AU15: =IF(A15="","","CRR-"&TEXT(A15,"yyyymmdd")&"-"&M15&"-"&TEXT(ROW()-3,"0000")) | AV15: =IF(A15="","",IF(OR(B15="",C15="",E15="",F15="",M15="",N15=""),"Revisar campos obligatorios",IF(AND(P15="Atraso primera hora",Q15=""),"Falta justificación atraso primera hora",IF(AND(Z15="No cumple",AA15=""),"Falta justificación recambio >15 min",IF(AND(ISNUMBER(SEARCH("suspend",N15)),OR(AG15="",AH15="")),"Falta causa/motivo suspensión","OK"))))) | AW15: =IF(N15="","",IF(ISNUMBER(SEARCH("suspend",N15)),IF(AND(AG15="",AH15=""),"Sin causa/motivo registrado",IF(AG15="",AH15,IF(AH15="",AG15,AG15&": "&AH15))),""))
A16: 46167 | B16: JOSÉ JAIME | C16: BARRIENTOS | D16: 64a 11m 14d | E16: OSTEOSINTESIS METACARPIANAS O DE FALANGES, CUALQUIER TECNICA | F16: SERVICIO DE TRAUMATOLOGIA | H16: 2104099-4 | J16: =IF(H16<>"",IFERROR(VLOOKUP(IFERROR(LEFT(H16,FIND("-",H16)-1),H16),'Catalogo MINSAL'!A:E,5,FALSE),""),IF(I16<>"",IFERROR(VLOOKUP(IFERROR(LEFT(I16,FIND("-",I16)-1),I16),'Catalogo MINSAL'!A:E,5,FALSE),""),"")) | K16: ALVARO RIDERELLI SANCHEZ | L16: Dr. Alexis Arredondo Torrales | M16: Quirofano 11 | N16: Atendido | O16: 0.57638889 | P16: =IFERROR(IF(OR(O16="",A16="",M16=""),"",IF(SUMPRODUCT(($A$4:$A$500=A16)*($M$4:$M$500=M16)*($O$4:$O$500<>"")*(MOD($O$4:$O$500,1)<MOD(O16,1)))=0,IF(MOD(O16,1)<=TIME(8,15,0),"Ingreso adecuado primera hora","Atraso primera hora"),"No aplica")),"") | R16: 0.60416667 | S16: 0.66666667 | T16: 0.67013889 | U16: =IFERROR(VLOOKUP(M16,'Horario Pabellones'!$A$4:$D$17,2,FALSE),"") | V16: =IFERROR(VLOOKUP(M16,'Horario Pabellones'!$A$4:$D$17,3,FALSE),"") | W16: =IFERROR(VLOOKUP(M16,'Horario Pabellones'!$A$4:$D$17,4,FALSE),"") | X16: =IFERROR(IF(OR(A16="",M16="",W16=""),"",(((_xludf.AGGREGATE(14,6,MOD($S$4:$S$500,1)/(($A$4:$A$500=A16)*($M$4:$M$500=M16)*($R$4:$R$500<>"")*($S$4:$S$500<>"")),1)-_xludf.AGGREGATE(15,6,MOD($R$4:$R$500,1)/(($A$4:$A$500=A16)*($M$4:$M$500=M16)*($R$4:$R$500<>"")*($S$4:$S$500<>"")),1))*1440)/60)/(W16/60)),"") | Y16: =IFERROR(IF(OR(O16="",A16="",M16=""),"",(IF(ISNUMBER(O16),MOD(O16,1),TIMEVALUE(O16))-LOOKUP(2,1/(($A$4:$A$500=A16)*($M$4:$M$500=M16)*($T$4:$T$500<>"")*($T$4:$T$500<IF(ISNUMBER(O16),MOD(O16,1),TIMEVALUE(O16)))),$T$4:$T$500))*1440),"") | Z16: =IFERROR(IF(Y16="","",IF(ROUND(Y16,0)<=15,"Cumple","No cumple")),"") | AB16: =IFERROR(IF(OR(O16="",R16=""),"",IF(IF(ISNUMBER(R16),MOD(R16,1),TIMEVALUE(R16))>=IF(ISNUMBER(O16),MOD(O16,1),TIMEVALUE(O16)),(IF(ISNUMBER(R16),MOD(R16,1),TIMEVALUE(R16))-IF(ISNUMBER(O16),MOD(O16,1),TIMEVALUE(O16)))*1440,(IF(ISNUMBER(R16),MOD(R16,1),TIMEVALUE(R16))+1-IF(ISNUMBER(O16),MOD(O16,1),TIMEVALUE(O16)))*1440)),"") | AC16: =IFERROR(IF(OR(R16="",S16=""),"",IF(IF(ISNUMBER(S16),MOD(S16,1),TIMEVALUE(S16))>=IF(ISNUMBER(R16),MOD(R16,1),TIMEVALUE(R16)),(IF(ISNUMBER(S16),MOD(S16,1),TIMEVALUE(S16))-IF(ISNUMBER(R16),MOD(R16,1),TIMEVALUE(R16)))*1440,(IF(ISNUMBER(S16),MOD(S16,1),TIMEVALUE(S16))+1-IF(ISNUMBER(R16),MOD(R16,1),TIMEVALUE(R16)))*1440)),"") | AD16: 90 | AE16: =IFERROR(IF(OR(AC16="",AD16=""),"",AC16-AD16),"") | AF16: =IFERROR(IF(AE16="","",IF(ROUND(AE16,0)>15,"Subestimacion",IF(ROUND(AE16,0)<-15,"Sobrestimacion","Asertivo"))),"") | AG16: Sin Suspensión | AM16: I0001187212 | AP16: =IF(A16="","",A16-WEEKDAY(A16,2)+1) | AQ16: =IF(AO16="","",AO16+6) | AR16: =IF(AO16="","","Semana "&TEXT(AO16,"dd-mm-yyyy")&" al "&TEXT(AP16,"dd-mm-yyyy")) | AS16: =IF(A16="","",TEXT(A16,"mmmm yyyy")) | AT16: =IF(A16="","",TEXT(A16,"dddd")) | AU16: =IF(A16="","","CRR-"&TEXT(A16,"yyyymmdd")&"-"&M16&"-"&TEXT(ROW()-3,"0000")) | AV16: =IF(A16="","",IF(OR(B16="",C16="",E16="",F16="",M16="",N16=""),"Revisar campos obligatorios",IF(AND(P16="Atraso primera hora",Q16=""),"Falta justificación atraso primera hora",IF(AND(Z16="No cumple",AA16=""),"Falta justificación recambio >15 min",IF(AND(ISNUMBER(SEARCH("suspend",N16)),OR(AG16="",AH16="")),"Falta causa/motivo suspensión","OK"))))) | AW16: =IF(N16="","",IF(ISNUMBER(SEARCH("suspend",N16)),IF(AND(AG16="",AH16=""),"Sin causa/motivo registrado",IF(AG16="",AH16,IF(AH16="",AG16,AG16&": "&AH16))),""))
A17: 46167 | B17: MARÍA ERCILIA | C17: MOLINA | D17: 72a 4m 15d | E17: RETIRO DE TORNILLOS, CLAVOS, AGUJAS DE OSTEOSINTESIS O SIMILARES | F17: SERVICIO DE TRAUMATOLOGIA | H17: 2106003-5 | J17: =IF(H17<>"",IFERROR(VLOOKUP(IFERROR(LEFT(H17,FIND("-",H17)-1),H17),'Catalogo MINSAL'!A:E,5,FALSE),""),IF(I17<>"",IFERROR(VLOOKUP(IFERROR(LEFT(I17,FIND("-",I17)-1),I17),'Catalogo MINSAL'!A:E,5,FALSE),""),"")) | K17: ALVARO RIDERELLI SANCHEZ | L17: Dr. Alexis Arredondo Torrales | M17: Quirofano 11 | N17: Atendido | O17: 0.70833333 | P17: =IFERROR(IF(OR(O17="",A17="",M17=""),"",IF(SUMPRODUCT(($A$4:$A$500=A17)*($M$4:$M$500=M17)*($O$4:$O$500<>"")*(MOD($O$4:$O$500,1)<MOD(O17,1)))=0,IF(MOD(O17,1)<=TIME(8,15,0),"Ingreso adecuado primera hora","Atraso primera hora"),"No aplica")),"") | R17: 0.72916667 | S17: 0.77083333 | T17: 0.77777778 | U17: =IFERROR(VLOOKUP(M17,'Horario Pabellones'!$A$4:$D$17,2,FALSE),"") | V17: =IFERROR(VLOOKUP(M17,'Horario Pabellones'!$A$4:$D$17,3,FALSE),"") | W17: =IFERROR(VLOOKUP(M17,'Horario Pabellones'!$A$4:$D$17,4,FALSE),"") | X17: =IFERROR(IF(OR(A17="",M17="",W17=""),"",(((_xludf.AGGREGATE(14,6,MOD($S$4:$S$500,1)/(($A$4:$A$500=A17)*($M$4:$M$500=M17)*($R$4:$R$500<>"")*($S$4:$S$500<>"")),1)-_xludf.AGGREGATE(15,6,MOD($R$4:$R$500,1)/(($A$4:$A$500=A17)*($M$4:$M$500=M17)*($R$4:$R$500<>"")*($S$4:$S$500<>"")),1))*1440)/60)/(W17/60)),"") | Y17: =IFERROR(IF(OR(O17="",A17="",M17=""),"",(IF(ISNUMBER(O17),MOD(O17,1),TIMEVALUE(O17))-LOOKUP(2,1/(($A$4:$A$500=A17)*($M$4:$M$500=M17)*($T$4:$T$500<>"")*($T$4:$T$500<IF(ISNUMBER(O17),MOD(O17,1),TIMEVALUE(O17)))),$T$4:$T$500))*1440),"") | Z17: =IFERROR(IF(Y17="","",IF(ROUND(Y17,0)<=15,"Cumple","No cumple")),"") | AB17: =IFERROR(IF(OR(O17="",R17=""),"",IF(IF(ISNUMBER(R17),MOD(R17,1),TIMEVALUE(R17))>=IF(ISNUMBER(O17),MOD(O17,1),TIMEVALUE(O17)),(IF(ISNUMBER(R17),MOD(R17,1),TIMEVALUE(R17))-IF(ISNUMBER(O17),MOD(O17,1),TIMEVALUE(O17)))*1440,(IF(ISNUMBER(R17),MOD(R17,1),TIMEVALUE(R17))+1-IF(ISNUMBER(O17),MOD(O17,1),TIMEVALUE(O17)))*1440)),"") | AC17: =IFERROR(IF(OR(R17="",S17=""),"",IF(IF(ISNUMBER(S17),MOD(S17,1),TIMEVALUE(S17))>=IF(ISNUMBER(R17),MOD(R17,1),TIMEVALUE(R17)),(IF(ISNUMBER(S17),MOD(S17,1),TIMEVALUE(S17))-IF(ISNUMBER(R17),MOD(R17,1),TIMEVALUE(R17)))*1440,(IF(ISNUMBER(S17),MOD(S17,1),TIMEVALUE(S17))+1-IF(ISNUMBER(R17),MOD(R17,1),TIMEVALUE(R17)))*1440)),"") | AD17: 60 | AE17: =IFERROR(IF(OR(AC17="",AD17=""),"",AC17-AD17),"") | AF17: =IFERROR(IF(AE17="","",IF(ROUND(AE17,0)>15,"Subestimacion",IF(ROUND(AE17,0)<-15,"Sobrestimacion","Asertivo"))),"") | AG17: Sin Suspensión | AM17: I0001187223 | AP17: =IF(A17="","",A17-WEEKDAY(A17,2)+1) | AQ17: =IF(AO17="","",AO17+6) | AR17: =IF(AO17="","","Semana "&TEXT(AO17,"dd-mm-yyyy")&" al "&TEXT(AP17,"dd-mm-yyyy")) | AS17: =IF(A17="","",TEXT(A17,"mmmm yyyy")) | AT17: =IF(A17="","",TEXT(A17,"dddd")) | AU17: =IF(A17="","","CRR-"&TEXT(A17,"yyyymmdd")&"-"&M17&"-"&TEXT(ROW()-3,"0000")) | AV17: =IF(A17="","",IF(OR(B17="",C17="",E17="",F17="",M17="",N17=""),"Revisar campos obligatorios",IF(AND(P17="Atraso primera hora",Q17=""),"Falta justificación atraso primera hora",IF(AND(Z17="No cumple",AA17=""),"Falta justificación recambio >15 min",IF(AND(ISNUMBER(SEARCH("suspend",N17)),OR(AG17="",AH17="")),"Falta causa/motivo suspensión","OK"))))) | AW17: =IF(N17="","",IF(ISNUMBER(SEARCH("suspend",N17)),IF(AND(AG17="",AH17=""),"Sin causa/motivo registrado",IF(AG17="",AH17,IF(AH17="",AG17,AG17&": "&AH17))),""))
A18: 46167 | B18: MARTÍN ALFONSO | C18: ASTUDILLO | D18: 22a 0m 0d | E18: OSTEOSINTESIS METACARPIANAS O DE FALANGES, CUALQUIER TECNICA | F18: SERVICIO DE TRAUMATOLOGIA | H18: 2104099-4 | J18: =IF(H18<>"",IFERROR(VLOOKUP(IFERROR(LEFT(H18,FIND("-",H18)-1),H18),'Catalogo MINSAL'!A:E,5,FALSE),""),IF(I18<>"",IFERROR(VLOOKUP(IFERROR(LEFT(I18,FIND("-",I18)-1),I18),'Catalogo MINSAL'!A:E,5,FALSE),""),"")) | L18: Dr. Alexis Arredondo Torrales | M18: Quirofano 11 | N18: Suspendido | P18: =IFERROR(IF(OR(O18="",A18="",M18=""),"",IF(SUMPRODUCT(($A$4:$A$500=A18)*($M$4:$M$500=M18)*($O$4:$O$500<>"")*(MOD($O$4:$O$500,1)<MOD(O18,1)))=0,IF(MOD(O18,1)<=TIME(8,15,0),"Ingreso adecuado primera hora","Atraso primera hora"),"No aplica")),"") | U18: =IFERROR(VLOOKUP(M18,'Horario Pabellones'!$A$4:$D$17,2,FALSE),"") | V18: =IFERROR(VLOOKUP(M18,'Horario Pabellones'!$A$4:$D$17,3,FALSE),"") | W18: =IFERROR(VLOOKUP(M18,'Horario Pabellones'!$A$4:$D$17,4,FALSE),"") | X18: =IFERROR(IF(OR(A18="",M18="",W18=""),"",(((_xludf.AGGREGATE(14,6,MOD($S$4:$S$500,1)/(($A$4:$A$500=A18)*($M$4:$M$500=M18)*($R$4:$R$500<>"")*($S$4:$S$500<>"")),1)-_xludf.AGGREGATE(15,6,MOD($R$4:$R$500,1)/(($A$4:$A$500=A18)*($M$4:$M$500=M18)*($R$4:$R$500<>"")*($S$4:$S$500<>"")),1))*1440)/60)/(W18/60)),"") | Y18: =IFERROR(IF(OR(O18="",A18="",M18=""),"",(IF(ISNUMBER(O18),MOD(O18,1),TIMEVALUE(O18))-LOOKUP(2,1/(($A$4:$A$500=A18)*($M$4:$M$500=M18)*($T$4:$T$500<>"")*($T$4:$T$500<IF(ISNUMBER(O18),MOD(O18,1),TIMEVALUE(O18)))),$T$4:$T$500))*1440),"") | Z18: =IFERROR(IF(Y18="","",IF(ROUND(Y18,0)<=15,"Cumple","No cumple")),"") | AB18: =IFERROR(IF(OR(O18="",R18=""),"",IF(IF(ISNUMBER(R18),MOD(R18,1),TIMEVALUE(R18))>=IF(ISNUMBER(O18),MOD(O18,1),TIMEVALUE(O18)),(IF(ISNUMBER(R18),MOD(R18,1),TIMEVALUE(R18))-IF(ISNUMBER(O18),MOD(O18,1),TIMEVALUE(O18)))*1440,(IF(ISNUMBER(R18),MOD(R18,1),TIMEVALUE(R18))+1-IF(ISNUMBER(O18),MOD(O18,1),TIMEVALUE(O18)))*1440)),"") | AC18: =IFERROR(IF(OR(R18="",S18=""),"",IF(IF(ISNUMBER(S18),MOD(S18,1),TIMEVALUE(S18))>=IF(ISNUMBER(R18),MOD(R18,1),TIMEVALUE(R18)),(IF(ISNUMBER(S18),MOD(S18,1),TIMEVALUE(S18))-IF(ISNUMBER(R18),MOD(R18,1),TIMEVALUE(R18)))*1440,(IF(ISNUMBER(S18),MOD(S18,1),TIMEVALUE(S18))+1-IF(ISNUMBER(R18),MOD(R18,1),TIMEVALUE(R18)))*1440)),"") | AE18: =IFERROR(IF(OR(AC18="",AD18=""),"",AC18-AD18),"") | AF18: =IFERROR(IF(AE18="","",IF(ROUND(AE18,0)>15,"Subestimacion",IF(ROUND(AE18,0)<-15,"Sobrestimacion","Asertivo"))),"") | AG18: No se presenta | AM18: I0001187222 | AP18: =IF(A18="","",A18-WEEKDAY(A18,2)+1) | AQ18: =IF(AO18="","",AO18+6) | AR18: =IF(AO18="","","Semana "&TEXT(AO18,"dd-mm-yyyy")&" al "&TEXT(AP18,"dd-mm-yyyy")) | AS18: =IF(A18="","",TEXT(A18,"mmmm yyyy")) | AT18: =IF(A18="","",TEXT(A18,"dddd")) | AU18: =IF(A18="","","CRR-"&TEXT(A18,"yyyymmdd")&"-"&M18&"-"&TEXT(ROW()-3,"0000")) | AV18: =IF(A18="","",IF(OR(B18="",C18="",E18="",F18="",M18="",N18=""),"Revisar campos obligatorios",IF(AND(P18="Atraso primera hora",Q18=""),"Falta justificación atraso primera hora",IF(AND(Z18="No cumple",AA18=""),"Falta justificación recambio >15 min",IF(AND(ISNUMBER(SEARCH("suspend",N18)),OR(AG18="",AH18="")),"Falta causa/motivo suspensión","OK"))))) | AW18: =IF(N18="","",IF(ISNUMBER(SEARCH("suspend",N18)),IF(AND(AG18="",AH18=""),"Sin causa/motivo registrado",IF(AG18="",AH18,IF(AH18="",AG18,AG18&": "&AH18))),""))
A19: 46167 | B19: LÚA AMARA | C19: HERMOSILLA | D19: 3a 10m 12d | E19: MANO DEDOS EN GATILLO, TRAT. QUIR., CUALQUIER NUMERO | F19: SERVICIO DE TRAUMATOLOGIA | H19: 2104093-4 | J19: =IF(H19<>"",IFERROR(VLOOKUP(IFERROR(LEFT(H19,FIND("-",H19)-1),H19),'Catalogo MINSAL'!A:E,5,FALSE),""),IF(I19<>"",IFERROR(VLOOKUP(IFERROR(LEFT(I19,FIND("-",I19)-1),I19),'Catalogo MINSAL'!A:E,5,FALSE),""),"")) | K19: Maximo Sepulveda Pizarro | L19: Dr. Isaías Sulantay Oyanedel | M19: Quirofano 13 | N19: Realizado | O19: 0.34236111 | P19: =IFERROR(IF(OR(O19="",A19="",M19=""),"",IF(SUMPRODUCT(($A$4:$A$500=A19)*($M$4:$M$500=M19)*($O$4:$O$500<>"")*(MOD($O$4:$O$500,1)<MOD(O19,1)))=0,IF(MOD(O19,1)<=TIME(8,15,0),"Ingreso adecuado primera hora","Atraso primera hora"),"No aplica")),"") | R19: 0.35833333 | S19: 0.375 | T19: 0.38333333 | U19: =IFERROR(VLOOKUP(M19,'Horario Pabellones'!$A$4:$D$17,2,FALSE),"") | V19: =IFERROR(VLOOKUP(M19,'Horario Pabellones'!$A$4:$D$17,3,FALSE),"") | W19: =IFERROR(VLOOKUP(M19,'Horario Pabellones'!$A$4:$D$17,4,FALSE),"") | X19: =IFERROR(IF(OR(A19="",M19="",W19=""),"",(((_xludf.AGGREGATE(14,6,MOD($S$4:$S$500,1)/(($A$4:$A$500=A19)*($M$4:$M$500=M19)*($R$4:$R$500<>"")*($S$4:$S$500<>"")),1)-_xludf.AGGREGATE(15,6,MOD($R$4:$R$500,1)/(($A$4:$A$500=A19)*($M$4:$M$500=M19)*($R$4:$R$500<>"")*($S$4:$S$500<>"")),1))*1440)/60)/(W19/60)),"") | Y19: =IFERROR(IF(OR(O19="",A19="",M19=""),"",(IF(ISNUMBER(O19),MOD(O19,1),TIMEVALUE(O19))-LOOKUP(2,1/(($A$4:$A$500=A19)*($M$4:$M$500=M19)*($T$4:$T$500<>"")*($T$4:$T$500<IF(ISNUMBER(O19),MOD(O19,1),TIMEVALUE(O19)))),$T$4:$T$500))*1440),"") | Z19: =IFERROR(IF(Y19="","",IF(ROUND(Y19,0)<=15,"Cumple","No cumple")),"") | AB19: =IFERROR(IF(OR(O19="",R19=""),"",IF(IF(ISNUMBER(R19),MOD(R19,1),TIMEVALUE(R19))>=IF(ISNUMBER(O19),MOD(O19,1),TIMEVALUE(O19)),(IF(ISNUMBER(R19),MOD(R19,1),TIMEVALUE(R19))-IF(ISNUMBER(O19),MOD(O19,1),TIMEVALUE(O19)))*1440,(IF(ISNUMBER(R19),MOD(R19,1),TIMEVALUE(R19))+1-IF(ISNUMBER(O19),MOD(O19,1),TIMEVALUE(O19)))*1440)),"") | AC19: =IFERROR(IF(OR(R19="",S19=""),"",IF(IF(ISNUMBER(S19),MOD(S19,1),TIMEVALUE(S19))>=IF(ISNUMBER(R19),MOD(R19,1),TIMEVALUE(R19)),(IF(ISNUMBER(S19),MOD(S19,1),TIMEVALUE(S19))-IF(ISNUMBER(R19),MOD(R19,1),TIMEVALUE(R19)))*1440,(IF(ISNUMBER(S19),MOD(S19,1),TIMEVALUE(S19))+1-IF(ISNUMBER(R19),MOD(R19,1),TIMEVALUE(R19)))*1440)),"") | AD19: 40 | AE19: =IFERROR(IF(OR(AC19="",AD19=""),"",AC19-AD19),"") | AF19: =IFERROR(IF(AE19="","",IF(ROUND(AE19,0)>15,"Subestimacion",IF(ROUND(AE19,0)<-15,"Sobrestimacion","Asertivo"))),"") | AG19: Sin Suspensión | AM19: I0001187195 | AP19: =IF(A19="","",A19-WEEKDAY(A19,2)+1) | AQ19: =IF(AO19="","",AO19+6) | AR19: =IF(AO19="","","Semana "&TEXT(AO19,"dd-mm-yyyy")&" al "&TEXT(AP19,"dd-mm-yyyy")) | AS19: =IF(A19="","",TEXT(A19,"mmmm yyyy")) | AT19: =IF(A19="","",TEXT(A19,"dddd")) | AU19: =IF(A19="","","CRR-"&TEXT(A19,"yyyymmdd")&"-"&M19&"-"&TEXT(ROW()-3,"0000")) | AV19: =IF(A19="","",IF(OR(B19="",C19="",E19="",F19="",M19="",N19=""),"Revisar campos obligatorios",IF(AND(P19="Atraso primera hora",Q19=""),"Falta justificación atraso primera hora",IF(AND(Z19="No cumple",AA19=""),"Falta justificación recambio >15 min",IF(AND(ISNUMBER(SEARCH("suspend",N19)),OR(AG19="",AH19="")),"Falta causa/motivo suspensión","OK"))))) | AW19: =IF(N19="","",IF(ISNUMBER(SEARCH("suspend",N19)),IF(AND(AG19="",AH19=""),"Sin causa/motivo registrado",IF(AG19="",AH19,IF(AH19="",AG19,AG19&": "&AH19))),""))
A20: 46167 | B20: DIEGO ALONSO | C20: MUGA | D20: 10a 8m 4d | E20: SINOVECTOMIAS QUIRURGICAS (PROC. AUT.) CODO O MUÑECA O METACARPOFALANGICAS, C/U | F20: SERVICIO DE TRAUMATOLOGIA | H20: 2104029-5 | J20: =IF(H20<>"",IFERROR(VLOOKUP(IFERROR(LEFT(H20,FIND("-",H20)-1),H20),'Catalogo MINSAL'!A:E,5,FALSE),""),IF(I20<>"",IFERROR(VLOOKUP(IFERROR(LEFT(I20,FIND("-",I20)-1),I20),'Catalogo MINSAL'!A:E,5,FALSE),""),"")) | K20: Maximo Sepulveda Pizarro | L20: Dr. Camilo Garcia | M20: Quirofano 13 | N20: Atendido | O20: 0.39930556 | P20: =IFERROR(IF(OR(O20="",A20="",M20=""),"",IF(SUMPRODUCT(($A$4:$A$500=A20)*($M$4:$M$500=M20)*($O$4:$O$500<>"")*(MOD($O$4:$O$500,1)<MOD(O20,1)))=0,IF(MOD(O20,1)<=TIME(8,15,0),"Ingreso adecuado primera hora","Atraso primera hora"),"No aplica")),"") | R20: 0.42152778 | S20: 0.45833333 | T20: 0.46666667 | U20: =IFERROR(VLOOKUP(M20,'Horario Pabellones'!$A$4:$D$17,2,FALSE),"") | V20: =IFERROR(VLOOKUP(M20,'Horario Pabellones'!$A$4:$D$17,3,FALSE),"") | W20: =IFERROR(VLOOKUP(M20,'Horario Pabellones'!$A$4:$D$17,4,FALSE),"") | X20: =IFERROR(IF(OR(A20="",M20="",W20=""),"",(((_xludf.AGGREGATE(14,6,MOD($S$4:$S$500,1)/(($A$4:$A$500=A20)*($M$4:$M$500=M20)*($R$4:$R$500<>"")*($S$4:$S$500<>"")),1)-_xludf.AGGREGATE(15,6,MOD($R$4:$R$500,1)/(($A$4:$A$500=A20)*($M$4:$M$500=M20)*($R$4:$R$500<>"")*($S$4:$S$500<>"")),1))*1440)/60)/(W20/60)),"") | Y20: =IFERROR(IF(OR(O20="",A20="",M20=""),"",(IF(ISNUMBER(O20),MOD(O20,1),TIMEVALUE(O20))-LOOKUP(2,1/(($A$4:$A$500=A20)*($M$4:$M$500=M20)*($T$4:$T$500<>"")*($T$4:$T$500<IF(ISNUMBER(O20),MOD(O20,1),TIMEVALUE(O20)))),$T$4:$T$500))*1440),"") | Z20: =IFERROR(IF(Y20="","",IF(ROUND(Y20,0)<=15,"Cumple","No cumple")),"") | AB20: =IFERROR(IF(OR(O20="",R20=""),"",IF(IF(ISNUMBER(R20),MOD(R20,1),TIMEVALUE(R20))>=IF(ISNUMBER(O20),MOD(O20,1),TIMEVALUE(O20)),(IF(ISNUMBER(R20),MOD(R20,1),TIMEVALUE(R20))-IF(ISNUMBER(O20),MOD(O20,1),TIMEVALUE(O20)))*1440,(IF(ISNUMBER(R20),MOD(R20,1),TIMEVALUE(R20))+1-IF(ISNUMBER(O20),MOD(O20,1),TIMEVALUE(O20)))*1440)),"") | AC20: =IFERROR(IF(OR(R20="",S20=""),"",IF(IF(ISNUMBER(S20),MOD(S20,1),TIMEVALUE(S20))>=IF(ISNUMBER(R20),MOD(R20,1),TIMEVALUE(R20)),(IF(ISNUMBER(S20),MOD(S20,1),TIMEVALUE(S20))-IF(ISNUMBER(R20),MOD(R20,1),TIMEVALUE(R20)))*1440,(IF(ISNUMBER(S20),MOD(S20,1),TIMEVALUE(S20))+1-IF(ISNUMBER(R20),MOD(R20,1),TIMEVALUE(R20)))*1440)),"") | AD20: 45 | AE20: =IFERROR(IF(OR(AC20="",AD20=""),"",AC20-AD20),"") | AF20: =IFERROR(IF(AE20="","",IF(ROUND(AE20,0)>15,"Subestimacion",IF(ROUND(AE20,0)<-15,"Sobrestimacion","Asertivo"))),"") | AG20: Sin Suspensión | AM20: I0001187199 | AP20: =IF(A20="","",A20-WEEKDAY(A20,2)+1) | AQ20: =IF(AO20="","",AO20+6) | AR20: =IF(AO20="","","Semana "&TEXT(AO20,"dd-mm-yyyy")&" al "&TEXT(AP20,"dd-mm-yyyy")) | AS20: =IF(A20="","",TEXT(A20,"mmmm yyyy")) | AT20: =IF(A20="","",TEXT(A20,"dddd")) | AU20: =IF(A20="","","CRR-"&TEXT(A20,"yyyymmdd")&"-"&M20&"-"&TEXT(ROW()-3,"0000")) | AV20: =IF(A20="","",IF(OR(B20="",C20="",E20="",F20="",M20="",N20=""),"Revisar campos obligatorios",IF(AND(P20="Atraso primera hora",Q20=""),"Falta justificación atraso primera hora",IF(AND(Z20="No cumple",AA20=""),"Falta justificación recambio >15 min",IF(AND(ISNUMBER(SEARCH("suspend",N20)),OR(AG20="",AH20="")),"Falta causa/motivo suspensión","OK"))))) | AW20: =IF(N20="","",IF(ISNUMBER(SEARCH("suspend",N20)),IF(AND(AG20="",AH20=""),"Sin causa/motivo registrado",IF(AG20="",AH20,IF(AH20="",AG20,AG20&": "&AH20))),""))
A21: 46167 | B21: KARL-HERTZ STURRIDGE | C21: DESVALLONS | D21: 11a 4m 1d | E21: RETIRO DE TORNILLOS, CLAVOS, AGUJAS DE OSTEOSINTESIS O SIMILARES | F21: SERVICIO DE TRAUMATOLOGIA | H21: 2106003-5 | J21: =IF(H21<>"",IFERROR(VLOOKUP(IFERROR(LEFT(H21,FIND("-",H21)-1),H21),'Catalogo MINSAL'!A:E,5,FALSE),""),IF(I21<>"",IFERROR(VLOOKUP(IFERROR(LEFT(I21,FIND("-",I21)-1),I21),'Catalogo MINSAL'!A:E,5,FALSE),""),"")) | K21: Maximo Sepulveda Pizarro | L21: Dr. Isaías Sulantay Oyanedel | M21: Quirofano 13 | N21: Atendido | O21: 0.47777778 | P21: =IFERROR(IF(OR(O21="",A21="",M21=""),"",IF(SUMPRODUCT(($A$4:$A$500=A21)*($M$4:$M$500=M21)*($O$4:$O$500<>"")*(MOD($O$4:$O$500,1)<MOD(O21,1)))=0,IF(MOD(O21,1)<=TIME(8,15,0),"Ingreso adecuado primera hora","Atraso primera hora"),"No aplica")),"") | R21: 0.50763889 | S21: 0.55208333 | T21: 0.56597222 | U21: =IFERROR(VLOOKUP(M21,'Horario Pabellones'!$A$4:$D$17,2,FALSE),"") | V21: =IFERROR(VLOOKUP(M21,'Horario Pabellones'!$A$4:$D$17,3,FALSE),"") | W21: =IFERROR(VLOOKUP(M21,'Horario Pabellones'!$A$4:$D$17,4,FALSE),"") | X21: =IFERROR(IF(OR(A21="",M21="",W21=""),"",(((_xludf.AGGREGATE(14,6,MOD($S$4:$S$500,1)/(($A$4:$A$500=A21)*($M$4:$M$500=M21)*($R$4:$R$500<>"")*($S$4:$S$500<>"")),1)-_xludf.AGGREGATE(15,6,MOD($R$4:$R$500,1)/(($A$4:$A$500=A21)*($M$4:$M$500=M21)*($R$4:$R$500<>"")*($S$4:$S$500<>"")),1))*1440)/60)/(W21/60)),"") | Y21: =IFERROR(IF(OR(O21="",A21="",M21=""),"",(IF(ISNUMBER(O21),MOD(O21,1),TIMEVALUE(O21))-LOOKUP(2,1/(($A$4:$A$500=A21)*($M$4:$M$500=M21)*($T$4:$T$500<>"")*($T$4:$T$500<IF(ISNUMBER(O21),MOD(O21,1),TIMEVALUE(O21)))),$T$4:$T$500))*1440),"") | Z21: =IFERROR(IF(Y21="","",IF(ROUND(Y21,0)<=15,"Cumple","No cumple")),"") | AB21: =IFERROR(IF(OR(O21="",R21=""),"",IF(IF(ISNUMBER(R21),MOD(R21,1),TIMEVALUE(R21))>=IF(ISNUMBER(O21),MOD(O21,1),TIMEVALUE(O21)),(IF(ISNUMBER(R21),MOD(R21,1),TIMEVALUE(R21))-IF(ISNUMBER(O21),MOD(O21,1),TIMEVALUE(O21)))*1440,(IF(ISNUMBER(R21),MOD(R21,1),TIMEVALUE(R21))+1-IF(ISNUMBER(O21),MOD(O21,1),TIMEVALUE(O21)))*1440)),"") | AC21: =IFERROR(IF(OR(R21="",S21=""),"",IF(IF(ISNUMBER(S21),MOD(S21,1),TIMEVALUE(S21))>=IF(ISNUMBER(R21),MOD(R21,1),TIMEVALUE(R21)),(IF(ISNUMBER(S21),MOD(S21,1),TIMEVALUE(S21))-IF(ISNUMBER(R21),MOD(R21,1),TIMEVALUE(R21)))*1440,(IF(ISNUMBER(S21),MOD(S21,1),TIMEVALUE(S21))+1-IF(ISNUMBER(R21),MOD(R21,1),TIMEVALUE(R21)))*1440)),"") | AD21: 60 | AE21: =IFERROR(IF(OR(AC21="",AD21=""),"",AC21-AD21),"") | AF21: =IFERROR(IF(AE21="","",IF(ROUND(AE21,0)>15,"Subestimacion",IF(ROUND(AE21,0)<-15,"Sobrestimacion","Asertivo"))),"") | AG21: Sin Suspensión | AM21: I0001187201 | AP21: =IF(A21="","",A21-WEEKDAY(A21,2)+1) | AQ21: =IF(AO21="","",AO21+6) | AR21: =IF(AO21="","","Semana "&TEXT(AO21,"dd-mm-yyyy")&" al "&TEXT(AP21,"dd-mm-yyyy")) | AS21: =IF(A21="","",TEXT(A21,"mmmm yyyy")) | AT21: =IF(A21="","",TEXT(A21,"dddd")) | AU21: =IF(A21="","","CRR-"&TEXT(A21,"yyyymmdd")&"-"&M21&"-"&TEXT(ROW()-3,"0000")) | AV21: =IF(A21="","",IF(OR(B21="",C21="",E21="",F21="",M21="",N21=""),"Revisar campos obligatorios",IF(AND(P21="Atraso primera hora",Q21=""),"Falta justificación atraso primera hora",IF(AND(Z21="No cumple",AA21=""),"Falta justificación recambio >15 min",IF(AND(ISNUMBER(SEARCH("suspend",N21)),OR(AG21="",AH21="")),"Falta causa/motivo suspensión","OK"))))) | AW21: =IF(N21="","",IF(ISNUMBER(SEARCH("suspend",N21)),IF(AND(AG21="",AH21=""),"Sin causa/motivo registrado",IF(AG21="",AH21,IF(AH21="",AG21,AG21&": "&AH21))),""))
A22: 46167 | B22: MATÍAS IGNACIO | C22: MONTENEGRO | D22: 13a 5m 2d | E22: PIE PLANO, TRAT. QUIR. (CUALQUIER TECNICA) | F22: SERVICIO DE TRAUMATOLOGIA | H22: 2104198-5 | J22: =IF(H22<>"",IFERROR(VLOOKUP(IFERROR(LEFT(H22,FIND("-",H22)-1),H22),'Catalogo MINSAL'!A:E,5,FALSE),""),IF(I22<>"",IFERROR(VLOOKUP(IFERROR(LEFT(I22,FIND("-",I22)-1),I22),'Catalogo MINSAL'!A:E,5,FALSE),""),"")) | K22: Maximo Sepulveda Pizarro | L22: Maria Jose Rosen Petersen | M22: Quirofano 13 | N22: Atendido | O22: 0.57986111 | P22: =IFERROR(IF(OR(O22="",A22="",M22=""),"",IF(SUMPRODUCT(($A$4:$A$500=A22)*($M$4:$M$500=M22)*($O$4:$O$500<>"")*(MOD($O$4:$O$500,1)<MOD(O22,1)))=0,IF(MOD(O22,1)<=TIME(8,15,0),"Ingreso adecuado primera hora","Atraso primera hora"),"No aplica")),"") | R22: 0.59722222 | S22: 0.61805556 | T22: 0.63194444 | U22: =IFERROR(VLOOKUP(M22,'Horario Pabellones'!$A$4:$D$17,2,FALSE),"") | V22: =IFERROR(VLOOKUP(M22,'Horario Pabellones'!$A$4:$D$17,3,FALSE),"") | W22: =IFERROR(VLOOKUP(M22,'Horario Pabellones'!$A$4:$D$17,4,FALSE),"") | X22: =IFERROR(IF(OR(A22="",M22="",W22=""),"",(((_xludf.AGGREGATE(14,6,MOD($S$4:$S$500,1)/(($A$4:$A$500=A22)*($M$4:$M$500=M22)*($R$4:$R$500<>"")*($S$4:$S$500<>"")),1)-_xludf.AGGREGATE(15,6,MOD($R$4:$R$500,1)/(($A$4:$A$500=A22)*($M$4:$M$500=M22)*($R$4:$R$500<>"")*($S$4:$S$500<>"")),1))*1440)/60)/(W22/60)),"") | Y22: =IFERROR(IF(OR(O22="",A22="",M22=""),"",(IF(ISNUMBER(O22),MOD(O22,1),TIMEVALUE(O22))-LOOKUP(2,1/(($A$4:$A$500=A22)*($M$4:$M$500=M22)*($T$4:$T$500<>"")*($T$4:$T$500<IF(ISNUMBER(O22),MOD(O22,1),TIMEVALUE(O22)))),$T$4:$T$500))*1440),"") | Z22: =IFERROR(IF(Y22="","",IF(ROUND(Y22,0)<=15,"Cumple","No cumple")),"") | AB22: =IFERROR(IF(OR(O22="",R22=""),"",IF(IF(ISNUMBER(R22),MOD(R22,1),TIMEVALUE(R22))>=IF(ISNUMBER(O22),MOD(O22,1),TIMEVALUE(O22)),(IF(ISNUMBER(R22),MOD(R22,1),TIMEVALUE(R22))-IF(ISNUMBER(O22),MOD(O22,1),TIMEVALUE(O22)))*1440,(IF(ISNUMBER(R22),MOD(R22,1),TIMEVALUE(R22))+1-IF(ISNUMBER(O22),MOD(O22,1),TIMEVALUE(O22)))*1440)),"") | AC22: =IFERROR(IF(OR(R22="",S22=""),"",IF(IF(ISNUMBER(S22),MOD(S22,1),TIMEVALUE(S22))>=IF(ISNUMBER(R22),MOD(R22,1),TIMEVALUE(R22)),(IF(ISNUMBER(S22),MOD(S22,1),TIMEVALUE(S22))-IF(ISNUMBER(R22),MOD(R22,1),TIMEVALUE(R22)))*1440,(IF(ISNUMBER(S22),MOD(S22,1),TIMEVALUE(S22))+1-IF(ISNUMBER(R22),MOD(R22,1),TIMEVALUE(R22)))*1440)),"") | AD22: 45 | AE22: =IFERROR(IF(OR(AC22="",AD22=""),"",AC22-AD22),"") | AF22: =IFERROR(IF(AE22="","",IF(ROUND(AE22,0)>15,"Subestimacion",IF(ROUND(AE22,0)<-15,"Sobrestimacion","Asertivo"))),"") | AG22: Sin Suspensión | AM22: I0001187204 | AP22: =IF(A22="","",A22-WEEKDAY(A22,2)+1) | AQ22: =IF(AO22="","",AO22+6) | AR22: =IF(AO22="","","Semana "&TEXT(AO22,"dd-mm-yyyy")&" al "&TEXT(AP22,"dd-mm-yyyy")) | AS22: =IF(A22="","",TEXT(A22,"mmmm yyyy")) | AT22: =IF(A22="","",TEXT(A22,"dddd")) | AU22: =IF(A22="","","CRR-"&TEXT(A22,"yyyymmdd")&"-"&M22&"-"&TEXT(ROW()-3,"0000")) | AV22: =IF(A22="","",IF(OR(B22="",C22="",E22="",F22="",M22="",N22=""),"Revisar campos obligatorios",IF(AND(P22="Atraso primera hora",Q22=""),"Falta justificación atraso primera hora",IF(AND(Z22="No cumple",AA22=""),"Falta justificación recambio >15 min",IF(AND(ISNUMBER(SEARCH("suspend",N22)),OR(AG22="",AH22="")),"Falta causa/motivo suspensión","OK"))))) | AW22: =IF(N22="","",IF(ISNUMBER(SEARCH("suspend",N22)),IF(AND(AG22="",AH22=""),"Sin causa/motivo registrado",IF(AG22="",AH22,IF(AH22="",AG22,AG22&": "&AH22))),""))
A23: 46167 | B23: MAITE EMILIA | C23: GOMEZ | D23: 11a 9m 14d | E23: HALLUX VALGUS O RIGIDUS, TRAT.QUIR. COMPLETO (CUALQUIER TEC.) | F23: SERVICIO DE TRAUMATOLOGIA | H23: 2104190-5 | J23: =IF(H23<>"",IFERROR(VLOOKUP(IFERROR(LEFT(H23,FIND("-",H23)-1),H23),'Catalogo MINSAL'!A:E,5,FALSE),""),IF(I23<>"",IFERROR(VLOOKUP(IFERROR(LEFT(I23,FIND("-",I23)-1),I23),'Catalogo MINSAL'!A:E,5,FALSE),""),"")) | K23: Maximo Sepulveda Pizarro | L23: Maria Jose Rosen Petersen | M23: Quirofano 13 | N23: Atendido | O23: 0.64930556 | P23: =IFERROR(IF(OR(O23="",A23="",M23=""),"",IF(SUMPRODUCT(($A$4:$A$500=A23)*($M$4:$M$500=M23)*($O$4:$O$500<>"")*(MOD($O$4:$O$500,1)<MOD(O23,1)))=0,IF(MOD(O23,1)<=TIME(8,15,0),"Ingreso adecuado primera hora","Atraso primera hora"),"No aplica")),"") | R23: 0.67430556 | S23: 0.70486111 | T23: 0.71319444 | U23: =IFERROR(VLOOKUP(M23,'Horario Pabellones'!$A$4:$D$17,2,FALSE),"") | V23: =IFERROR(VLOOKUP(M23,'Horario Pabellones'!$A$4:$D$17,3,FALSE),"") | W23: =IFERROR(VLOOKUP(M23,'Horario Pabellones'!$A$4:$D$17,4,FALSE),"") | X23: =IFERROR(IF(OR(A23="",M23="",W23=""),"",(((_xludf.AGGREGATE(14,6,MOD($S$4:$S$500,1)/(($A$4:$A$500=A23)*($M$4:$M$500=M23)*($R$4:$R$500<>"")*($S$4:$S$500<>"")),1)-_xludf.AGGREGATE(15,6,MOD($R$4:$R$500,1)/(($A$4:$A$500=A23)*($M$4:$M$500=M23)*($R$4:$R$500<>"")*($S$4:$S$500<>"")),1))*1440)/60)/(W23/60)),"") | Y23: =IFERROR(IF(OR(O23="",A23="",M23=""),"",(IF(ISNUMBER(O23),MOD(O23,1),TIMEVALUE(O23))-LOOKUP(2,1/(($A$4:$A$500=A23)*($M$4:$M$500=M23)*($T$4:$T$500<>"")*($T$4:$T$500<IF(ISNUMBER(O23),MOD(O23,1),TIMEVALUE(O23)))),$T$4:$T$500))*1440),"") | Z23: =IFERROR(IF(Y23="","",IF(ROUND(Y23,0)<=15,"Cumple","No cumple")),"") | AB23: =IFERROR(IF(OR(O23="",R23=""),"",IF(IF(ISNUMBER(R23),MOD(R23,1),TIMEVALUE(R23))>=IF(ISNUMBER(O23),MOD(O23,1),TIMEVALUE(O23)),(IF(ISNUMBER(R23),MOD(R23,1),TIMEVALUE(R23))-IF(ISNUMBER(O23),MOD(O23,1),TIMEVALUE(O23)))*1440,(IF(ISNUMBER(R23),MOD(R23,1),TIMEVALUE(R23))+1-IF(ISNUMBER(O23),MOD(O23,1),TIMEVALUE(O23)))*1440)),"") | AC23: =IFERROR(IF(OR(R23="",S23=""),"",IF(IF(ISNUMBER(S23),MOD(S23,1),TIMEVALUE(S23))>=IF(ISNUMBER(R23),MOD(R23,1),TIMEVALUE(R23)),(IF(ISNUMBER(S23),MOD(S23,1),TIMEVALUE(S23))-IF(ISNUMBER(R23),MOD(R23,1),TIMEVALUE(R23)))*1440,(IF(ISNUMBER(S23),MOD(S23,1),TIMEVALUE(S23))+1-IF(ISNUMBER(R23),MOD(R23,1),TIMEVALUE(R23)))*1440)),"") | AD23: 45 | AE23: =IFERROR(IF(OR(AC23="",AD23=""),"",AC23-AD23),"") | AF23: =IFERROR(IF(AE23="","",IF(ROUND(AE23,0)>15,"Subestimacion",IF(ROUND(AE23,0)<-15,"Sobrestimacion","Asertivo"))),"") | AG23: Sin Suspensión | AM23: I0001187210 | AP23: =IF(A23="","",A23-WEEKDAY(A23,2)+1) | AQ23: =IF(AO23="","",AO23+6) | AR23: =IF(AO23="","","Semana "&TEXT(AO23,"dd-mm-yyyy")&" al "&TEXT(AP23,"dd-mm-yyyy")) | AS23: =IF(A23="","",TEXT(A23,"mmmm yyyy")) | AT23: =IF(A23="","",TEXT(A23,"dddd")) | AU23: =IF(A23="","","CRR-"&TEXT(A23,"yyyymmdd")&"-"&M23&"-"&TEXT(ROW()-3,"0000")) | AV23: =IF(A23="","",IF(OR(B23="",C23="",E23="",F23="",M23="",N23=""),"Revisar campos obligatorios",IF(AND(P23="Atraso primera hora",Q23=""),"Falta justificación atraso primera hora",IF(AND(Z23="No cumple",AA23=""),"Falta justificación recambio >15 min",IF(AND(ISNUMBER(SEARCH("suspend",N23)),OR(AG23="",AH23="")),"Falta causa/motivo suspensión","OK"))))) | AW23: =IF(N23="","",IF(ISNUMBER(SEARCH("suspend",N23)),IF(AND(AG23="",AH23=""),"Sin causa/motivo registrado",IF(AG23="",AH23,IF(AH23="",AG23,AG23&": "&AH23))),""))
A24: 46167 | B24: ALONSO EMILIANO | C24: MADRID | D24: 12a 6m 0d | E24: SINOVECTOMIAS QUIRURGICAS (PROC. AUT.) CODO O MUÑECA O METACARPOFALANGICAS, C/U | F24: SERVICIO DE TRAUMATOLOGIA | H24: 2104029-5 | J24: =IF(H24<>"",IFERROR(VLOOKUP(IFERROR(LEFT(H24,FIND("-",H24)-1),H24),'Catalogo MINSAL'!A:E,5,FALSE),""),IF(I24<>"",IFERROR(VLOOKUP(IFERROR(LEFT(I24,FIND("-",I24)-1),I24),'Catalogo MINSAL'!A:E,5,FALSE),""),"")) | K24: Maximo Sepulveda Pizarro | L24: Maria Jose Rosen Petersen | M24: Quirofano 13 | N24: Atendido | O24: 0.71944444 | P24: =IFERROR(IF(OR(O24="",A24="",M24=""),"",IF(SUMPRODUCT(($A$4:$A$500=A24)*($M$4:$M$500=M24)*($O$4:$O$500<>"")*(MOD($O$4:$O$500,1)<MOD(O24,1)))=0,IF(MOD(O24,1)<=TIME(8,15,0),"Ingreso adecuado primera hora","Atraso primera hora"),"No aplica")),"") | R24: 0.74583333 | S24: 0.77777778 | T24: 0.79166667 | U24: =IFERROR(VLOOKUP(M24,'Horario Pabellones'!$A$4:$D$17,2,FALSE),"") | V24: =IFERROR(VLOOKUP(M24,'Horario Pabellones'!$A$4:$D$17,3,FALSE),"") | W24: =IFERROR(VLOOKUP(M24,'Horario Pabellones'!$A$4:$D$17,4,FALSE),"") | X24: =IFERROR(IF(OR(A24="",M24="",W24=""),"",(((_xludf.AGGREGATE(14,6,MOD($S$4:$S$500,1)/(($A$4:$A$500=A24)*($M$4:$M$500=M24)*($R$4:$R$500<>"")*($S$4:$S$500<>"")),1)-_xludf.AGGREGATE(15,6,MOD($R$4:$R$500,1)/(($A$4:$A$500=A24)*($M$4:$M$500=M24)*($R$4:$R$500<>"")*($S$4:$S$500<>"")),1))*1440)/60)/(W24/60)),"") | Y24: =IFERROR(IF(OR(O24="",A24="",M24=""),"",(IF(ISNUMBER(O24),MOD(O24,1),TIMEVALUE(O24))-LOOKUP(2,1/(($A$4:$A$500=A24)*($M$4:$M$500=M24)*($T$4:$T$500<>"")*($T$4:$T$500<IF(ISNUMBER(O24),MOD(O24,1),TIMEVALUE(O24)))),$T$4:$T$500))*1440),"") | Z24: =IFERROR(IF(Y24="","",IF(ROUND(Y24,0)<=15,"Cumple","No cumple")),"") | AB24: =IFERROR(IF(OR(O24="",R24=""),"",IF(IF(ISNUMBER(R24),MOD(R24,1),TIMEVALUE(R24))>=IF(ISNUMBER(O24),MOD(O24,1),TIMEVALUE(O24)),(IF(ISNUMBER(R24),MOD(R24,1),TIMEVALUE(R24))-IF(ISNUMBER(O24),MOD(O24,1),TIMEVALUE(O24)))*1440,(IF(ISNUMBER(R24),MOD(R24,1),TIMEVALUE(R24))+1-IF(ISNUMBER(O24),MOD(O24,1),TIMEVALUE(O24)))*1440)),"") | AC24: =IFERROR(IF(OR(R24="",S24=""),"",IF(IF(ISNUMBER(S24),MOD(S24,1),TIMEVALUE(S24))>=IF(ISNUMBER(R24),MOD(R24,1),TIMEVALUE(R24)),(IF(ISNUMBER(S24),MOD(S24,1),TIMEVALUE(S24))-IF(ISNUMBER(R24),MOD(R24,1),TIMEVALUE(R24)))*1440,(IF(ISNUMBER(S24),MOD(S24,1),TIMEVALUE(S24))+1-IF(ISNUMBER(R24),MOD(R24,1),TIMEVALUE(R24)))*1440)),"") | AD24: 90 | AE24: =IFERROR(IF(OR(AC24="",AD24=""),"",AC24-AD24),"") | AF24: =IFERROR(IF(AE24="","",IF(ROUND(AE24,0)>15,"Subestimacion",IF(ROUND(AE24,0)<-15,"Sobrestimacion","Asertivo"))),"") | AG24: Sin Suspensión | AM24: I0001187211 | AP24: =IF(A24="","",A24-WEEKDAY(A24,2)+1) | AQ24: =IF(AO24="","",AO24+6) | AR24: =IF(AO24="","","Semana "&TEXT(AO24,"dd-mm-yyyy")&" al "&TEXT(AP24,"dd-mm-yyyy")) | AS24: =IF(A24="","",TEXT(A24,"mmmm yyyy")) | AT24: =IF(A24="","",TEXT(A24,"dddd")) | AU24: =IF(A24="","","CRR-"&TEXT(A24,"yyyymmdd")&"-"&M24&"-"&TEXT(ROW()-3,"0000")) | AV24: =IF(A24="","",IF(OR(B24="",C24="",E24="",F24="",M24="",N24=""),"Revisar campos obligatorios",IF(AND(P24="Atraso primera hora",Q24=""),"Falta justificación atraso primera hora",IF(AND(Z24="No cumple",AA24=""),"Falta justificación recambio >15 min",IF(AND(ISNUMBER(SEARCH("suspend",N24)),OR(AG24="",AH24="")),"Falta causa/motivo suspensión","OK"))))) | AW24: =IF(N24="","",IF(ISNUMBER(SEARCH("suspend",N24)),IF(AND(AG24="",AH24=""),"Sin causa/motivo registrado",IF(AG24="",AH24,IF(AH24="",AG24,AG24&": "&AH24))),""))
A25: 46167 | B25: DANNA | C25: LIENDRO | D25: 3a 5m 15d | E25: POLIDACTILIA, EXTIRPACION Y PLASTIA UN LADO | F25: SERVICIO DE TRAUMATOLOGIA | H25: 1502058-5 | J25: =IF(H25<>"",IFERROR(VLOOKUP(IFERROR(LEFT(H25,FIND("-",H25)-1),H25),'Catalogo MINSAL'!A:E,5,FALSE),""),IF(I25<>"",IFERROR(VLOOKUP(IFERROR(LEFT(I25,FIND("-",I25)-1),I25),'Catalogo MINSAL'!A:E,5,FALSE),""),"")) | K25: Maximo Sepulveda Pizarro | L25: Maria Jose Rosen Petersen | M25: Quirofano 13 | N25: Agendado | P25: =IFERROR(IF(OR(O25="",A25="",M25=""),"",IF(SUMPRODUCT(($A$4:$A$500=A25)*($M$4:$M$500=M25)*($O$4:$O$500<>"")*(MOD($O$4:$O$500,1)<MOD(O25,1)))=0,IF(MOD(O25,1)<=TIME(8,15,0),"Ingreso adecuado primera hora","Atraso primera hora"),"No aplica")),"") | U25: =IFERROR(VLOOKUP(M25,'Horario Pabellones'!$A$4:$D$17,2,FALSE),"") | V25: =IFERROR(VLOOKUP(M25,'Horario Pabellones'!$A$4:$D$17,3,FALSE),"") | W25: =IFERROR(VLOOKUP(M25,'Horario Pabellones'!$A$4:$D$17,4,FALSE),"") | X25: =IFERROR(IF(OR(A25="",M25="",W25=""),"",(((_xludf.AGGREGATE(14,6,MOD($S$4:$S$500,1)/(($A$4:$A$500=A25)*($M$4:$M$500=M25)*($R$4:$R$500<>"")*($S$4:$S$500<>"")),1)-_xludf.AGGREGATE(15,6,MOD($R$4:$R$500,1)/(($A$4:$A$500=A25)*($M$4:$M$500=M25)*($R$4:$R$500<>"")*($S$4:$S$500<>"")),1))*1440)/60)/(W25/60)),"") | Y25: =IFERROR(IF(OR(O25="",A25="",M25=""),"",(IF(ISNUMBER(O25),MOD(O25,1),TIMEVALUE(O25))-LOOKUP(2,1/(($A$4:$A$500=A25)*($M$4:$M$500=M25)*($T$4:$T$500<>"")*($T$4:$T$500<IF(ISNUMBER(O25),MOD(O25,1),TIMEVALUE(O25)))),$T$4:$T$500))*1440),"") | Z25: =IFERROR(IF(Y25="","",IF(ROUND(Y25,0)<=15,"Cumple","No cumple")),"") | AB25: =IFERROR(IF(OR(O25="",R25=""),"",IF(IF(ISNUMBER(R25),MOD(R25,1),TIMEVALUE(R25))>=IF(ISNUMBER(O25),MOD(O25,1),TIMEVALUE(O25)),(IF(ISNUMBER(R25),MOD(R25,1),TIMEVALUE(R25))-IF(ISNUMBER(O25),MOD(O25,1),TIMEVALUE(O25)))*1440,(IF(ISNUMBER(R25),MOD(R25,1),TIMEVALUE(R25))+1-IF(ISNUMBER(O25),MOD(O25,1),TIMEVALUE(O25)))*1440)),"") | AC25: =IFERROR(IF(OR(R25="",S25=""),"",IF(IF(ISNUMBER(S25),MOD(S25,1),TIMEVALUE(S25))>=IF(ISNUMBER(R25),MOD(R25,1),TIMEVALUE(R25)),(IF(ISNUMBER(S25),MOD(S25,1),TIMEVALUE(S25))-IF(ISNUMBER(R25),MOD(R25,1),TIMEVALUE(R25)))*1440,(IF(ISNUMBER(S25),MOD(S25,1),TIMEVALUE(S25))+1-IF(ISNUMBER(R25),MOD(R25,1),TIMEVALUE(R25)))*1440)),"") | AE25: =IFERROR(IF(OR(AC25="",AD25=""),"",AC25-AD25),"") | AF25: =IFERROR(IF(AE25="","",IF(ROUND(AE25,0)>15,"Subestimacion",IF(ROUND(AE25,0)<-15,"Sobrestimacion","Asertivo"))),"") | AG25: No se presenta | AM25: I0001187197 | AP25: =IF(A25="","",A25-WEEKDAY(A25,2)+1) | AQ25: =IF(AO25="","",AO25+6) | AR25: =IF(AO25="","","Semana "&TEXT(AO25,"dd-mm-yyyy")&" al "&TEXT(AP25,"dd-mm-yyyy")) | AS25: =IF(A25="","",TEXT(A25,"mmmm yyyy")) | AT25: =IF(A25="","",TEXT(A25,"dddd")) | AU25: =IF(A25="","","CRR-"&TEXT(A25,"yyyymmdd")&"-"&M25&"-"&TEXT(ROW()-3,"0000")) | AV25: =IF(A25="","",IF(OR(B25="",C25="",E25="",F25="",M25="",N25=""),"Revisar campos obligatorios",IF(AND(P25="Atraso primera hora",Q25=""),"Falta justificación atraso primera hora",IF(AND(Z25="No cumple",AA25=""),"Falta justificación recambio >15 min",IF(AND(ISNUMBER(SEARCH("suspend",N25)),OR(AG25="",AH25="")),"Falta causa/motivo suspensión","OK"))))) | AW25: =IF(N25="","",IF(ISNUMBER(SEARCH("suspend",N25)),IF(AND(AG25="",AH25=""),"Sin causa/motivo registrado",IF(AG25="",AH25,IF(AH25="",AG25,AG25&": "&AH25))),""))
A26: 46168 | B26: BALTAZAR LEON | C26: PAILLAVIL | D26: 3a 3m 5d | E26: AMIGDALECTOMIA C/S ADENOIDECTOMIA, UNI O BILATERAL | F26: SERVICIO DE CIRUGIA ADULTO | H26: 1302029-5 | J26: =IF(H26<>"",IFERROR(VLOOKUP(IFERROR(LEFT(H26,FIND("-",H26)-1),H26),'Catalogo MINSAL'!A:E,5,FALSE),""),IF(I26<>"",IFERROR(VLOOKUP(IFERROR(LEFT(I26,FIND("-",I26)-1),I26),'Catalogo MINSAL'!A:E,5,FALSE),""),"")) | K26: Rodrigo Alejandro Villegas Lugo | L26: Dr. Cristian Aedo Bendel | M26: Quirofano 06 | N26: Atendido | O26: 0.35555556 | P26: =IFERROR(IF(OR(O26="",A26="",M26=""),"",IF(SUMPRODUCT(($A$4:$A$500=A26)*($M$4:$M$500=M26)*($O$4:$O$500<>"")*(MOD($O$4:$O$500,1)<MOD(O26,1)))=0,IF(MOD(O26,1)<=TIME(8,15,0),"Ingreso adecuado primera hora","Atraso primera hora"),"No aplica")),"") | R26: 0.37847222 | S26: 0.39236111 | T26: 0.42708333 | U26: =IFERROR(VLOOKUP(M26,'Horario Pabellones'!$A$4:$D$17,2,FALSE),"") | V26: =IFERROR(VLOOKUP(M26,'Horario Pabellones'!$A$4:$D$17,3,FALSE),"") | W26: =IFERROR(VLOOKUP(M26,'Horario Pabellones'!$A$4:$D$17,4,FALSE),"") | X26: =IFERROR(IF(OR(A26="",M26="",W26=""),"",(((_xludf.AGGREGATE(14,6,MOD($S$4:$S$500,1)/(($A$4:$A$500=A26)*($M$4:$M$500=M26)*($R$4:$R$500<>"")*($S$4:$S$500<>"")),1)-_xludf.AGGREGATE(15,6,MOD($R$4:$R$500,1)/(($A$4:$A$500=A26)*($M$4:$M$500=M26)*($R$4:$R$500<>"")*($S$4:$S$500<>"")),1))*1440)/60)/(W26/60)),"") | Y26: =IFERROR(IF(OR(O26="",A26="",M26=""),"",(IF(ISNUMBER(O26),MOD(O26,1),TIMEVALUE(O26))-LOOKUP(2,1/(($A$4:$A$500=A26)*($M$4:$M$500=M26)*($T$4:$T$500<>"")*($T$4:$T$500<IF(ISNUMBER(O26),MOD(O26,1),TIMEVALUE(O26)))),$T$4:$T$500))*1440),"") | Z26: =IFERROR(IF(Y26="","",IF(ROUND(Y26,0)<=15,"Cumple","No cumple")),"") | AB26: =IFERROR(IF(OR(O26="",R26=""),"",IF(IF(ISNUMBER(R26),MOD(R26,1),TIMEVALUE(R26))>=IF(ISNUMBER(O26),MOD(O26,1),TIMEVALUE(O26)),(IF(ISNUMBER(R26),MOD(R26,1),TIMEVALUE(R26))-IF(ISNUMBER(O26),MOD(O26,1),TIMEVALUE(O26)))*1440,(IF(ISNUMBER(R26),MOD(R26,1),TIMEVALUE(R26))+1-IF(ISNUMBER(O26),MOD(O26,1),TIMEVALUE(O26)))*1440)),"") | AC26: =IFERROR(IF(OR(R26="",S26=""),"",IF(IF(ISNUMBER(S26),MOD(S26,1),TIMEVALUE(S26))>=IF(ISNUMBER(R26),MOD(R26,1),TIMEVALUE(R26)),(IF(ISNUMBER(S26),MOD(S26,1),TIMEVALUE(S26))-IF(ISNUMBER(R26),MOD(R26,1),TIMEVALUE(R26)))*1440,(IF(ISNUMBER(S26),MOD(S26,1),TIMEVALUE(S26))+1-IF(ISNUMBER(R26),MOD(R26,1),TIMEVALUE(R26)))*1440)),"") | AD26: 90 | AE26: =IFERROR(IF(OR(AC26="",AD26=""),"",AC26-AD26),"") | AF26: =IFERROR(IF(AE26="","",IF(ROUND(AE26,0)>15,"Subestimacion",IF(ROUND(AE26,0)<-15,"Sobrestimacion","Asertivo"))),"") | AG26: Sin Suspensión | AM26: I0001187788 | AP26: =IF(A26="","",A26-WEEKDAY(A26,2)+1) | AQ26: =IF(AO26="","",AO26+6) | AR26: =IF(AO26="","","Semana "&TEXT(AO26,"dd-mm-yyyy")&" al "&TEXT(AP26,"dd-mm-yyyy")) | AS26: =IF(A26="","",TEXT(A26,"mmmm yyyy")) | AT26: =IF(A26="","",TEXT(A26,"dddd")) | AU26: =IF(A26="","","CRR-"&TEXT(A26,"yyyymmdd")&"-"&M26&"-"&TEXT(ROW()-3,"0000")) | AV26: =IF(A26="","",IF(OR(B26="",C26="",E26="",F26="",M26="",N26=""),"Revisar campos obligatorios",IF(AND(P26="Atraso primera hora",Q26=""),"Falta justificación atraso primera hora",IF(AND(Z26="No cumple",AA26=""),"Falta justificación recambio >15 min",IF(AND(ISNUMBER(SEARCH("suspend",N26)),OR(AG26="",AH26="")),"Falta causa/motivo suspensión","OK"))))) | AW26: =IF(N26="","",IF(ISNUMBER(SEARCH("suspend",N26)),IF(AND(AG26="",AH26=""),"Sin causa/motivo registrado",IF(AG26="",AH26,IF(AH26="",AG26,AG26&": "&AH26))),""))
A27: 46168 | B27: JARED VALENTINO | C27: SALINAS | D27: 6a 0m 1d | E27: AMIGDALECTOMIA C/S ADENOIDECTOMIA, UNI O BILATERAL | F27: SERVICIO DE CIRUGIA ADULTO | H27: 1302029-5 | J27: =IF(H27<>"",IFERROR(VLOOKUP(IFERROR(LEFT(H27,FIND("-",H27)-1),H27),'Catalogo MINSAL'!A:E,5,FALSE),""),IF(I27<>"",IFERROR(VLOOKUP(IFERROR(LEFT(I27,FIND("-",I27)-1),I27),'Catalogo MINSAL'!A:E,5,FALSE),""),"")) | K27: Rodrigo Alejandro Villegas Lugo | L27: Dr. Cristian Aedo Bendel | M27: Quirofano 06 | N27: Atendido | O27: 0.44444444 | P27: =IFERROR(IF(OR(O27="",A27="",M27=""),"",IF(SUMPRODUCT(($A$4:$A$500=A27)*($M$4:$M$500=M27)*($O$4:$O$500<>"")*(MOD($O$4:$O$500,1)<MOD(O27,1)))=0,IF(MOD(O27,1)<=TIME(8,15,0),"Ingreso adecuado primera hora","Atraso primera hora"),"No aplica")),"") | R27: 0.45833333 | S27: 0.5 | T27: 0.51041667 | U27: =IFERROR(VLOOKUP(M27,'Horario Pabellones'!$A$4:$D$17,2,FALSE),"") | V27: =IFERROR(VLOOKUP(M27,'Horario Pabellones'!$A$4:$D$17,3,FALSE),"") | W27: =IFERROR(VLOOKUP(M27,'Horario Pabellones'!$A$4:$D$17,4,FALSE),"") | X27: =IFERROR(IF(OR(A27="",M27="",W27=""),"",(((_xludf.AGGREGATE(14,6,MOD($S$4:$S$500,1)/(($A$4:$A$500=A27)*($M$4:$M$500=M27)*($R$4:$R$500<>"")*($S$4:$S$500<>"")),1)-_xludf.AGGREGATE(15,6,MOD($R$4:$R$500,1)/(($A$4:$A$500=A27)*($M$4:$M$500=M27)*($R$4:$R$500<>"")*($S$4:$S$500<>"")),1))*1440)/60)/(W27/60)),"") | Y27: =IFERROR(IF(OR(O27="",A27="",M27=""),"",(IF(ISNUMBER(O27),MOD(O27,1),TIMEVALUE(O27))-LOOKUP(2,1/(($A$4:$A$500=A27)*($M$4:$M$500=M27)*($T$4:$T$500<>"")*($T$4:$T$500<IF(ISNUMBER(O27),MOD(O27,1),TIMEVALUE(O27)))),$T$4:$T$500))*1440),"") | Z27: =IFERROR(IF(Y27="","",IF(ROUND(Y27,0)<=15,"Cumple","No cumple")),"") | AB27: =IFERROR(IF(OR(O27="",R27=""),"",IF(IF(ISNUMBER(R27),MOD(R27,1),TIMEVALUE(R27))>=IF(ISNUMBER(O27),MOD(O27,1),TIMEVALUE(O27)),(IF(ISNUMBER(R27),MOD(R27,1),TIMEVALUE(R27))-IF(ISNUMBER(O27),MOD(O27,1),TIMEVALUE(O27)))*1440,(IF(ISNUMBER(R27),MOD(R27,1),TIMEVALUE(R27))+1-IF(ISNUMBER(O27),MOD(O27,1),TIMEVALUE(O27)))*1440)),"") | AC27: =IFERROR(IF(OR(R27="",S27=""),"",IF(IF(ISNUMBER(S27),MOD(S27,1),TIMEVALUE(S27))>=IF(ISNUMBER(R27),MOD(R27,1),TIMEVALUE(R27)),(IF(ISNUMBER(S27),MOD(S27,1),TIMEVALUE(S27))-IF(ISNUMBER(R27),MOD(R27,1),TIMEVALUE(R27)))*1440,(IF(ISNUMBER(S27),MOD(S27,1),TIMEVALUE(S27))+1-IF(ISNUMBER(R27),MOD(R27,1),TIMEVALUE(R27)))*1440)),"") | AD27: 60 | AE27: =IFERROR(IF(OR(AC27="",AD27=""),"",AC27-AD27),"") | AF27: =IFERROR(IF(AE27="","",IF(ROUND(AE27,0)>15,"Subestimacion",IF(ROUND(AE27,0)<-15,"Sobrestimacion","Asertivo"))),"") | AG27: Sin Suspensión | AM27: I0001187790 | AP27: =IF(A27="","",A27-WEEKDAY(A27,2)+1) | AQ27: =IF(AO27="","",AO27+6) | AR27: =IF(AO27="","","Semana "&TEXT(AO27,"dd-mm-yyyy")&" al "&TEXT(AP27,"dd-mm-yyyy")) | AS27: =IF(A27="","",TEXT(A27,"mmmm yyyy")) | AT27: =IF(A27="","",TEXT(A27,"dddd")) | AU27: =IF(A27="","","CRR-"&TEXT(A27,"yyyymmdd")&"-"&M27&"-"&TEXT(ROW()-3,"0000")) | AV27: =IF(A27="","",IF(OR(B27="",C27="",E27="",F27="",M27="",N27=""),"Revisar campos obligatorios",IF(AND(P27="Atraso primera hora",Q27=""),"Falta justificación atraso primera hora",IF(AND(Z27="No cumple",AA27=""),"Falta justificación recambio >15 min",IF(AND(ISNUMBER(SEARCH("suspend",N27)),OR(AG27="",AH27="")),"Falta causa/motivo suspensión","OK"))))) | AW27: =IF(N27="","",IF(ISNUMBER(SEARCH("suspend",N27)),IF(AND(AG27="",AH27=""),"Sin causa/motivo registrado",IF(AG27="",AH27,IF(AH27="",AG27,AG27&": "&AH27))),""))
A28: 46168 | B28: ÁNGEL ALEJANDRO | C28: CARIQUEO | D28: 4a 9m 12d | E28: AMIGDALECTOMIA C/S ADENOIDECTOMIA, UNI O BILATERAL | F28: SERVICIO DE CIRUGIA ADULTO | H28: 1302029-5 | J28: =IF(H28<>"",IFERROR(VLOOKUP(IFERROR(LEFT(H28,FIND("-",H28)-1),H28),'Catalogo MINSAL'!A:E,5,FALSE),""),IF(I28<>"",IFERROR(VLOOKUP(IFERROR(LEFT(I28,FIND("-",I28)-1),I28),'Catalogo MINSAL'!A:E,5,FALSE),""),"")) | K28: Rodrigo Alejandro Villegas Lugo | L28: Dr. Christian Diaz Frias | M28: Quirofano 06 | N28: Recepcionado | O28: 0.52083333 | P28: =IFERROR(IF(OR(O28="",A28="",M28=""),"",IF(SUMPRODUCT(($A$4:$A$500=A28)*($M$4:$M$500=M28)*($O$4:$O$500<>"")*(MOD($O$4:$O$500,1)<MOD(O28,1)))=0,IF(MOD(O28,1)<=TIME(8,15,0),"Ingreso adecuado primera hora","Atraso primera hora"),"No aplica")),"") | R28: 0.53611111 | S28: 0.55972222 | T28: 0.57777778 | U28: =IFERROR(VLOOKUP(M28,'Horario Pabellones'!$A$4:$D$17,2,FALSE),"") | V28: =IFERROR(VLOOKUP(M28,'Horario Pabellones'!$A$4:$D$17,3,FALSE),"") | W28: =IFERROR(VLOOKUP(M28,'Horario Pabellones'!$A$4:$D$17,4,FALSE),"") | X28: =IFERROR(IF(OR(A28="",M28="",W28=""),"",(((_xludf.AGGREGATE(14,6,MOD($S$4:$S$500,1)/(($A$4:$A$500=A28)*($M$4:$M$500=M28)*($R$4:$R$500<>"")*($S$4:$S$500<>"")),1)-_xludf.AGGREGATE(15,6,MOD($R$4:$R$500,1)/(($A$4:$A$500=A28)*($M$4:$M$500=M28)*($R$4:$R$500<>"")*($S$4:$S$500<>"")),1))*1440)/60)/(W28/60)),"") | Y28: =IFERROR(IF(OR(O28="",A28="",M28=""),"",(IF(ISNUMBER(O28),MOD(O28,1),TIMEVALUE(O28))-LOOKUP(2,1/(($A$4:$A$500=A28)*($M$4:$M$500=M28)*($T$4:$T$500<>"")*($T$4:$T$500<IF(ISNUMBER(O28),MOD(O28,1),TIMEVALUE(O28)))),$T$4:$T$500))*1440),"") | Z28: =IFERROR(IF(Y28="","",IF(ROUND(Y28,0)<=15,"Cumple","No cumple")),"") | AB28: =IFERROR(IF(OR(O28="",R28=""),"",IF(IF(ISNUMBER(R28),MOD(R28,1),TIMEVALUE(R28))>=IF(ISNUMBER(O28),MOD(O28,1),TIMEVALUE(O28)),(IF(ISNUMBER(R28),MOD(R28,1),TIMEVALUE(R28))-IF(ISNUMBER(O28),MOD(O28,1),TIMEVALUE(O28)))*1440,(IF(ISNUMBER(R28),MOD(R28,1),TIMEVALUE(R28))+1-IF(ISNUMBER(O28),MOD(O28,1),TIMEVALUE(O28)))*1440)),"") | AC28: =IFERROR(IF(OR(R28="",S28=""),"",IF(IF(ISNUMBER(S28),MOD(S28,1),TIMEVALUE(S28))>=IF(ISNUMBER(R28),MOD(R28,1),TIMEVALUE(R28)),(IF(ISNUMBER(S28),MOD(S28,1),TIMEVALUE(S28))-IF(ISNUMBER(R28),MOD(R28,1),TIMEVALUE(R28)))*1440,(IF(ISNUMBER(S28),MOD(S28,1),TIMEVALUE(S28))+1-IF(ISNUMBER(R28),MOD(R28,1),TIMEVALUE(R28)))*1440)),"") | AD28: 60 | AE28: =IFERROR(IF(OR(AC28="",AD28=""),"",AC28-AD28),"") | AF28: =IFERROR(IF(AE28="","",IF(ROUND(AE28,0)>15,"Subestimacion",IF(ROUND(AE28,0)<-15,"Sobrestimacion","Asertivo"))),"") | AG28: Sin Suspensión | AM28: I0001187794 | AP28: =IF(A28="","",A28-WEEKDAY(A28,2)+1) | AQ28: =IF(AO28="","",AO28+6) | AR28: =IF(AO28="","","Semana "&TEXT(AO28,"dd-mm-yyyy")&" al "&TEXT(AP28,"dd-mm-yyyy")) | AS28: =IF(A28="","",TEXT(A28,"mmmm yyyy")) | AT28: =IF(A28="","",TEXT(A28,"dddd")) | AU28: =IF(A28="","","CRR-"&TEXT(A28,"yyyymmdd")&"-"&M28&"-"&TEXT(ROW()-3,"0000")) | AV28: =IF(A28="","",IF(OR(B28="",C28="",E28="",F28="",M28="",N28=""),"Revisar campos obligatorios",IF(AND(P28="Atraso primera hora",Q28=""),"Falta justificación atraso primera hora",IF(AND(Z28="No cumple",AA28=""),"Falta justificación recambio >15 min",IF(AND(ISNUMBER(SEARCH("suspend",N28)),OR(AG28="",AH28="")),"Falta causa/motivo suspensión","OK"))))) | AW28: =IF(N28="","",IF(ISNUMBER(SEARCH("suspend",N28)),IF(AND(AG28="",AH28=""),"Sin causa/motivo registrado",IF(AG28="",AH28,IF(AH28="",AG28,AG28&": "&AH28))),""))
A29: 46168 | B29: AYELEN TRINIDAD | C29: GONZÁLEZ | D29: 11a 1m 28d | E29: ADENOIDECTOMIA (PROC. AUT.) | F29: SERVICIO DE CIRUGIA ADULTO | H29: 1302028-5 | J29: =IF(H29<>"",IFERROR(VLOOKUP(IFERROR(LEFT(H29,FIND("-",H29)-1),H29),'Catalogo MINSAL'!A:E,5,FALSE),""),IF(I29<>"",IFERROR(VLOOKUP(IFERROR(LEFT(I29,FIND("-",I29)-1),I29),'Catalogo MINSAL'!A:E,5,FALSE),""),"")) | K29: Rodrigo Alejandro Villegas Lugo | L29: Dr. Christian Diaz Frias | M29: Quirofano 06 | N29: Atendido | O29: 0.61111111 | P29: =IFERROR(IF(OR(O29="",A29="",M29=""),"",IF(SUMPRODUCT(($A$4:$A$500=A29)*($M$4:$M$500=M29)*($O$4:$O$500<>"")*(MOD($O$4:$O$500,1)<MOD(O29,1)))=0,IF(MOD(O29,1)<=TIME(8,15,0),"Ingreso adecuado primera hora","Atraso primera hora"),"No aplica")),"") | R29: 0.62152778 | S29: 0.64097222 | T29: 0.65277778 | U29: =IFERROR(VLOOKUP(M29,'Horario Pabellones'!$A$4:$D$17,2,FALSE),"") | V29: =IFERROR(VLOOKUP(M29,'Horario Pabellones'!$A$4:$D$17,3,FALSE),"") | W29: =IFERROR(VLOOKUP(M29,'Horario Pabellones'!$A$4:$D$17,4,FALSE),"") | X29: =IFERROR(IF(OR(A29="",M29="",W29=""),"",(((_xludf.AGGREGATE(14,6,MOD($S$4:$S$500,1)/(($A$4:$A$500=A29)*($M$4:$M$500=M29)*($R$4:$R$500<>"")*($S$4:$S$500<>"")),1)-_xludf.AGGREGATE(15,6,MOD($R$4:$R$500,1)/(($A$4:$A$500=A29)*($M$4:$M$500=M29)*($R$4:$R$500<>"")*($S$4:$S$500<>"")),1))*1440)/60)/(W29/60)),"") | Y29: =IFERROR(IF(OR(O29="",A29="",M29=""),"",(IF(ISNUMBER(O29),MOD(O29,1),TIMEVALUE(O29))-LOOKUP(2,1/(($A$4:$A$500=A29)*($M$4:$M$500=M29)*($T$4:$T$500<>"")*($T$4:$T$500<IF(ISNUMBER(O29),MOD(O29,1),TIMEVALUE(O29)))),$T$4:$T$500))*1440),"") | Z29: =IFERROR(IF(Y29="","",IF(ROUND(Y29,0)<=15,"Cumple","No cumple")),"") | AB29: =IFERROR(IF(OR(O29="",R29=""),"",IF(IF(ISNUMBER(R29),MOD(R29,1),TIMEVALUE(R29))>=IF(ISNUMBER(O29),MOD(O29,1),TIMEVALUE(O29)),(IF(ISNUMBER(R29),MOD(R29,1),TIMEVALUE(R29))-IF(ISNUMBER(O29),MOD(O29,1),TIMEVALUE(O29)))*1440,(IF(ISNUMBER(R29),MOD(R29,1),TIMEVALUE(R29))+1-IF(ISNUMBER(O29),MOD(O29,1),TIMEVALUE(O29)))*1440)),"") | AC29: =IFERROR(IF(OR(R29="",S29=""),"",IF(IF(ISNUMBER(S29),MOD(S29,1),TIMEVALUE(S29))>=IF(ISNUMBER(R29),MOD(R29,1),TIMEVALUE(R29)),(IF(ISNUMBER(S29),MOD(S29,1),TIMEVALUE(S29))-IF(ISNUMBER(R29),MOD(R29,1),TIMEVALUE(R29)))*1440,(IF(ISNUMBER(S29),MOD(S29,1),TIMEVALUE(S29))+1-IF(ISNUMBER(R29),MOD(R29,1),TIMEVALUE(R29)))*1440)),"") | AD29: 40 | AE29: =IFERROR(IF(OR(AC29="",AD29=""),"",AC29-AD29),"") | AF29: =IFERROR(IF(AE29="","",IF(ROUND(AE29,0)>15,"Subestimacion",IF(ROUND(AE29,0)<-15,"Sobrestimacion","Asertivo"))),"") | AG29: Sin Suspensión | AM29: I0001187796 | AP29: =IF(A29="","",A29-WEEKDAY(A29,2)+1) | AQ29: =IF(AO29="","",AO29+6) | AR29: =IF(AO29="","","Semana "&TEXT(AO29,"dd-mm-yyyy")&" al "&TEXT(AP29,"dd-mm-yyyy")) | AS29: =IF(A29="","",TEXT(A29,"mmmm yyyy")) | AT29: =IF(A29="","",TEXT(A29,"dddd")) | AU29: =IF(A29="","","CRR-"&TEXT(A29,"yyyymmdd")&"-"&M29&"-"&TEXT(ROW()-3,"0000")) | AV29: =IF(A29="","",IF(OR(B29="",C29="",E29="",F29="",M29="",N29=""),"Revisar campos obligatorios",IF(AND(P29="Atraso primera hora",Q29=""),"Falta justificación atraso primera hora",IF(AND(Z29="No cumple",AA29=""),"Falta justificación recambio >15 min",IF(AND(ISNUMBER(SEARCH("suspend",N29)),OR(AG29="",AH29="")),"Falta causa/motivo suspensión","OK"))))) | AW29: =IF(N29="","",IF(ISNUMBER(SEARCH("suspend",N29)),IF(AND(AG29="",AH29=""),"Sin causa/motivo registrado",IF(AG29="",AH29,IF(AH29="",AG29,AG29&": "&AH29))),""))
A30: 46168 | B30: BENJAMÍN ALONSO | C30: CORDERO | D30: 17a 3m 25d | E30: AMIGDALECTOMIA C/S ADENOIDECTOMIA, UNI O BILATERAL | F30: SERVICIO DE CIRUGIA ADULTO | H30: 1302029-5 | J30: =IF(H30<>"",IFERROR(VLOOKUP(IFERROR(LEFT(H30,FIND("-",H30)-1),H30),'Catalogo MINSAL'!A:E,5,FALSE),""),IF(I30<>"",IFERROR(VLOOKUP(IFERROR(LEFT(I30,FIND("-",I30)-1),I30),'Catalogo MINSAL'!A:E,5,FALSE),""),"")) | K30: Rodrigo Alejandro Villegas Lugo | L30: Dr. Fernando Rivas Castillo | M30: Quirofano 06 | N30: Atendido | O30: 0.66111111 | P30: =IFERROR(IF(OR(O30="",A30="",M30=""),"",IF(SUMPRODUCT(($A$4:$A$500=A30)*($M$4:$M$500=M30)*($O$4:$O$500<>"")*(MOD($O$4:$O$500,1)<MOD(O30,1)))=0,IF(MOD(O30,1)<=TIME(8,15,0),"Ingreso adecuado primera hora","Atraso primera hora"),"No aplica")),"") | R30: 0.67013889 | S30: 0.70138889 | T30: 0.72083333 | U30: =IFERROR(VLOOKUP(M30,'Horario Pabellones'!$A$4:$D$17,2,FALSE),"") | V30: =IFERROR(VLOOKUP(M30,'Horario Pabellones'!$A$4:$D$17,3,FALSE),"") | W30: =IFERROR(VLOOKUP(M30,'Horario Pabellones'!$A$4:$D$17,4,FALSE),"") | X30: =IFERROR(IF(OR(A30="",M30="",W30=""),"",(((_xludf.AGGREGATE(14,6,MOD($S$4:$S$500,1)/(($A$4:$A$500=A30)*($M$4:$M$500=M30)*($R$4:$R$500<>"")*($S$4:$S$500<>"")),1)-_xludf.AGGREGATE(15,6,MOD($R$4:$R$500,1)/(($A$4:$A$500=A30)*($M$4:$M$500=M30)*($R$4:$R$500<>"")*($S$4:$S$500<>"")),1))*1440)/60)/(W30/60)),"") | Y30: =IFERROR(IF(OR(O30="",A30="",M30=""),"",(IF(ISNUMBER(O30),MOD(O30,1),TIMEVALUE(O30))-LOOKUP(2,1/(($A$4:$A$500=A30)*($M$4:$M$500=M30)*($T$4:$T$500<>"")*($T$4:$T$500<IF(ISNUMBER(O30),MOD(O30,1),TIMEVALUE(O30)))),$T$4:$T$500))*1440),"") | Z30: =IFERROR(IF(Y30="","",IF(ROUND(Y30,0)<=15,"Cumple","No cumple")),"") | AB30: =IFERROR(IF(OR(O30="",R30=""),"",IF(IF(ISNUMBER(R30),MOD(R30,1),TIMEVALUE(R30))>=IF(ISNUMBER(O30),MOD(O30,1),TIMEVALUE(O30)),(IF(ISNUMBER(R30),MOD(R30,1),TIMEVALUE(R30))-IF(ISNUMBER(O30),MOD(O30,1),TIMEVALUE(O30)))*1440,(IF(ISNUMBER(R30),MOD(R30,1),TIMEVALUE(R30))+1-IF(ISNUMBER(O30),MOD(O30,1),TIMEVALUE(O30)))*1440)),"") | AC30: =IFERROR(IF(OR(R30="",S30=""),"",IF(IF(ISNUMBER(S30),MOD(S30,1),TIMEVALUE(S30))>=IF(ISNUMBER(R30),MOD(R30,1),TIMEVALUE(R30)),(IF(ISNUMBER(S30),MOD(S30,1),TIMEVALUE(S30))-IF(ISNUMBER(R30),MOD(R30,1),TIMEVALUE(R30)))*1440,(IF(ISNUMBER(S30),MOD(S30,1),TIMEVALUE(S30))+1-IF(ISNUMBER(R30),MOD(R30,1),TIMEVALUE(R30)))*1440)),"") | AD30: 45 | AE30: =IFERROR(IF(OR(AC30="",AD30=""),"",AC30-AD30),"") | AF30: =IFERROR(IF(AE30="","",IF(ROUND(AE30,0)>15,"Subestimacion",IF(ROUND(AE30,0)<-15,"Sobrestimacion","Asertivo"))),"") | AG30: Sin Suspensión | AM30: I0001187797 | AP30: =IF(A30="","",A30-WEEKDAY(A30,2)+1) | AQ30: =IF(AO30="","",AO30+6) | AR30: =IF(AO30="","","Semana "&TEXT(AO30,"dd-mm-yyyy")&" al "&TEXT(AP30,"dd-mm-yyyy")) | AS30: =IF(A30="","",TEXT(A30,"mmmm yyyy")) | AT30: =IF(A30="","",TEXT(A30,"dddd")) | AU30: =IF(A30="","","CRR-"&TEXT(A30,"yyyymmdd")&"-"&M30&"-"&TEXT(ROW()-3,"0000")) | AV30: =IF(A30="","",IF(OR(B30="",C30="",E30="",F30="",M30="",N30=""),"Revisar campos obligatorios",IF(AND(P30="Atraso primera hora",Q30=""),"Falta justificación atraso primera hora",IF(AND(Z30="No cumple",AA30=""),"Falta justificación recambio >15 min",IF(AND(ISNUMBER(SEARCH("suspend",N30)),OR(AG30="",AH30="")),"Falta causa/motivo suspensión","OK"))))) | AW30: =IF(N30="","",IF(ISNUMBER(SEARCH("suspend",N30)),IF(AND(AG30="",AH30=""),"Sin causa/motivo registrado",IF(AG30="",AH30,IF(AH30="",AG30,AG30&": "&AH30))),""))
A31: 46168 | B31: PAOLA ANDREA | C31: OLGUÍN | D31: 57a 6m 11d | E31: COLECISTECTOMIA POR VIDEOLAPAROSCOPIA, PROC. COMPLETO | F31: SERVICIO DE CIRUGIA ADULTO | H31: 1802081-10 | J31: =IF(H31<>"",IFERROR(VLOOKUP(IFERROR(LEFT(H31,FIND("-",H31)-1),H31),'Catalogo MINSAL'!A:E,5,FALSE),""),IF(I31<>"",IFERROR(VLOOKUP(IFERROR(LEFT(I31,FIND("-",I31)-1),I31),'Catalogo MINSAL'!A:E,5,FALSE),""),"")) | K31: Aliana Violeta Morales Ruiz | L31: Felicia Meza Maldonado | M31: Quirofano 09 | N31: Recepcionado | O31: 0.35208333 | P31: =IFERROR(IF(OR(O31="",A31="",M31=""),"",IF(SUMPRODUCT(($A$4:$A$500=A31)*($M$4:$M$500=M31)*($O$4:$O$500<>"")*(MOD($O$4:$O$500,1)<MOD(O31,1)))=0,IF(MOD(O31,1)<=TIME(8,15,0),"Ingreso adecuado primera hora","Atraso primera hora"),"No aplica")),"") | R31: 0.3875 | S31: 0.4125 | T31: 0.43541667 | U31: =IFERROR(VLOOKUP(M31,'Horario Pabellones'!$A$4:$D$17,2,FALSE),"") | V31: =IFERROR(VLOOKUP(M31,'Horario Pabellones'!$A$4:$D$17,3,FALSE),"") | W31: =IFERROR(VLOOKUP(M31,'Horario Pabellones'!$A$4:$D$17,4,FALSE),"") | X31: =IFERROR(IF(OR(A31="",M31="",W31=""),"",(((_xludf.AGGREGATE(14,6,MOD($S$4:$S$500,1)/(($A$4:$A$500=A31)*($M$4:$M$500=M31)*($R$4:$R$500<>"")*($S$4:$S$500<>"")),1)-_xludf.AGGREGATE(15,6,MOD($R$4:$R$500,1)/(($A$4:$A$500=A31)*($M$4:$M$500=M31)*($R$4:$R$500<>"")*($S$4:$S$500<>"")),1))*1440)/60)/(W31/60)),"") | Y31: =IFERROR(IF(OR(O31="",A31="",M31=""),"",(IF(ISNUMBER(O31),MOD(O31,1),TIMEVALUE(O31))-LOOKUP(2,1/(($A$4:$A$500=A31)*($M$4:$M$500=M31)*($T$4:$T$500<>"")*($T$4:$T$500<IF(ISNUMBER(O31),MOD(O31,1),TIMEVALUE(O31)))),$T$4:$T$500))*1440),"") | Z31: =IFERROR(IF(Y31="","",IF(ROUND(Y31,0)<=15,"Cumple","No cumple")),"") | AB31: =IFERROR(IF(OR(O31="",R31=""),"",IF(IF(ISNUMBER(R31),MOD(R31,1),TIMEVALUE(R31))>=IF(ISNUMBER(O31),MOD(O31,1),TIMEVALUE(O31)),(IF(ISNUMBER(R31),MOD(R31,1),TIMEVALUE(R31))-IF(ISNUMBER(O31),MOD(O31,1),TIMEVALUE(O31)))*1440,(IF(ISNUMBER(R31),MOD(R31,1),TIMEVALUE(R31))+1-IF(ISNUMBER(O31),MOD(O31,1),TIMEVALUE(O31)))*1440)),"") | AC31: =IFERROR(IF(OR(R31="",S31=""),"",IF(IF(ISNUMBER(S31),MOD(S31,1),TIMEVALUE(S31))>=IF(ISNUMBER(R31),MOD(R31,1),TIMEVALUE(R31)),(IF(ISNUMBER(S31),MOD(S31,1),TIMEVALUE(S31))-IF(ISNUMBER(R31),MOD(R31,1),TIMEVALUE(R31)))*1440,(IF(ISNUMBER(S31),MOD(S31,1),TIMEVALUE(S31))+1-IF(ISNUMBER(R31),MOD(R31,1),TIMEVALUE(R31)))*1440)),"") | AD31: 60 | AE31: =IFERROR(IF(OR(AC31="",AD31=""),"",AC31-AD31),"") | AF31: =IFERROR(IF(AE31="","",IF(ROUND(AE31,0)>15,"Subestimacion",IF(ROUND(AE31,0)<-15,"Sobrestimacion","Asertivo"))),"") | AG31: Sin Suspensión | AM31: I0001187721 | AP31: =IF(A31="","",A31-WEEKDAY(A31,2)+1) | AQ31: =IF(AO31="","",AO31+6) | AR31: =IF(AO31="","","Semana "&TEXT(AO31,"dd-mm-yyyy")&" al "&TEXT(AP31,"dd-mm-yyyy")) | AS31: =IF(A31="","",TEXT(A31,"mmmm yyyy")) | AT31: =IF(A31="","",TEXT(A31,"dddd")) | AU31: =IF(A31="","","CRR-"&TEXT(A31,"yyyymmdd")&"-"&M31&"-"&TEXT(ROW()-3,"0000")) | AV31: =IF(A31="","",IF(OR(B31="",C31="",E31="",F31="",M31="",N31=""),"Revisar campos obligatorios",IF(AND(P31="Atraso primera hora",Q31=""),"Falta justificación atraso primera hora",IF(AND(Z31="No cumple",AA31=""),"Falta justificación recambio >15 min",IF(AND(ISNUMBER(SEARCH("suspend",N31)),OR(AG31="",AH31="")),"Falta causa/motivo suspensión","OK"))))) | AW31: =IF(N31="","",IF(ISNUMBER(SEARCH("suspend",N31)),IF(AND(AG31="",AH31=""),"Sin causa/motivo registrado",IF(AG31="",AH31,IF(AH31="",AG31,AG31&": "&AH31))),""))
A32: 46168 | B32: JUANA ROSA | C32: FLORES | D32: 43a 9m 11d | E32: COLECISTECTOMIA POR VIDEOLAPAROSCOPIA, PROC. COMPLETO | F32: SERVICIO DE CIRUGIA ADULTO | H32: 1802081-10 | J32: =IF(H32<>"",IFERROR(VLOOKUP(IFERROR(LEFT(H32,FIND("-",H32)-1),H32),'Catalogo MINSAL'!A:E,5,FALSE),""),IF(I32<>"",IFERROR(VLOOKUP(IFERROR(LEFT(I32,FIND("-",I32)-1),I32),'Catalogo MINSAL'!A:E,5,FALSE),""),"")) | K32: Aliana Violeta Morales Ruiz | L32: Carleny Cordero Lugo | M32: Quirofano 09 | N32: Atendido | O32: 0.44444444 | P32: =IFERROR(IF(OR(O32="",A32="",M32=""),"",IF(SUMPRODUCT(($A$4:$A$500=A32)*($M$4:$M$500=M32)*($O$4:$O$500<>"")*(MOD($O$4:$O$500,1)<MOD(O32,1)))=0,IF(MOD(O32,1)<=TIME(8,15,0),"Ingreso adecuado primera hora","Atraso primera hora"),"No aplica")),"") | R32: 0.46875 | S32: 0.5 | T32: 0.52083333 | U32: =IFERROR(VLOOKUP(M32,'Horario Pabellones'!$A$4:$D$17,2,FALSE),"") | V32: =IFERROR(VLOOKUP(M32,'Horario Pabellones'!$A$4:$D$17,3,FALSE),"") | W32: =IFERROR(VLOOKUP(M32,'Horario Pabellones'!$A$4:$D$17,4,FALSE),"") | X32: =IFERROR(IF(OR(A32="",M32="",W32=""),"",(((_xludf.AGGREGATE(14,6,MOD($S$4:$S$500,1)/(($A$4:$A$500=A32)*($M$4:$M$500=M32)*($R$4:$R$500<>"")*($S$4:$S$500<>"")),1)-_xludf.AGGREGATE(15,6,MOD($R$4:$R$500,1)/(($A$4:$A$500=A32)*($M$4:$M$500=M32)*($R$4:$R$500<>"")*($S$4:$S$500<>"")),1))*1440)/60)/(W32/60)),"") | Y32: =IFERROR(IF(OR(O32="",A32="",M32=""),"",(IF(ISNUMBER(O32),MOD(O32,1),TIMEVALUE(O32))-LOOKUP(2,1/(($A$4:$A$500=A32)*($M$4:$M$500=M32)*($T$4:$T$500<>"")*($T$4:$T$500<IF(ISNUMBER(O32),MOD(O32,1),TIMEVALUE(O32)))),$T$4:$T$500))*1440),"") | Z32: =IFERROR(IF(Y32="","",IF(ROUND(Y32,0)<=15,"Cumple","No cumple")),"") | AB32: =IFERROR(IF(OR(O32="",R32=""),"",IF(IF(ISNUMBER(R32),MOD(R32,1),TIMEVALUE(R32))>=IF(ISNUMBER(O32),MOD(O32,1),TIMEVALUE(O32)),(IF(ISNUMBER(R32),MOD(R32,1),TIMEVALUE(R32))-IF(ISNUMBER(O32),MOD(O32,1),TIMEVALUE(O32)))*1440,(IF(ISNUMBER(R32),MOD(R32,1),TIMEVALUE(R32))+1-IF(ISNUMBER(O32),MOD(O32,1),TIMEVALUE(O32)))*1440)),"") | AC32: =IFERROR(IF(OR(R32="",S32=""),"",IF(IF(ISNUMBER(S32),MOD(S32,1),TIMEVALUE(S32))>=IF(ISNUMBER(R32),MOD(R32,1),TIMEVALUE(R32)),(IF(ISNUMBER(S32),MOD(S32,1),TIMEVALUE(S32))-IF(ISNUMBER(R32),MOD(R32,1),TIMEVALUE(R32)))*1440,(IF(ISNUMBER(S32),MOD(S32,1),TIMEVALUE(S32))+1-IF(ISNUMBER(R32),MOD(R32,1),TIMEVALUE(R32)))*1440)),"") | AD32: 45 | AE32: =IFERROR(IF(OR(AC32="",AD32=""),"",AC32-AD32),"") | AF32: =IFERROR(IF(AE32="","",IF(ROUND(AE32,0)>15,"Subestimacion",IF(ROUND(AE32,0)<-15,"Sobrestimacion","Asertivo"))),"") | AG32: Sin Suspensión | AM32: I0001187723 | AP32: =IF(A32="","",A32-WEEKDAY(A32,2)+1) | AQ32: =IF(AO32="","",AO32+6) | AR32: =IF(AO32="","","Semana "&TEXT(AO32,"dd-mm-yyyy")&" al "&TEXT(AP32,"dd-mm-yyyy")) | AS32: =IF(A32="","",TEXT(A32,"mmmm yyyy")) | AT32: =IF(A32="","",TEXT(A32,"dddd")) | AU32: =IF(A32="","","CRR-"&TEXT(A32,"yyyymmdd")&"-"&M32&"-"&TEXT(ROW()-3,"0000")) | AV32: =IF(A32="","",IF(OR(B32="",C32="",E32="",F32="",M32="",N32=""),"Revisar campos obligatorios",IF(AND(P32="Atraso primera hora",Q32=""),"Falta justificación atraso primera hora",IF(AND(Z32="No cumple",AA32=""),"Falta justificación recambio >15 min",IF(AND(ISNUMBER(SEARCH("suspend",N32)),OR(AG32="",AH32="")),"Falta causa/motivo suspensión","OK"))))) | AW32: =IF(N32="","",IF(ISNUMBER(SEARCH("suspend",N32)),IF(AND(AG32="",AH32=""),"Sin causa/motivo registrado",IF(AG32="",AH32,IF(AH32="",AG32,AG32&": "&AH32))),""))
A33: 46168 | B33: MARÍA JOSÉ | C33: ARIAS | D33: 41a 4m 13d | E33: COLECISTECTOMIA POR VIDEOLAPAROSCOPIA, PROC. COMPLETO | F33: SERVICIO DE CIRUGIA ADULTO | H33: 1802081-10 | J33: =IF(H33<>"",IFERROR(VLOOKUP(IFERROR(LEFT(H33,FIND("-",H33)-1),H33),'Catalogo MINSAL'!A:E,5,FALSE),""),IF(I33<>"",IFERROR(VLOOKUP(IFERROR(LEFT(I33,FIND("-",I33)-1),I33),'Catalogo MINSAL'!A:E,5,FALSE),""),"")) | K33: Aliana Violeta Morales Ruiz | L33: Jesus Soublett Rivas | M33: Quirofano 09 | N33: Atendido | O33: 0.53125 | P33: =IFERROR(IF(OR(O33="",A33="",M33=""),"",IF(SUMPRODUCT(($A$4:$A$500=A33)*($M$4:$M$500=M33)*($O$4:$O$500<>"")*(MOD($O$4:$O$500,1)<MOD(O33,1)))=0,IF(MOD(O33,1)<=TIME(8,15,0),"Ingreso adecuado primera hora","Atraso primera hora"),"No aplica")),"") | R33: 0.55555556 | S33: 0.59722222 | T33: 0.61527778 | U33: =IFERROR(VLOOKUP(M33,'Horario Pabellones'!$A$4:$D$17,2,FALSE),"") | V33: =IFERROR(VLOOKUP(M33,'Horario Pabellones'!$A$4:$D$17,3,FALSE),"") | W33: =IFERROR(VLOOKUP(M33,'Horario Pabellones'!$A$4:$D$17,4,FALSE),"") | X33: =IFERROR(IF(OR(A33="",M33="",W33=""),"",(((_xludf.AGGREGATE(14,6,MOD($S$4:$S$500,1)/(($A$4:$A$500=A33)*($M$4:$M$500=M33)*($R$4:$R$500<>"")*($S$4:$S$500<>"")),1)-_xludf.AGGREGATE(15,6,MOD($R$4:$R$500,1)/(($A$4:$A$500=A33)*($M$4:$M$500=M33)*($R$4:$R$500<>"")*($S$4:$S$500<>"")),1))*1440)/60)/(W33/60)),"") | Y33: =IFERROR(IF(OR(O33="",A33="",M33=""),"",(IF(ISNUMBER(O33),MOD(O33,1),TIMEVALUE(O33))-LOOKUP(2,1/(($A$4:$A$500=A33)*($M$4:$M$500=M33)*($T$4:$T$500<>"")*($T$4:$T$500<IF(ISNUMBER(O33),MOD(O33,1),TIMEVALUE(O33)))),$T$4:$T$500))*1440),"") | Z33: =IFERROR(IF(Y33="","",IF(ROUND(Y33,0)<=15,"Cumple","No cumple")),"") | AB33: =IFERROR(IF(OR(O33="",R33=""),"",IF(IF(ISNUMBER(R33),MOD(R33,1),TIMEVALUE(R33))>=IF(ISNUMBER(O33),MOD(O33,1),TIMEVALUE(O33)),(IF(ISNUMBER(R33),MOD(R33,1),TIMEVALUE(R33))-IF(ISNUMBER(O33),MOD(O33,1),TIMEVALUE(O33)))*1440,(IF(ISNUMBER(R33),MOD(R33,1),TIMEVALUE(R33))+1-IF(ISNUMBER(O33),MOD(O33,1),TIMEVALUE(O33)))*1440)),"") | AC33: =IFERROR(IF(OR(R33="",S33=""),"",IF(IF(ISNUMBER(S33),MOD(S33,1),TIMEVALUE(S33))>=IF(ISNUMBER(R33),MOD(R33,1),TIMEVALUE(R33)),(IF(ISNUMBER(S33),MOD(S33,1),TIMEVALUE(S33))-IF(ISNUMBER(R33),MOD(R33,1),TIMEVALUE(R33)))*1440,(IF(ISNUMBER(S33),MOD(S33,1),TIMEVALUE(S33))+1-IF(ISNUMBER(R33),MOD(R33,1),TIMEVALUE(R33)))*1440)),"") | AD33: 45 | AE33: =IFERROR(IF(OR(AC33="",AD33=""),"",AC33-AD33),"") | AF33: =IFERROR(IF(AE33="","",IF(ROUND(AE33,0)>15,"Subestimacion",IF(ROUND(AE33,0)<-15,"Sobrestimacion","Asertivo"))),"") | AG33: Sin Suspensión | AM33: I0001187725 | AP33: =IF(A33="","",A33-WEEKDAY(A33,2)+1) | AQ33: =IF(AO33="","",AO33+6) | AR33: =IF(AO33="","","Semana "&TEXT(AO33,"dd-mm-yyyy")&" al "&TEXT(AP33,"dd-mm-yyyy")) | AS33: =IF(A33="","",TEXT(A33,"mmmm yyyy")) | AT33: =IF(A33="","",TEXT(A33,"dddd")) | AU33: =IF(A33="","","CRR-"&TEXT(A33,"yyyymmdd")&"-"&M33&"-"&TEXT(ROW()-3,"0000")) | AV33: =IF(A33="","",IF(OR(B33="",C33="",E33="",F33="",M33="",N33=""),"Revisar campos obligatorios",IF(AND(P33="Atraso primera hora",Q33=""),"Falta justificación atraso primera hora",IF(AND(Z33="No cumple",AA33=""),"Falta justificación recambio >15 min",IF(AND(ISNUMBER(SEARCH("suspend",N33)),OR(AG33="",AH33="")),"Falta causa/motivo suspensión","OK"))))) | AW33: =IF(N33="","",IF(ISNUMBER(SEARCH("suspend",N33)),IF(AND(AG33="",AH33=""),"Sin causa/motivo registrado",IF(AG33="",AH33,IF(AH33="",AG33,AG33&": "&AH33))),""))
A34: 46168 | B34: JESSICA ROSARIO | C34: NORAMBUENA | D34: 48a 5m 9d | E34: COLECISTECTOMIA POR VIDEOLAPAROSCOPIA, PROC. COMPLETO | F34: SERVICIO DE CIRUGIA ADULTO | H34: 1802081-10 | J34: =IF(H34<>"",IFERROR(VLOOKUP(IFERROR(LEFT(H34,FIND("-",H34)-1),H34),'Catalogo MINSAL'!A:E,5,FALSE),""),IF(I34<>"",IFERROR(VLOOKUP(IFERROR(LEFT(I34,FIND("-",I34)-1),I34),'Catalogo MINSAL'!A:E,5,FALSE),""),"")) | K34: Aliana Violeta Morales Ruiz | L34: Gonzalo Godoy Moya | M34: Quirofano 09 | N34: Atendido | O34: 0.625 | P34: =IFERROR(IF(OR(O34="",A34="",M34=""),"",IF(SUMPRODUCT(($A$4:$A$500=A34)*($M$4:$M$500=M34)*($O$4:$O$500<>"")*(MOD($O$4:$O$500,1)<MOD(O34,1)))=0,IF(MOD(O34,1)<=TIME(8,15,0),"Ingreso adecuado primera hora","Atraso primera hora"),"No aplica")),"") | R34: 0.65138889 | S34: 0.67638889 | T34: 0.69236111 | U34: =IFERROR(VLOOKUP(M34,'Horario Pabellones'!$A$4:$D$17,2,FALSE),"") | V34: =IFERROR(VLOOKUP(M34,'Horario Pabellones'!$A$4:$D$17,3,FALSE),"") | W34: =IFERROR(VLOOKUP(M34,'Horario Pabellones'!$A$4:$D$17,4,FALSE),"") | X34: =IFERROR(IF(OR(A34="",M34="",W34=""),"",(((_xludf.AGGREGATE(14,6,MOD($S$4:$S$500,1)/(($A$4:$A$500=A34)*($M$4:$M$500=M34)*($R$4:$R$500<>"")*($S$4:$S$500<>"")),1)-_xludf.AGGREGATE(15,6,MOD($R$4:$R$500,1)/(($A$4:$A$500=A34)*($M$4:$M$500=M34)*($R$4:$R$500<>"")*($S$4:$S$500<>"")),1))*1440)/60)/(W34/60)),"") | Y34: =IFERROR(IF(OR(O34="",A34="",M34=""),"",(IF(ISNUMBER(O34),MOD(O34,1),TIMEVALUE(O34))-LOOKUP(2,1/(($A$4:$A$500=A34)*($M$4:$M$500=M34)*($T$4:$T$500<>"")*($T$4:$T$500<IF(ISNUMBER(O34),MOD(O34,1),TIMEVALUE(O34)))),$T$4:$T$500))*1440),"") | Z34: =IFERROR(IF(Y34="","",IF(ROUND(Y34,0)<=15,"Cumple","No cumple")),"") | AB34: =IFERROR(IF(OR(O34="",R34=""),"",IF(IF(ISNUMBER(R34),MOD(R34,1),TIMEVALUE(R34))>=IF(ISNUMBER(O34),MOD(O34,1),TIMEVALUE(O34)),(IF(ISNUMBER(R34),MOD(R34,1),TIMEVALUE(R34))-IF(ISNUMBER(O34),MOD(O34,1),TIMEVALUE(O34)))*1440,(IF(ISNUMBER(R34),MOD(R34,1),TIMEVALUE(R34))+1-IF(ISNUMBER(O34),MOD(O34,1),TIMEVALUE(O34)))*1440)),"") | AC34: =IFERROR(IF(OR(R34="",S34=""),"",IF(IF(ISNUMBER(S34),MOD(S34,1),TIMEVALUE(S34))>=IF(ISNUMBER(R34),MOD(R34,1),TIMEVALUE(R34)),(IF(ISNUMBER(S34),MOD(S34,1),TIMEVALUE(S34))-IF(ISNUMBER(R34),MOD(R34,1),TIMEVALUE(R34)))*1440,(IF(ISNUMBER(S34),MOD(S34,1),TIMEVALUE(S34))+1-IF(ISNUMBER(R34),MOD(R34,1),TIMEVALUE(R34)))*1440)),"") | AD34: 45 | AE34: =IFERROR(IF(OR(AC34="",AD34=""),"",AC34-AD34),"") | AF34: =IFERROR(IF(AE34="","",IF(ROUND(AE34,0)>15,"Subestimacion",IF(ROUND(AE34,0)<-15,"Sobrestimacion","Asertivo"))),"") | AG34: Sin Suspensión | AM34: I0001187724 | AP34: =IF(A34="","",A34-WEEKDAY(A34,2)+1) | AQ34: =IF(AO34="","",AO34+6) | AR34: =IF(AO34="","","Semana "&TEXT(AO34,"dd-mm-yyyy")&" al "&TEXT(AP34,"dd-mm-yyyy")) | AS34: =IF(A34="","",TEXT(A34,"mmmm yyyy")) | AT34: =IF(A34="","",TEXT(A34,"dddd")) | AU34: =IF(A34="","","CRR-"&TEXT(A34,"yyyymmdd")&"-"&M34&"-"&TEXT(ROW()-3,"0000")) | AV34: =IF(A34="","",IF(OR(B34="",C34="",E34="",F34="",M34="",N34=""),"Revisar campos obligatorios",IF(AND(P34="Atraso primera hora",Q34=""),"Falta justificación atraso primera hora",IF(AND(Z34="No cumple",AA34=""),"Falta justificación recambio >15 min",IF(AND(ISNUMBER(SEARCH("suspend",N34)),OR(AG34="",AH34="")),"Falta causa/motivo suspensión","OK"))))) | AW34: =IF(N34="","",IF(ISNUMBER(SEARCH("suspend",N34)),IF(AND(AG34="",AH34=""),"Sin causa/motivo registrado",IF(AG34="",AH34,IF(AH34="",AG34,AG34&": "&AH34))),""))
A35: 46168 | B35: BEATRIZ SOLEDAD | C35: ROSALES | D35: 50a 8m 10d | E35: COLECISTECTOMIA POR VIDEOLAPAROSCOPIA, PROC. COMPLETO | F35: SERVICIO DE CIRUGIA ADULTO | H35: 1802081-10 | J35: =IF(H35<>"",IFERROR(VLOOKUP(IFERROR(LEFT(H35,FIND("-",H35)-1),H35),'Catalogo MINSAL'!A:E,5,FALSE),""),IF(I35<>"",IFERROR(VLOOKUP(IFERROR(LEFT(I35,FIND("-",I35)-1),I35),'Catalogo MINSAL'!A:E,5,FALSE),""),"")) | K35: Aliana Violeta Morales Ruiz | L35: Gonzalo Godoy Moya | M35: Quirofano 09 | N35: Recepcionado | O35: 0.70277778 | P35: =IFERROR(IF(OR(O35="",A35="",M35=""),"",IF(SUMPRODUCT(($A$4:$A$500=A35)*($M$4:$M$500=M35)*($O$4:$O$500<>"")*(MOD($O$4:$O$500,1)<MOD(O35,1)))=0,IF(MOD(O35,1)<=TIME(8,15,0),"Ingreso adecuado primera hora","Atraso primera hora"),"No aplica")),"") | R35: 0.74305556 | S35: 0.76388889 | T35: 0.77430556 | U35: =IFERROR(VLOOKUP(M35,'Horario Pabellones'!$A$4:$D$17,2,FALSE),"") | V35: =IFERROR(VLOOKUP(M35,'Horario Pabellones'!$A$4:$D$17,3,FALSE),"") | W35: =IFERROR(VLOOKUP(M35,'Horario Pabellones'!$A$4:$D$17,4,FALSE),"") | X35: =IFERROR(IF(OR(A35="",M35="",W35=""),"",(((_xludf.AGGREGATE(14,6,MOD($S$4:$S$500,1)/(($A$4:$A$500=A35)*($M$4:$M$500=M35)*($R$4:$R$500<>"")*($S$4:$S$500<>"")),1)-_xludf.AGGREGATE(15,6,MOD($R$4:$R$500,1)/(($A$4:$A$500=A35)*($M$4:$M$500=M35)*($R$4:$R$500<>"")*($S$4:$S$500<>"")),1))*1440)/60)/(W35/60)),"") | Y35: =IFERROR(IF(OR(O35="",A35="",M35=""),"",(IF(ISNUMBER(O35),MOD(O35,1),TIMEVALUE(O35))-LOOKUP(2,1/(($A$4:$A$500=A35)*($M$4:$M$500=M35)*($T$4:$T$500<>"")*($T$4:$T$500<IF(ISNUMBER(O35),MOD(O35,1),TIMEVALUE(O35)))),$T$4:$T$500))*1440),"") | Z35: =IFERROR(IF(Y35="","",IF(ROUND(Y35,0)<=15,"Cumple","No cumple")),"") | AB35: =IFERROR(IF(OR(O35="",R35=""),"",IF(IF(ISNUMBER(R35),MOD(R35,1),TIMEVALUE(R35))>=IF(ISNUMBER(O35),MOD(O35,1),TIMEVALUE(O35)),(IF(ISNUMBER(R35),MOD(R35,1),TIMEVALUE(R35))-IF(ISNUMBER(O35),MOD(O35,1),TIMEVALUE(O35)))*1440,(IF(ISNUMBER(R35),MOD(R35,1),TIMEVALUE(R35))+1-IF(ISNUMBER(O35),MOD(O35,1),TIMEVALUE(O35)))*1440)),"") | AC35: =IFERROR(IF(OR(R35="",S35=""),"",IF(IF(ISNUMBER(S35),MOD(S35,1),TIMEVALUE(S35))>=IF(ISNUMBER(R35),MOD(R35,1),TIMEVALUE(R35)),(IF(ISNUMBER(S35),MOD(S35,1),TIMEVALUE(S35))-IF(ISNUMBER(R35),MOD(R35,1),TIMEVALUE(R35)))*1440,(IF(ISNUMBER(S35),MOD(S35,1),TIMEVALUE(S35))+1-IF(ISNUMBER(R35),MOD(R35,1),TIMEVALUE(R35)))*1440)),"") | AD35: 40 | AE35: =IFERROR(IF(OR(AC35="",AD35=""),"",AC35-AD35),"") | AF35: =IFERROR(IF(AE35="","",IF(ROUND(AE35,0)>15,"Subestimacion",IF(ROUND(AE35,0)<-15,"Sobrestimacion","Asertivo"))),"") | AG35: Sin Suspensión | AM35: I0001187726 | AP35: =IF(A35="","",A35-WEEKDAY(A35,2)+1) | AQ35: =IF(AO35="","",AO35+6) | AR35: =IF(AO35="","","Semana "&TEXT(AO35,"dd-mm-yyyy")&" al "&TEXT(AP35,"dd-mm-yyyy")) | AS35: =IF(A35="","",TEXT(A35,"mmmm yyyy")) | AT35: =IF(A35="","",TEXT(A35,"dddd")) | AU35: =IF(A35="","","CRR-"&TEXT(A35,"yyyymmdd")&"-"&M35&"-"&TEXT(ROW()-3,"0000")) | AV35: =IF(A35="","",IF(OR(B35="",C35="",E35="",F35="",M35="",N35=""),"Revisar campos obligatorios",IF(AND(P35="Atraso primera hora",Q35=""),"Falta justificación atraso primera hora",IF(AND(Z35="No cumple",AA35=""),"Falta justificación recambio >15 min",IF(AND(ISNUMBER(SEARCH("suspend",N35)),OR(AG35="",AH35="")),"Falta causa/motivo suspensión","OK"))))) | AW35: =IF(N35="","",IF(ISNUMBER(SEARCH("suspend",N35)),IF(AND(AG35="",AH35=""),"Sin causa/motivo registrado",IF(AG35="",AH35,IF(AH35="",AG35,AG35&": "&AH35))),""))
A36: 46168 | B36: RUTH XIMENA | C36: DOMINGUAL | D36: 41a 3m 27d | E36: COLECISTECTOMIA POR VIDEOLAPAROSCOPIA, PROC. COMPLETO | F36: SERVICIO DE CIRUGIA ADULTO | H36: 1802081-10 | J36: =IF(H36<>"",IFERROR(VLOOKUP(IFERROR(LEFT(H36,FIND("-",H36)-1),H36),'Catalogo MINSAL'!A:E,5,FALSE),""),IF(I36<>"",IFERROR(VLOOKUP(IFERROR(LEFT(I36,FIND("-",I36)-1),I36),'Catalogo MINSAL'!A:E,5,FALSE),""),"")) | K36: Aliana Violeta Morales Ruiz | L36: Gonzalo Godoy Moya | M36: Quirofano 09 | N36: Suspendido | P36: =IFERROR(IF(OR(O36="",A36="",M36=""),"",IF(SUMPRODUCT(($A$4:$A$500=A36)*($M$4:$M$500=M36)*($O$4:$O$500<>"")*(MOD($O$4:$O$500,1)<MOD(O36,1)))=0,IF(MOD(O36,1)<=TIME(8,15,0),"Ingreso adecuado primera hora","Atraso primera hora"),"No aplica")),"") | U36: =IFERROR(VLOOKUP(M36,'Horario Pabellones'!$A$4:$D$17,2,FALSE),"") | V36: =IFERROR(VLOOKUP(M36,'Horario Pabellones'!$A$4:$D$17,3,FALSE),"") | W36: =IFERROR(VLOOKUP(M36,'Horario Pabellones'!$A$4:$D$17,4,FALSE),"") | X36: =IFERROR(IF(OR(A36="",M36="",W36=""),"",(((_xludf.AGGREGATE(14,6,MOD($S$4:$S$500,1)/(($A$4:$A$500=A36)*($M$4:$M$500=M36)*($R$4:$R$500<>"")*($S$4:$S$500<>"")),1)-_xludf.AGGREGATE(15,6,MOD($R$4:$R$500,1)/(($A$4:$A$500=A36)*($M$4:$M$500=M36)*($R$4:$R$500<>"")*($S$4:$S$500<>"")),1))*1440)/60)/(W36/60)),"") | Y36: =IFERROR(IF(OR(O36="",A36="",M36=""),"",(IF(ISNUMBER(O36),MOD(O36,1),TIMEVALUE(O36))-LOOKUP(2,1/(($A$4:$A$500=A36)*($M$4:$M$500=M36)*($T$4:$T$500<>"")*($T$4:$T$500<IF(ISNUMBER(O36),MOD(O36,1),TIMEVALUE(O36)))),$T$4:$T$500))*1440),"") | Z36: =IFERROR(IF(Y36="","",IF(ROUND(Y36,0)<=15,"Cumple","No cumple")),"") | AB36: =IFERROR(IF(OR(O36="",R36=""),"",IF(IF(ISNUMBER(R36),MOD(R36,1),TIMEVALUE(R36))>=IF(ISNUMBER(O36),MOD(O36,1),TIMEVALUE(O36)),(IF(ISNUMBER(R36),MOD(R36,1),TIMEVALUE(R36))-IF(ISNUMBER(O36),MOD(O36,1),TIMEVALUE(O36)))*1440,(IF(ISNUMBER(R36),MOD(R36,1),TIMEVALUE(R36))+1-IF(ISNUMBER(O36),MOD(O36,1),TIMEVALUE(O36)))*1440)),"") | AC36: =IFERROR(IF(OR(R36="",S36=""),"",IF(IF(ISNUMBER(S36),MOD(S36,1),TIMEVALUE(S36))>=IF(ISNUMBER(R36),MOD(R36,1),TIMEVALUE(R36)),(IF(ISNUMBER(S36),MOD(S36,1),TIMEVALUE(S36))-IF(ISNUMBER(R36),MOD(R36,1),TIMEVALUE(R36)))*1440,(IF(ISNUMBER(S36),MOD(S36,1),TIMEVALUE(S36))+1-IF(ISNUMBER(R36),MOD(R36,1),TIMEVALUE(R36)))*1440)),"") | AD36: 60 | AE36: =IFERROR(IF(OR(AC36="",AD36=""),"",AC36-AD36),"") | AF36: =IFERROR(IF(AE36="","",IF(ROUND(AE36,0)>15,"Subestimacion",IF(ROUND(AE36,0)<-15,"Sobrestimacion","Asertivo"))),"") | AG36: Error de programación | AM36: I0001187728 | AP36: =IF(A36="","",A36-WEEKDAY(A36,2)+1) | AQ36: =IF(AO36="","",AO36+6) | AR36: =IF(AO36="","","Semana "&TEXT(AO36,"dd-mm-yyyy")&" al "&TEXT(AP36,"dd-mm-yyyy")) | AS36: =IF(A36="","",TEXT(A36,"mmmm yyyy")) | AT36: =IF(A36="","",TEXT(A36,"dddd")) | AU36: =IF(A36="","","CRR-"&TEXT(A36,"yyyymmdd")&"-"&M36&"-"&TEXT(ROW()-3,"0000")) | AV36: =IF(A36="","",IF(OR(B36="",C36="",E36="",F36="",M36="",N36=""),"Revisar campos obligatorios",IF(AND(P36="Atraso primera hora",Q36=""),"Falta justificación atraso primera hora",IF(AND(Z36="No cumple",AA36=""),"Falta justificación recambio >15 min",IF(AND(ISNUMBER(SEARCH("suspend",N36)),OR(AG36="",AH36="")),"Falta causa/motivo suspensión","OK"))))) | AW36: =IF(N36="","",IF(ISNUMBER(SEARCH("suspend",N36)),IF(AND(AG36="",AH36=""),"Sin causa/motivo registrado",IF(AG36="",AH36,IF(AH36="",AG36,AG36&": "&AH36))),""))
A37: 46169 | B37: SALVADOR ALONSO | C37: SILVA | D37: 3a 11m 14d | E37: AMIGDALECTOMIA C/S ADENOIDECTOMIA, UNI O BILATERAL | F37: SERVICIO DE CIRUGIA ADULTO | H37: 1302029-5 | J37: =IF(H37<>"",IFERROR(VLOOKUP(IFERROR(LEFT(H37,FIND("-",H37)-1),H37),'Catalogo MINSAL'!A:E,5,FALSE),""),IF(I37<>"",IFERROR(VLOOKUP(IFERROR(LEFT(I37,FIND("-",I37)-1),I37),'Catalogo MINSAL'!A:E,5,FALSE),""),"")) | K37: Jackeline Nuñez | L37: Dr. Pablo Acuña Espinoza | M37: Quirofano 06 | N37: Atendido | O37: 0.375 | P37: =IFERROR(IF(OR(O37="",A37="",M37=""),"",IF(SUMPRODUCT(($A$4:$A$500=A37)*($M$4:$M$500=M37)*($O$4:$O$500<>"")*(MOD($O$4:$O$500,1)<MOD(O37,1)))=0,IF(MOD(O37,1)<=TIME(8,15,0),"Ingreso adecuado primera hora","Atraso primera hora"),"No aplica")),"") | R37: 0.37847222 | S37: 0.39583333 | T37: 0.40972222 | U37: =IFERROR(VLOOKUP(M37,'Horario Pabellones'!$A$4:$D$17,2,FALSE),"") | V37: =IFERROR(VLOOKUP(M37,'Horario Pabellones'!$A$4:$D$17,3,FALSE),"") | W37: =IFERROR(VLOOKUP(M37,'Horario Pabellones'!$A$4:$D$17,4,FALSE),"") | X37: =IFERROR(IF(OR(A37="",M37="",W37=""),"",(((_xludf.AGGREGATE(14,6,MOD($S$4:$S$500,1)/(($A$4:$A$500=A37)*($M$4:$M$500=M37)*($R$4:$R$500<>"")*($S$4:$S$500<>"")),1)-_xludf.AGGREGATE(15,6,MOD($R$4:$R$500,1)/(($A$4:$A$500=A37)*($M$4:$M$500=M37)*($R$4:$R$500<>"")*($S$4:$S$500<>"")),1))*1440)/60)/(W37/60)),"") | Y37: =IFERROR(IF(OR(O37="",A37="",M37=""),"",(IF(ISNUMBER(O37),MOD(O37,1),TIMEVALUE(O37))-LOOKUP(2,1/(($A$4:$A$500=A37)*($M$4:$M$500=M37)*($T$4:$T$500<>"")*($T$4:$T$500<IF(ISNUMBER(O37),MOD(O37,1),TIMEVALUE(O37)))),$T$4:$T$500))*1440),"") | Z37: =IFERROR(IF(Y37="","",IF(ROUND(Y37,0)<=15,"Cumple","No cumple")),"") | AB37: =IFERROR(IF(OR(O37="",R37=""),"",IF(IF(ISNUMBER(R37),MOD(R37,1),TIMEVALUE(R37))>=IF(ISNUMBER(O37),MOD(O37,1),TIMEVALUE(O37)),(IF(ISNUMBER(R37),MOD(R37,1),TIMEVALUE(R37))-IF(ISNUMBER(O37),MOD(O37,1),TIMEVALUE(O37)))*1440,(IF(ISNUMBER(R37),MOD(R37,1),TIMEVALUE(R37))+1-IF(ISNUMBER(O37),MOD(O37,1),TIMEVALUE(O37)))*1440)),"") | AC37: =IFERROR(IF(OR(R37="",S37=""),"",IF(IF(ISNUMBER(S37),MOD(S37,1),TIMEVALUE(S37))>=IF(ISNUMBER(R37),MOD(R37,1),TIMEVALUE(R37)),(IF(ISNUMBER(S37),MOD(S37,1),TIMEVALUE(S37))-IF(ISNUMBER(R37),MOD(R37,1),TIMEVALUE(R37)))*1440,(IF(ISNUMBER(S37),MOD(S37,1),TIMEVALUE(S37))+1-IF(ISNUMBER(R37),MOD(R37,1),TIMEVALUE(R37)))*1440)),"") | AD37: 60 | AE37: =IFERROR(IF(OR(AC37="",AD37=""),"",AC37-AD37),"") | AF37: =IFERROR(IF(AE37="","",IF(ROUND(AE37,0)>15,"Subestimacion",IF(ROUND(AE37,0)<-15,"Sobrestimacion","Asertivo"))),"") | AG37: Sin Suspensión | AM37: I0001188095 | AP37: =IF(A37="","",A37-WEEKDAY(A37,2)+1) | AQ37: =IF(AO37="","",AO37+6) | AR37: =IF(AO37="","","Semana "&TEXT(AO37,"dd-mm-yyyy")&" al "&TEXT(AP37,"dd-mm-yyyy")) | AS37: =IF(A37="","",TEXT(A37,"mmmm yyyy")) | AT37: =IF(A37="","",TEXT(A37,"dddd")) | AU37: =IF(A37="","","CRR-"&TEXT(A37,"yyyymmdd")&"-"&M37&"-"&TEXT(ROW()-3,"0000")) | AV37: =IF(A37="","",IF(OR(B37="",C37="",E37="",F37="",M37="",N37=""),"Revisar campos obligatorios",IF(AND(P37="Atraso primera hora",Q37=""),"Falta justificación atraso primera hora",IF(AND(Z37="No cumple",AA37=""),"Falta justificación recambio >15 min",IF(AND(ISNUMBER(SEARCH("suspend",N37)),OR(AG37="",AH37="")),"Falta causa/motivo suspensión","OK"))))) | AW37: =IF(N37="","",IF(ISNUMBER(SEARCH("suspend",N37)),IF(AND(AG37="",AH37=""),"Sin causa/motivo registrado",IF(AG37="",AH37,IF(AH37="",AG37,AG37&": "&AH37))),""))
A38: 46169 | B38: NINOSKA ANDREA | C38: GONZÁLEZ | D38: 37a 8m 23d | E38: AMIGDALECTOMIA C/S ADENOIDECTOMIA, UNI O BILATERAL | F38: SERVICIO DE CIRUGIA ADULTO | H38: 1302029-5 | J38: =IF(H38<>"",IFERROR(VLOOKUP(IFERROR(LEFT(H38,FIND("-",H38)-1),H38),'Catalogo MINSAL'!A:E,5,FALSE),""),IF(I38<>"",IFERROR(VLOOKUP(IFERROR(LEFT(I38,FIND("-",I38)-1),I38),'Catalogo MINSAL'!A:E,5,FALSE),""),"")) | K38: Jackeline Nuñez | L38: Dr. Pablo Acuña Espinoza | M38: Quirofano 06 | N38: Atendido | O38: 0.42013889 | P38: =IFERROR(IF(OR(O38="",A38="",M38=""),"",IF(SUMPRODUCT(($A$4:$A$500=A38)*($M$4:$M$500=M38)*($O$4:$O$500<>"")*(MOD($O$4:$O$500,1)<MOD(O38,1)))=0,IF(MOD(O38,1)<=TIME(8,15,0),"Ingreso adecuado primera hora","Atraso primera hora"),"No aplica")),"") | R38: 0.43402778 | S38: 0.46875 | T38: 0.48472222 | U38: =IFERROR(VLOOKUP(M38,'Horario Pabellones'!$A$4:$D$17,2,FALSE),"") | V38: =IFERROR(VLOOKUP(M38,'Horario Pabellones'!$A$4:$D$17,3,FALSE),"") | W38: =IFERROR(VLOOKUP(M38,'Horario Pabellones'!$A$4:$D$17,4,FALSE),"") | X38: =IFERROR(IF(OR(A38="",M38="",W38=""),"",(((_xludf.AGGREGATE(14,6,MOD($S$4:$S$500,1)/(($A$4:$A$500=A38)*($M$4:$M$500=M38)*($R$4:$R$500<>"")*($S$4:$S$500<>"")),1)-_xludf.AGGREGATE(15,6,MOD($R$4:$R$500,1)/(($A$4:$A$500=A38)*($M$4:$M$500=M38)*($R$4:$R$500<>"")*($S$4:$S$500<>"")),1))*1440)/60)/(W38/60)),"") | Y38: =IFERROR(IF(OR(O38="",A38="",M38=""),"",(IF(ISNUMBER(O38),MOD(O38,1),TIMEVALUE(O38))-LOOKUP(2,1/(($A$4:$A$500=A38)*($M$4:$M$500=M38)*($T$4:$T$500<>"")*($T$4:$T$500<IF(ISNUMBER(O38),MOD(O38,1),TIMEVALUE(O38)))),$T$4:$T$500))*1440),"") | Z38: =IFERROR(IF(Y38="","",IF(ROUND(Y38,0)<=15,"Cumple","No cumple")),"") | AB38: =IFERROR(IF(OR(O38="",R38=""),"",IF(IF(ISNUMBER(R38),MOD(R38,1),TIMEVALUE(R38))>=IF(ISNUMBER(O38),MOD(O38,1),TIMEVALUE(O38)),(IF(ISNUMBER(R38),MOD(R38,1),TIMEVALUE(R38))-IF(ISNUMBER(O38),MOD(O38,1),TIMEVALUE(O38)))*1440,(IF(ISNUMBER(R38),MOD(R38,1),TIMEVALUE(R38))+1-IF(ISNUMBER(O38),MOD(O38,1),TIMEVALUE(O38)))*1440)),"") | AC38: =IFERROR(IF(OR(R38="",S38=""),"",IF(IF(ISNUMBER(S38),MOD(S38,1),TIMEVALUE(S38))>=IF(ISNUMBER(R38),MOD(R38,1),TIMEVALUE(R38)),(IF(ISNUMBER(S38),MOD(S38,1),TIMEVALUE(S38))-IF(ISNUMBER(R38),MOD(R38,1),TIMEVALUE(R38)))*1440,(IF(ISNUMBER(S38),MOD(S38,1),TIMEVALUE(S38))+1-IF(ISNUMBER(R38),MOD(R38,1),TIMEVALUE(R38)))*1440)),"") | AD38: 60 | AE38: =IFERROR(IF(OR(AC38="",AD38=""),"",AC38-AD38),"") | AF38: =IFERROR(IF(AE38="","",IF(ROUND(AE38,0)>15,"Subestimacion",IF(ROUND(AE38,0)<-15,"Sobrestimacion","Asertivo"))),"") | AG38: Sin Suspensión | AM38: I0001188096 | AP38: =IF(A38="","",A38-WEEKDAY(A38,2)+1) | AQ38: =IF(AO38="","",AO38+6) | AR38: =IF(AO38="","","Semana "&TEXT(AO38,"dd-mm-yyyy")&" al "&TEXT(AP38,"dd-mm-yyyy")) | AS38: =IF(A38="","",TEXT(A38,"mmmm yyyy")) | AT38: =IF(A38="","",TEXT(A38,"dddd")) | AU38: =IF(A38="","","CRR-"&TEXT(A38,"yyyymmdd")&"-"&M38&"-"&TEXT(ROW()-3,"0000")) | AV38: =IF(A38="","",IF(OR(B38="",C38="",E38="",F38="",M38="",N38=""),"Revisar campos obligatorios",IF(AND(P38="Atraso primera hora",Q38=""),"Falta justificación atraso primera hora",IF(AND(Z38="No cumple",AA38=""),"Falta justificación recambio >15 min",IF(AND(ISNUMBER(SEARCH("suspend",N38)),OR(AG38="",AH38="")),"Falta causa/motivo suspensión","OK"))))) | AW38: =IF(N38="","",IF(ISNUMBER(SEARCH("suspend",N38)),IF(AND(AG38="",AH38=""),"Sin causa/motivo registrado",IF(AG38="",AH38,IF(AH38="",AG38,AG38&": "&AH38))),""))
A39: 46169 | B39: KETTELENE | C39: ORILUS | D39: 29a 2m 4d | E39: Turbinectomía o cauterización de cornetes, cualquier técnica | F39: SERVICIO DE CIRUGIA ADULTO | H39: 1302042-4 | J39: =IF(H39<>"",IFERROR(VLOOKUP(IFERROR(LEFT(H39,FIND("-",H39)-1),H39),'Catalogo MINSAL'!A:E,5,FALSE),""),IF(I39<>"",IFERROR(VLOOKUP(IFERROR(LEFT(I39,FIND("-",I39)-1),I39),'Catalogo MINSAL'!A:E,5,FALSE),""),"")) | K39: Jackeline Nuñez | L39: Hector Contreras Pinto | M39: Quirofano 06 | N39: Recepcionado | O39: 0.60416667 | P39: =IFERROR(IF(OR(O39="",A39="",M39=""),"",IF(SUMPRODUCT(($A$4:$A$500=A39)*($M$4:$M$500=M39)*($O$4:$O$500<>"")*(MOD($O$4:$O$500,1)<MOD(O39,1)))=0,IF(MOD(O39,1)<=TIME(8,15,0),"Ingreso adecuado primera hora","Atraso primera hora"),"No aplica")),"") | R39: 0.61458333 | S39: 0.63194444 | T39: 0.64583333 | U39: =IFERROR(VLOOKUP(M39,'Horario Pabellones'!$A$4:$D$17,2,FALSE),"") | V39: =IFERROR(VLOOKUP(M39,'Horario Pabellones'!$A$4:$D$17,3,FALSE),"") | W39: =IFERROR(VLOOKUP(M39,'Horario Pabellones'!$A$4:$D$17,4,FALSE),"") | X39: =IFERROR(IF(OR(A39="",M39="",W39=""),"",(((_xludf.AGGREGATE(14,6,MOD($S$4:$S$500,1)/(($A$4:$A$500=A39)*($M$4:$M$500=M39)*($R$4:$R$500<>"")*($S$4:$S$500<>"")),1)-_xludf.AGGREGATE(15,6,MOD($R$4:$R$500,1)/(($A$4:$A$500=A39)*($M$4:$M$500=M39)*($R$4:$R$500<>"")*($S$4:$S$500<>"")),1))*1440)/60)/(W39/60)),"") | Y39: =IFERROR(IF(OR(O39="",A39="",M39=""),"",(IF(ISNUMBER(O39),MOD(O39,1),TIMEVALUE(O39))-LOOKUP(2,1/(($A$4:$A$500=A39)*($M$4:$M$500=M39)*($T$4:$T$500<>"")*($T$4:$T$500<IF(ISNUMBER(O39),MOD(O39,1),TIMEVALUE(O39)))),$T$4:$T$500))*1440),"") | Z39: =IFERROR(IF(Y39="","",IF(ROUND(Y39,0)<=15,"Cumple","No cumple")),"") | AB39: =IFERROR(IF(OR(O39="",R39=""),"",IF(IF(ISNUMBER(R39),MOD(R39,1),TIMEVALUE(R39))>=IF(ISNUMBER(O39),MOD(O39,1),TIMEVALUE(O39)),(IF(ISNUMBER(R39),MOD(R39,1),TIMEVALUE(R39))-IF(ISNUMBER(O39),MOD(O39,1),TIMEVALUE(O39)))*1440,(IF(ISNUMBER(R39),MOD(R39,1),TIMEVALUE(R39))+1-IF(ISNUMBER(O39),MOD(O39,1),TIMEVALUE(O39)))*1440)),"") | AC39: =IFERROR(IF(OR(R39="",S39=""),"",IF(IF(ISNUMBER(S39),MOD(S39,1),TIMEVALUE(S39))>=IF(ISNUMBER(R39),MOD(R39,1),TIMEVALUE(R39)),(IF(ISNUMBER(S39),MOD(S39,1),TIMEVALUE(S39))-IF(ISNUMBER(R39),MOD(R39,1),TIMEVALUE(R39)))*1440,(IF(ISNUMBER(S39),MOD(S39,1),TIMEVALUE(S39))+1-IF(ISNUMBER(R39),MOD(R39,1),TIMEVALUE(R39)))*1440)),"") | AD39: 60 | AE39: =IFERROR(IF(OR(AC39="",AD39=""),"",AC39-AD39),"") | AF39: =IFERROR(IF(AE39="","",IF(ROUND(AE39,0)>15,"Subestimacion",IF(ROUND(AE39,0)<-15,"Sobrestimacion","Asertivo"))),"") | AG39: Sin Suspensión | AM39: I0001188101 | AP39: =IF(A39="","",A39-WEEKDAY(A39,2)+1) | AQ39: =IF(AO39="","",AO39+6) | AR39: =IF(AO39="","","Semana "&TEXT(AO39,"dd-mm-yyyy")&" al "&TEXT(AP39,"dd-mm-yyyy")) | AS39: =IF(A39="","",TEXT(A39,"mmmm yyyy")) | AT39: =IF(A39="","",TEXT(A39,"dddd")) | AU39: =IF(A39="","","CRR-"&TEXT(A39,"yyyymmdd")&"-"&M39&"-"&TEXT(ROW()-3,"0000")) | AV39: =IF(A39="","",IF(OR(B39="",C39="",E39="",F39="",M39="",N39=""),"Revisar campos obligatorios",IF(AND(P39="Atraso primera hora",Q39=""),"Falta justificación atraso primera hora",IF(AND(Z39="No cumple",AA39=""),"Falta justificación recambio >15 min",IF(AND(ISNUMBER(SEARCH("suspend",N39)),OR(AG39="",AH39="")),"Falta causa/motivo suspensión","OK"))))) | AW39: =IF(N39="","",IF(ISNUMBER(SEARCH("suspend",N39)),IF(AND(AG39="",AH39=""),"Sin causa/motivo registrado",IF(AG39="",AH39,IF(AH39="",AG39,AG39&": "&AH39))),""))
A40: 46169 | B40: PABLO ANDRES | C40: ALARCÓN | D40: 4a 5m 25d | E40: Extracción cuerpo extraño en conducto auditivo externo | F40: SERVICIO DE CIRUGIA ADULTO | H40: 1302002-3 | J40: =IF(H40<>"",IFERROR(VLOOKUP(IFERROR(LEFT(H40,FIND("-",H40)-1),H40),'Catalogo MINSAL'!A:E,5,FALSE),""),IF(I40<>"",IFERROR(VLOOKUP(IFERROR(LEFT(I40,FIND("-",I40)-1),I40),'Catalogo MINSAL'!A:E,5,FALSE),""),"")) | K40: Valentina Fernanda Silva Barreto | L40: Dr. Pablo Acuña Espinoza | M40: Quirofano 06 | N40: Suspendido | P40: =IFERROR(IF(OR(O40="",A40="",M40=""),"",IF(SUMPRODUCT(($A$4:$A$500=A40)*($M$4:$M$500=M40)*($O$4:$O$500<>"")*(MOD($O$4:$O$500,1)<MOD(O40,1)))=0,IF(MOD(O40,1)<=TIME(8,15,0),"Ingreso adecuado primera hora","Atraso primera hora"),"No aplica")),"") | U40: =IFERROR(VLOOKUP(M40,'Horario Pabellones'!$A$4:$D$17,2,FALSE),"") | V40: =IFERROR(VLOOKUP(M40,'Horario Pabellones'!$A$4:$D$17,3,FALSE),"") | W40: =IFERROR(VLOOKUP(M40,'Horario Pabellones'!$A$4:$D$17,4,FALSE),"") | X40: =IFERROR(IF(OR(A40="",M40="",W40=""),"",(((_xludf.AGGREGATE(14,6,MOD($S$4:$S$500,1)/(($A$4:$A$500=A40)*($M$4:$M$500=M40)*($R$4:$R$500<>"")*($S$4:$S$500<>"")),1)-_xludf.AGGREGATE(15,6,MOD($R$4:$R$500,1)/(($A$4:$A$500=A40)*($M$4:$M$500=M40)*($R$4:$R$500<>"")*($S$4:$S$500<>"")),1))*1440)/60)/(W40/60)),"") | Y40: =IFERROR(IF(OR(O40="",A40="",M40=""),"",(IF(ISNUMBER(O40),MOD(O40,1),TIMEVALUE(O40))-LOOKUP(2,1/(($A$4:$A$500=A40)*($M$4:$M$500=M40)*($T$4:$T$500<>"")*($T$4:$T$500<IF(ISNUMBER(O40),MOD(O40,1),TIMEVALUE(O40)))),$T$4:$T$500))*1440),"") | Z40: =IFERROR(IF(Y40="","",IF(ROUND(Y40,0)<=15,"Cumple","No cumple")),"") | AB40: =IFERROR(IF(OR(O40="",R40=""),"",IF(IF(ISNUMBER(R40),MOD(R40,1),TIMEVALUE(R40))>=IF(ISNUMBER(O40),MOD(O40,1),TIMEVALUE(O40)),(IF(ISNUMBER(R40),MOD(R40,1),TIMEVALUE(R40))-IF(ISNUMBER(O40),MOD(O40,1),TIMEVALUE(O40)))*1440,(IF(ISNUMBER(R40),MOD(R40,1),TIMEVALUE(R40))+1-IF(ISNUMBER(O40),MOD(O40,1),TIMEVALUE(O40)))*1440)),"") | AC40: =IFERROR(IF(OR(R40="",S40=""),"",IF(IF(ISNUMBER(S40),MOD(S40,1),TIMEVALUE(S40))>=IF(ISNUMBER(R40),MOD(R40,1),TIMEVALUE(R40)),(IF(ISNUMBER(S40),MOD(S40,1),TIMEVALUE(S40))-IF(ISNUMBER(R40),MOD(R40,1),TIMEVALUE(R40)))*1440,(IF(ISNUMBER(S40),MOD(S40,1),TIMEVALUE(S40))+1-IF(ISNUMBER(R40),MOD(R40,1),TIMEVALUE(R40)))*1440)),"") | AD40: 60 | AE40: =IFERROR(IF(OR(AC40="",AD40=""),"",AC40-AD40),"") | AF40: =IFERROR(IF(AE40="","",IF(ROUND(AE40,0)>15,"Subestimacion",IF(ROUND(AE40,0)<-15,"Sobrestimacion","Asertivo"))),"") | AG40: Falta de preparación de piel, intestinal, antibiótica u otra específica | AM40: I0001188094 | AP40: =IF(A40="","",A40-WEEKDAY(A40,2)+1) | AQ40: =IF(AO40="","",AO40+6) | AR40: =IF(AO40="","","Semana "&TEXT(AO40,"dd-mm-yyyy")&" al "&TEXT(AP40,"dd-mm-yyyy")) | AS40: =IF(A40="","",TEXT(A40,"mmmm yyyy")) | AT40: =IF(A40="","",TEXT(A40,"dddd")) | AU40: =IF(A40="","","CRR-"&TEXT(A40,"yyyymmdd")&"-"&M40&"-"&TEXT(ROW()-3,"0000")) | AV40: =IF(A40="","",IF(OR(B40="",C40="",E40="",F40="",M40="",N40=""),"Revisar campos obligatorios",IF(AND(P40="Atraso primera hora",Q40=""),"Falta justificación atraso primera hora",IF(AND(Z40="No cumple",AA40=""),"Falta justificación recambio >15 min",IF(AND(ISNUMBER(SEARCH("suspend",N40)),OR(AG40="",AH40="")),"Falta causa/motivo suspensión","OK"))))) | AW40: =IF(N40="","",IF(ISNUMBER(SEARCH("suspend",N40)),IF(AND(AG40="",AH40=""),"Sin causa/motivo registrado",IF(AG40="",AH40,IF(AH40="",AG40,AG40&": "&AH40))),""))
A41: 46169 | B41: MARGARITA JAVIERA | C41: TARRÉS | D41: 69a 10m 24d | E41: Antrostomía seno maxilar, cualquier vía | F41: SERVICIO DE CIRUGIA ADULTO | H41: 1302055-6 | J41: =IF(H41<>"",IFERROR(VLOOKUP(IFERROR(LEFT(H41,FIND("-",H41)-1),H41),'Catalogo MINSAL'!A:E,5,FALSE),""),IF(I41<>"",IFERROR(VLOOKUP(IFERROR(LEFT(I41,FIND("-",I41)-1),I41),'Catalogo MINSAL'!A:E,5,FALSE),""),"")) | K41: Valentina Fernanda Silva Barreto | L41: Dr. Pablo Acuña Espinoza | M41: Quirofano 06 | N41: Suspendido | P41: =IFERROR(IF(OR(O41="",A41="",M41=""),"",IF(SUMPRODUCT(($A$4:$A$500=A41)*($M$4:$M$500=M41)*($O$4:$O$500<>"")*(MOD($O$4:$O$500,1)<MOD(O41,1)))=0,IF(MOD(O41,1)<=TIME(8,15,0),"Ingreso adecuado primera hora","Atraso primera hora"),"No aplica")),"") | U41: =IFERROR(VLOOKUP(M41,'Horario Pabellones'!$A$4:$D$17,2,FALSE),"") | V41: =IFERROR(VLOOKUP(M41,'Horario Pabellones'!$A$4:$D$17,3,FALSE),"") | W41: =IFERROR(VLOOKUP(M41,'Horario Pabellones'!$A$4:$D$17,4,FALSE),"") | X41: =IFERROR(IF(OR(A41="",M41="",W41=""),"",(((_xludf.AGGREGATE(14,6,MOD($S$4:$S$500,1)/(($A$4:$A$500=A41)*($M$4:$M$500=M41)*($R$4:$R$500<>"")*($S$4:$S$500<>"")),1)-_xludf.AGGREGATE(15,6,MOD($R$4:$R$500,1)/(($A$4:$A$500=A41)*($M$4:$M$500=M41)*($R$4:$R$500<>"")*($S$4:$S$500<>"")),1))*1440)/60)/(W41/60)),"") | Y41: =IFERROR(IF(OR(O41="",A41="",M41=""),"",(IF(ISNUMBER(O41),MOD(O41,1),TIMEVALUE(O41))-LOOKUP(2,1/(($A$4:$A$500=A41)*($M$4:$M$500=M41)*($T$4:$T$500<>"")*($T$4:$T$500<IF(ISNUMBER(O41),MOD(O41,1),TIMEVALUE(O41)))),$T$4:$T$500))*1440),"") | Z41: =IFERROR(IF(Y41="","",IF(ROUND(Y41,0)<=15,"Cumple","No cumple")),"") | AB41: =IFERROR(IF(OR(O41="",R41=""),"",IF(IF(ISNUMBER(R41),MOD(R41,1),TIMEVALUE(R41))>=IF(ISNUMBER(O41),MOD(O41,1),TIMEVALUE(O41)),(IF(ISNUMBER(R41),MOD(R41,1),TIMEVALUE(R41))-IF(ISNUMBER(O41),MOD(O41,1),TIMEVALUE(O41)))*1440,(IF(ISNUMBER(R41),MOD(R41,1),TIMEVALUE(R41))+1-IF(ISNUMBER(O41),MOD(O41,1),TIMEVALUE(O41)))*1440)),"") | AC41: =IFERROR(IF(OR(R41="",S41=""),"",IF(IF(ISNUMBER(S41),MOD(S41,1),TIMEVALUE(S41))>=IF(ISNUMBER(R41),MOD(R41,1),TIMEVALUE(R41)),(IF(ISNUMBER(S41),MOD(S41,1),TIMEVALUE(S41))-IF(ISNUMBER(R41),MOD(R41,1),TIMEVALUE(R41)))*1440,(IF(ISNUMBER(S41),MOD(S41,1),TIMEVALUE(S41))+1-IF(ISNUMBER(R41),MOD(R41,1),TIMEVALUE(R41)))*1440)),"") | AD41: 60 | AE41: =IFERROR(IF(OR(AC41="",AD41=""),"",AC41-AD41),"") | AF41: =IFERROR(IF(AE41="","",IF(ROUND(AE41,0)>15,"Subestimacion",IF(ROUND(AE41,0)<-15,"Sobrestimacion","Asertivo"))),"") | AG41: Instrumental y/o material con falla de esterilización | AM41: I0001188099 | AP41: =IF(A41="","",A41-WEEKDAY(A41,2)+1) | AQ41: =IF(AO41="","",AO41+6) | AR41: =IF(AO41="","","Semana "&TEXT(AO41,"dd-mm-yyyy")&" al "&TEXT(AP41,"dd-mm-yyyy")) | AS41: =IF(A41="","",TEXT(A41,"mmmm yyyy")) | AT41: =IF(A41="","",TEXT(A41,"dddd")) | AU41: =IF(A41="","","CRR-"&TEXT(A41,"yyyymmdd")&"-"&M41&"-"&TEXT(ROW()-3,"0000")) | AV41: =IF(A41="","",IF(OR(B41="",C41="",E41="",F41="",M41="",N41=""),"Revisar campos obligatorios",IF(AND(P41="Atraso primera hora",Q41=""),"Falta justificación atraso primera hora",IF(AND(Z41="No cumple",AA41=""),"Falta justificación recambio >15 min",IF(AND(ISNUMBER(SEARCH("suspend",N41)),OR(AG41="",AH41="")),"Falta causa/motivo suspensión","OK"))))) | AW41: =IF(N41="","",IF(ISNUMBER(SEARCH("suspend",N41)),IF(AND(AG41="",AH41=""),"Sin causa/motivo registrado",IF(AG41="",AH41,IF(AH41="",AG41,AG41&": "&AH41))),""))
A42: 46169 | B42: MARÍA ADELA | C42: PALMA | D42: 67a 10m 7d | E42: - FACOERESIS EXTRACAPSULAR CON IMPLANTE DE LENTE INTRAOCULAR (NO INCLUYE EL VALOR DE LA PROTESIS) | F42: UNIDAD DE OFTALMOLOGIA | H42: 1202064-10 | J42: =IF(H42<>"",IFERROR(VLOOKUP(IFERROR(LEFT(H42,FIND("-",H42)-1),H42),'Catalogo MINSAL'!A:E,5,FALSE),""),IF(I42<>"",IFERROR(VLOOKUP(IFERROR(LEFT(I42,FIND("-",I42)-1),I42),'Catalogo MINSAL'!A:E,5,FALSE),""),"")) | K42: Diandra Silva Rodriguez | L42: Dr. Arturo Hillerns Eltit | M42: Quirofano 08 | N42: Atendido | O42: 0.36458333 | P42: =IFERROR(IF(OR(O42="",A42="",M42=""),"",IF(SUMPRODUCT(($A$4:$A$500=A42)*($M$4:$M$500=M42)*($O$4:$O$500<>"")*(MOD($O$4:$O$500,1)<MOD(O42,1)))=0,IF(MOD(O42,1)<=TIME(8,15,0),"Ingreso adecuado primera hora","Atraso primera hora"),"No aplica")),"") | R42: 0.36666667 | S42: 0.37430556 | T42: 0.37638889 | U42: =IFERROR(VLOOKUP(M42,'Horario Pabellones'!$A$4:$D$17,2,FALSE),"") | V42: =IFERROR(VLOOKUP(M42,'Horario Pabellones'!$A$4:$D$17,3,FALSE),"") | W42: =IFERROR(VLOOKUP(M42,'Horario Pabellones'!$A$4:$D$17,4,FALSE),"") | X42: =IFERROR(IF(OR(A42="",M42="",W42=""),"",(((_xludf.AGGREGATE(14,6,MOD($S$4:$S$500,1)/(($A$4:$A$500=A42)*($M$4:$M$500=M42)*($R$4:$R$500<>"")*($S$4:$S$500<>"")),1)-_xludf.AGGREGATE(15,6,MOD($R$4:$R$500,1)/(($A$4:$A$500=A42)*($M$4:$M$500=M42)*($R$4:$R$500<>"")*($S$4:$S$500<>"")),1))*1440)/60)/(W42/60)),"") | Y42: =IFERROR(IF(OR(O42="",A42="",M42=""),"",(IF(ISNUMBER(O42),MOD(O42,1),TIMEVALUE(O42))-LOOKUP(2,1/(($A$4:$A$500=A42)*($M$4:$M$500=M42)*($T$4:$T$500<>"")*($T$4:$T$500<IF(ISNUMBER(O42),MOD(O42,1),TIMEVALUE(O42)))),$T$4:$T$500))*1440),"") | Z42: =IFERROR(IF(Y42="","",IF(ROUND(Y42,0)<=15,"Cumple","No cumple")),"") | AB42: =IFERROR(IF(OR(O42="",R42=""),"",IF(IF(ISNUMBER(R42),MOD(R42,1),TIMEVALUE(R42))>=IF(ISNUMBER(O42),MOD(O42,1),TIMEVALUE(O42)),(IF(ISNUMBER(R42),MOD(R42,1),TIMEVALUE(R42))-IF(ISNUMBER(O42),MOD(O42,1),TIMEVALUE(O42)))*1440,(IF(ISNUMBER(R42),MOD(R42,1),TIMEVALUE(R42))+1-IF(ISNUMBER(O42),MOD(O42,1),TIMEVALUE(O42)))*1440)),"") | AC42: =IFERROR(IF(OR(R42="",S42=""),"",IF(IF(ISNUMBER(S42),MOD(S42,1),TIMEVALUE(S42))>=IF(ISNUMBER(R42),MOD(R42,1),TIMEVALUE(R42)),(IF(ISNUMBER(S42),MOD(S42,1),TIMEVALUE(S42))-IF(ISNUMBER(R42),MOD(R42,1),TIMEVALUE(R42)))*1440,(IF(ISNUMBER(S42),MOD(S42,1),TIMEVALUE(S42))+1-IF(ISNUMBER(R42),MOD(R42,1),TIMEVALUE(R42)))*1440)),"") | AD42: 60 | AE42: =IFERROR(IF(OR(AC42="",AD42=""),"",AC42-AD42),"") | AF42: =IFERROR(IF(AE42="","",IF(ROUND(AE42,0)>15,"Subestimacion",IF(ROUND(AE42,0)<-15,"Sobrestimacion","Asertivo"))),"") | AG42: Sin Suspensión | AM42: I0001188069 | AP42: =IF(A42="","",A42-WEEKDAY(A42,2)+1) | AQ42: =IF(AO42="","",AO42+6) | AR42: =IF(AO42="","","Semana "&TEXT(AO42,"dd-mm-yyyy")&" al "&TEXT(AP42,"dd-mm-yyyy")) | AS42: =IF(A42="","",TEXT(A42,"mmmm yyyy")) | AT42: =IF(A42="","",TEXT(A42,"dddd")) | AU42: =IF(A42="","","CRR-"&TEXT(A42,"yyyymmdd")&"-"&M42&"-"&TEXT(ROW()-3,"0000")) | AV42: =IF(A42="","",IF(OR(B42="",C42="",E42="",F42="",M42="",N42=""),"Revisar campos obligatorios",IF(AND(P42="Atraso primera hora",Q42=""),"Falta justificación atraso primera hora",IF(AND(Z42="No cumple",AA42=""),"Falta justificación recambio >15 min",IF(AND(ISNUMBER(SEARCH("suspend",N42)),OR(AG42="",AH42="")),"Falta causa/motivo suspensión","OK"))))) | AW42: =IF(N42="","",IF(ISNUMBER(SEARCH("suspend",N42)),IF(AND(AG42="",AH42=""),"Sin causa/motivo registrado",IF(AG42="",AH42,IF(AH42="",AG42,AG42&": "&AH42))),""))
A43: 46169 | B43: NAVIDAD DEL CARMEN | C43: OLIVERA | D43: 65a 5m 2d | E43: VITRECTOMIA CON VITREOFAGO (PROC. AUT) | F43: UNIDAD DE OFTALMOLOGIA | H43: 1202062-8 | J43: =IF(H43<>"",IFERROR(VLOOKUP(IFERROR(LEFT(H43,FIND("-",H43)-1),H43),'Catalogo MINSAL'!A:E,5,FALSE),""),IF(I43<>"",IFERROR(VLOOKUP(IFERROR(LEFT(I43,FIND("-",I43)-1),I43),'Catalogo MINSAL'!A:E,5,FALSE),""),"")) | K43: Diandra Silva Rodriguez | L43: Dr. Arturo Hillerns Eltit | M43: Quirofano 08 | N43: Atendido | O43: 0.41666667 | P43: =IFERROR(IF(OR(O43="",A43="",M43=""),"",IF(SUMPRODUCT(($A$4:$A$500=A43)*($M$4:$M$500=M43)*($O$4:$O$500<>"")*(MOD($O$4:$O$500,1)<MOD(O43,1)))=0,IF(MOD(O43,1)<=TIME(8,15,0),"Ingreso adecuado primera hora","Atraso primera hora"),"No aplica")),"") | R43: 0.41875 | S43: 0.43402778 | T43: 0.43541667 | U43: =IFERROR(VLOOKUP(M43,'Horario Pabellones'!$A$4:$D$17,2,FALSE),"") | V43: =IFERROR(VLOOKUP(M43,'Horario Pabellones'!$A$4:$D$17,3,FALSE),"") | W43: =IFERROR(VLOOKUP(M43,'Horario Pabellones'!$A$4:$D$17,4,FALSE),"") | X43: =IFERROR(IF(OR(A43="",M43="",W43=""),"",(((_xludf.AGGREGATE(14,6,MOD($S$4:$S$500,1)/(($A$4:$A$500=A43)*($M$4:$M$500=M43)*($R$4:$R$500<>"")*($S$4:$S$500<>"")),1)-_xludf.AGGREGATE(15,6,MOD($R$4:$R$500,1)/(($A$4:$A$500=A43)*($M$4:$M$500=M43)*($R$4:$R$500<>"")*($S$4:$S$500<>"")),1))*1440)/60)/(W43/60)),"") | Y43: =IFERROR(IF(OR(O43="",A43="",M43=""),"",(IF(ISNUMBER(O43),MOD(O43,1),TIMEVALUE(O43))-LOOKUP(2,1/(($A$4:$A$500=A43)*($M$4:$M$500=M43)*($T$4:$T$500<>"")*($T$4:$T$500<IF(ISNUMBER(O43),MOD(O43,1),TIMEVALUE(O43)))),$T$4:$T$500))*1440),"") | Z43: =IFERROR(IF(Y43="","",IF(ROUND(Y43,0)<=15,"Cumple","No cumple")),"") | AB43: =IFERROR(IF(OR(O43="",R43=""),"",IF(IF(ISNUMBER(R43),MOD(R43,1),TIMEVALUE(R43))>=IF(ISNUMBER(O43),MOD(O43,1),TIMEVALUE(O43)),(IF(ISNUMBER(R43),MOD(R43,1),TIMEVALUE(R43))-IF(ISNUMBER(O43),MOD(O43,1),TIMEVALUE(O43)))*1440,(IF(ISNUMBER(R43),MOD(R43,1),TIMEVALUE(R43))+1-IF(ISNUMBER(O43),MOD(O43,1),TIMEVALUE(O43)))*1440)),"") | AC43: =IFERROR(IF(OR(R43="",S43=""),"",IF(IF(ISNUMBER(S43),MOD(S43,1),TIMEVALUE(S43))>=IF(ISNUMBER(R43),MOD(R43,1),TIMEVALUE(R43)),(IF(ISNUMBER(S43),MOD(S43,1),TIMEVALUE(S43))-IF(ISNUMBER(R43),MOD(R43,1),TIMEVALUE(R43)))*1440,(IF(ISNUMBER(S43),MOD(S43,1),TIMEVALUE(S43))+1-IF(ISNUMBER(R43),MOD(R43,1),TIMEVALUE(R43)))*1440)),"") | AD43: 60 | AE43: =IFERROR(IF(OR(AC43="",AD43=""),"",AC43-AD43),"") | AF43: =IFERROR(IF(AE43="","",IF(ROUND(AE43,0)>15,"Subestimacion",IF(ROUND(AE43,0)<-15,"Sobrestimacion","Asertivo"))),"") | AG43: Sin Suspensión | AM43: I0001188068 | AP43: =IF(A43="","",A43-WEEKDAY(A43,2)+1) | AQ43: =IF(AO43="","",AO43+6) | AR43: =IF(AO43="","","Semana "&TEXT(AO43,"dd-mm-yyyy")&" al "&TEXT(AP43,"dd-mm-yyyy")) | AS43: =IF(A43="","",TEXT(A43,"mmmm yyyy")) | AT43: =IF(A43="","",TEXT(A43,"dddd")) | AU43: =IF(A43="","","CRR-"&TEXT(A43,"yyyymmdd")&"-"&M43&"-"&TEXT(ROW()-3,"0000")) | AV43: =IF(A43="","",IF(OR(B43="",C43="",E43="",F43="",M43="",N43=""),"Revisar campos obligatorios",IF(AND(P43="Atraso primera hora",Q43=""),"Falta justificación atraso primera hora",IF(AND(Z43="No cumple",AA43=""),"Falta justificación recambio >15 min",IF(AND(ISNUMBER(SEARCH("suspend",N43)),OR(AG43="",AH43="")),"Falta causa/motivo suspensión","OK"))))) | AW43: =IF(N43="","",IF(ISNUMBER(SEARCH("suspend",N43)),IF(AND(AG43="",AH43=""),"Sin causa/motivo registrado",IF(AG43="",AH43,IF(AH43="",AG43,AG43&": "&AH43))),""))
A44: 46169 | B44: PATRICIA DEL CARMEN | C44: VELASCO | D44: 69a 7m 16d | E44: - FACOERESIS EXTRACAPSULAR CON IMPLANTE DE LENTE INTRAOCULAR (NO INCLUYE EL VALOR DE LA PROTESIS) | F44: UNIDAD DE OFTALMOLOGIA | H44: 1202064-10 | J44: =IF(H44<>"",IFERROR(VLOOKUP(IFERROR(LEFT(H44,FIND("-",H44)-1),H44),'Catalogo MINSAL'!A:E,5,FALSE),""),IF(I44<>"",IFERROR(VLOOKUP(IFERROR(LEFT(I44,FIND("-",I44)-1),I44),'Catalogo MINSAL'!A:E,5,FALSE),""),"")) | K44: Diandra Silva Rodriguez | L44: Dr. Arturo Hillerns Eltit | M44: Quirofano 08 | N44: Atendido | O44: 0.44305556 | P44: =IFERROR(IF(OR(O44="",A44="",M44=""),"",IF(SUMPRODUCT(($A$4:$A$500=A44)*($M$4:$M$500=M44)*($O$4:$O$500<>"")*(MOD($O$4:$O$500,1)<MOD(O44,1)))=0,IF(MOD(O44,1)<=TIME(8,15,0),"Ingreso adecuado primera hora","Atraso primera hora"),"No aplica")),"") | R44: 0.44791667 | S44: 0.46041667 | T44: 0.46180556 | U44: =IFERROR(VLOOKUP(M44,'Horario Pabellones'!$A$4:$D$17,2,FALSE),"") | V44: =IFERROR(VLOOKUP(M44,'Horario Pabellones'!$A$4:$D$17,3,FALSE),"") | W44: =IFERROR(VLOOKUP(M44,'Horario Pabellones'!$A$4:$D$17,4,FALSE),"") | X44: =IFERROR(IF(OR(A44="",M44="",W44=""),"",(((_xludf.AGGREGATE(14,6,MOD($S$4:$S$500,1)/(($A$4:$A$500=A44)*($M$4:$M$500=M44)*($R$4:$R$500<>"")*($S$4:$S$500<>"")),1)-_xludf.AGGREGATE(15,6,MOD($R$4:$R$500,1)/(($A$4:$A$500=A44)*($M$4:$M$500=M44)*($R$4:$R$500<>"")*($S$4:$S$500<>"")),1))*1440)/60)/(W44/60)),"") | Y44: =IFERROR(IF(OR(O44="",A44="",M44=""),"",(IF(ISNUMBER(O44),MOD(O44,1),TIMEVALUE(O44))-LOOKUP(2,1/(($A$4:$A$500=A44)*($M$4:$M$500=M44)*($T$4:$T$500<>"")*($T$4:$T$500<IF(ISNUMBER(O44),MOD(O44,1),TIMEVALUE(O44)))),$T$4:$T$500))*1440),"") | Z44: =IFERROR(IF(Y44="","",IF(ROUND(Y44,0)<=15,"Cumple","No cumple")),"") | AB44: =IFERROR(IF(OR(O44="",R44=""),"",IF(IF(ISNUMBER(R44),MOD(R44,1),TIMEVALUE(R44))>=IF(ISNUMBER(O44),MOD(O44,1),TIMEVALUE(O44)),(IF(ISNUMBER(R44),MOD(R44,1),TIMEVALUE(R44))-IF(ISNUMBER(O44),MOD(O44,1),TIMEVALUE(O44)))*1440,(IF(ISNUMBER(R44),MOD(R44,1),TIMEVALUE(R44))+1-IF(ISNUMBER(O44),MOD(O44,1),TIMEVALUE(O44)))*1440)),"") | AC44: =IFERROR(IF(OR(R44="",S44=""),"",IF(IF(ISNUMBER(S44),MOD(S44,1),TIMEVALUE(S44))>=IF(ISNUMBER(R44),MOD(R44,1),TIMEVALUE(R44)),(IF(ISNUMBER(S44),MOD(S44,1),TIMEVALUE(S44))-IF(ISNUMBER(R44),MOD(R44,1),TIMEVALUE(R44)))*1440,(IF(ISNUMBER(S44),MOD(S44,1),TIMEVALUE(S44))+1-IF(ISNUMBER(R44),MOD(R44,1),TIMEVALUE(R44)))*1440)),"") | AD44: 60 | AE44: =IFERROR(IF(OR(AC44="",AD44=""),"",AC44-AD44),"") | AF44: =IFERROR(IF(AE44="","",IF(ROUND(AE44,0)>15,"Subestimacion",IF(ROUND(AE44,0)<-15,"Sobrestimacion","Asertivo"))),"") | AG44: Sin Suspensión | AM44: I0001188070 | AP44: =IF(A44="","",A44-WEEKDAY(A44,2)+1) | AQ44: =IF(AO44="","",AO44+6) | AR44: =IF(AO44="","","Semana "&TEXT(AO44,"dd-mm-yyyy")&" al "&TEXT(AP44,"dd-mm-yyyy")) | AS44: =IF(A44="","",TEXT(A44,"mmmm yyyy")) | AT44: =IF(A44="","",TEXT(A44,"dddd")) | AU44: =IF(A44="","","CRR-"&TEXT(A44,"yyyymmdd")&"-"&M44&"-"&TEXT(ROW()-3,"0000")) | AV44: =IF(A44="","",IF(OR(B44="",C44="",E44="",F44="",M44="",N44=""),"Revisar campos obligatorios",IF(AND(P44="Atraso primera hora",Q44=""),"Falta justificación atraso primera hora",IF(AND(Z44="No cumple",AA44=""),"Falta justificación recambio >15 min",IF(AND(ISNUMBER(SEARCH("suspend",N44)),OR(AG44="",AH44="")),"Falta causa/motivo suspensión","OK"))))) | AW44: =IF(N44="","",IF(ISNUMBER(SEARCH("suspend",N44)),IF(AND(AG44="",AH44=""),"Sin causa/motivo registrado",IF(AG44="",AH44,IF(AH44="",AG44,AG44&": "&AH44))),""))
A45: 46169 | B45: LUZ ANDREA | C45: MOYANO | D45: 77a 2m 2d | E45: - FACOERESIS EXTRACAPSULAR CON IMPLANTE DE LENTE INTRAOCULAR (INCLUYE EL VALOR DE LA PROTESIS) | F45: UNIDAD DE OFTALMOLOGIA | H45: 1202164-10 | J45: =IF(H45<>"",IFERROR(VLOOKUP(IFERROR(LEFT(H45,FIND("-",H45)-1),H45),'Catalogo MINSAL'!A:E,5,FALSE),""),IF(I45<>"",IFERROR(VLOOKUP(IFERROR(LEFT(I45,FIND("-",I45)-1),I45),'Catalogo MINSAL'!A:E,5,FALSE),""),"")) | K45: Diandra Silva Rodriguez | L45: Dr. Arturo Hillerns Eltit | M45: Quirofano 08 | N45: Recepcionado | O45: 0.49652778 | P45: =IFERROR(IF(OR(O45="",A45="",M45=""),"",IF(SUMPRODUCT(($A$4:$A$500=A45)*($M$4:$M$500=M45)*($O$4:$O$500<>"")*(MOD($O$4:$O$500,1)<MOD(O45,1)))=0,IF(MOD(O45,1)<=TIME(8,15,0),"Ingreso adecuado primera hora","Atraso primera hora"),"No aplica")),"") | R45: 0.50555556 | S45: 0.51041667 | T45: 0.51527778 | U45: =IFERROR(VLOOKUP(M45,'Horario Pabellones'!$A$4:$D$17,2,FALSE),"") | V45: =IFERROR(VLOOKUP(M45,'Horario Pabellones'!$A$4:$D$17,3,FALSE),"") | W45: =IFERROR(VLOOKUP(M45,'Horario Pabellones'!$A$4:$D$17,4,FALSE),"") | X45: =IFERROR(IF(OR(A45="",M45="",W45=""),"",(((_xludf.AGGREGATE(14,6,MOD($S$4:$S$500,1)/(($A$4:$A$500=A45)*($M$4:$M$500=M45)*($R$4:$R$500<>"")*($S$4:$S$500<>"")),1)-_xludf.AGGREGATE(15,6,MOD($R$4:$R$500,1)/(($A$4:$A$500=A45)*($M$4:$M$500=M45)*($R$4:$R$500<>"")*($S$4:$S$500<>"")),1))*1440)/60)/(W45/60)),"") | Y45: =IFERROR(IF(OR(O45="",A45="",M45=""),"",(IF(ISNUMBER(O45),MOD(O45,1),TIMEVALUE(O45))-LOOKUP(2,1/(($A$4:$A$500=A45)*($M$4:$M$500=M45)*($T$4:$T$500<>"")*($T$4:$T$500<IF(ISNUMBER(O45),MOD(O45,1),TIMEVALUE(O45)))),$T$4:$T$500))*1440),"") | Z45: =IFERROR(IF(Y45="","",IF(ROUND(Y45,0)<=15,"Cumple","No cumple")),"") | AB45: =IFERROR(IF(OR(O45="",R45=""),"",IF(IF(ISNUMBER(R45),MOD(R45,1),TIMEVALUE(R45))>=IF(ISNUMBER(O45),MOD(O45,1),TIMEVALUE(O45)),(IF(ISNUMBER(R45),MOD(R45,1),TIMEVALUE(R45))-IF(ISNUMBER(O45),MOD(O45,1),TIMEVALUE(O45)))*1440,(IF(ISNUMBER(R45),MOD(R45,1),TIMEVALUE(R45))+1-IF(ISNUMBER(O45),MOD(O45,1),TIMEVALUE(O45)))*1440)),"") | AC45: =IFERROR(IF(OR(R45="",S45=""),"",IF(IF(ISNUMBER(S45),MOD(S45,1),TIMEVALUE(S45))>=IF(ISNUMBER(R45),MOD(R45,1),TIMEVALUE(R45)),(IF(ISNUMBER(S45),MOD(S45,1),TIMEVALUE(S45))-IF(ISNUMBER(R45),MOD(R45,1),TIMEVALUE(R45)))*1440,(IF(ISNUMBER(S45),MOD(S45,1),TIMEVALUE(S45))+1-IF(ISNUMBER(R45),MOD(R45,1),TIMEVALUE(R45)))*1440)),"") | AD45: 60 | AE45: =IFERROR(IF(OR(AC45="",AD45=""),"",AC45-AD45),"") | AF45: =IFERROR(IF(AE45="","",IF(ROUND(AE45,0)>15,"Subestimacion",IF(ROUND(AE45,0)<-15,"Sobrestimacion","Asertivo"))),"") | AG45: Sin Suspensión | AM45: I0001188091 | AP45: =IF(A45="","",A45-WEEKDAY(A45,2)+1) | AQ45: =IF(AO45="","",AO45+6) | AR45: =IF(AO45="","","Semana "&TEXT(AO45,"dd-mm-yyyy")&" al "&TEXT(AP45,"dd-mm-yyyy")) | AS45: =IF(A45="","",TEXT(A45,"mmmm yyyy")) | AT45: =IF(A45="","",TEXT(A45,"dddd")) | AU45: =IF(A45="","","CRR-"&TEXT(A45,"yyyymmdd")&"-"&M45&"-"&TEXT(ROW()-3,"0000")) | AV45: =IF(A45="","",IF(OR(B45="",C45="",E45="",F45="",M45="",N45=""),"Revisar campos obligatorios",IF(AND(P45="Atraso primera hora",Q45=""),"Falta justificación atraso primera hora",IF(AND(Z45="No cumple",AA45=""),"Falta justificación recambio >15 min",IF(AND(ISNUMBER(SEARCH("suspend",N45)),OR(AG45="",AH45="")),"Falta causa/motivo suspensión","OK"))))) | AW45: =IF(N45="","",IF(ISNUMBER(SEARCH("suspend",N45)),IF(AND(AG45="",AH45=""),"Sin causa/motivo registrado",IF(AG45="",AH45,IF(AH45="",AG45,AG45&": "&AH45))),""))
A46: 46169 | B46: CARMEN RAFAELA | C46: SIMOZA | D46: 75a 7m 3d | E46: - FACOERESIS EXTRACAPSULAR CON IMPLANTE DE LENTE INTRAOCULAR (NO INCLUYE EL VALOR DE LA PROTESIS) | F46: UNIDAD DE OFTALMOLOGIA | H46: 1202064-10 | J46: =IF(H46<>"",IFERROR(VLOOKUP(IFERROR(LEFT(H46,FIND("-",H46)-1),H46),'Catalogo MINSAL'!A:E,5,FALSE),""),IF(I46<>"",IFERROR(VLOOKUP(IFERROR(LEFT(I46,FIND("-",I46)-1),I46),'Catalogo MINSAL'!A:E,5,FALSE),""),"")) | K46: Diandra Silva Rodriguez | L46: Dr. Arturo Hillerns Eltit | M46: Quirofano 08 | N46: Atendido | O46: 0.52430556 | P46: =IFERROR(IF(OR(O46="",A46="",M46=""),"",IF(SUMPRODUCT(($A$4:$A$500=A46)*($M$4:$M$500=M46)*($O$4:$O$500<>"")*(MOD($O$4:$O$500,1)<MOD(O46,1)))=0,IF(MOD(O46,1)<=TIME(8,15,0),"Ingreso adecuado primera hora","Atraso primera hora"),"No aplica")),"") | R46: 0.53125 | S46: 0.53819444 | T46: 0.53958333 | U46: =IFERROR(VLOOKUP(M46,'Horario Pabellones'!$A$4:$D$17,2,FALSE),"") | V46: =IFERROR(VLOOKUP(M46,'Horario Pabellones'!$A$4:$D$17,3,FALSE),"") | W46: =IFERROR(VLOOKUP(M46,'Horario Pabellones'!$A$4:$D$17,4,FALSE),"") | X46: =IFERROR(IF(OR(A46="",M46="",W46=""),"",(((_xludf.AGGREGATE(14,6,MOD($S$4:$S$500,1)/(($A$4:$A$500=A46)*($M$4:$M$500=M46)*($R$4:$R$500<>"")*($S$4:$S$500<>"")),1)-_xludf.AGGREGATE(15,6,MOD($R$4:$R$500,1)/(($A$4:$A$500=A46)*($M$4:$M$500=M46)*($R$4:$R$500<>"")*($S$4:$S$500<>"")),1))*1440)/60)/(W46/60)),"") | Y46: =IFERROR(IF(OR(O46="",A46="",M46=""),"",(IF(ISNUMBER(O46),MOD(O46,1),TIMEVALUE(O46))-LOOKUP(2,1/(($A$4:$A$500=A46)*($M$4:$M$500=M46)*($T$4:$T$500<>"")*($T$4:$T$500<IF(ISNUMBER(O46),MOD(O46,1),TIMEVALUE(O46)))),$T$4:$T$500))*1440),"") | Z46: =IFERROR(IF(Y46="","",IF(ROUND(Y46,0)<=15,"Cumple","No cumple")),"") | AB46: =IFERROR(IF(OR(O46="",R46=""),"",IF(IF(ISNUMBER(R46),MOD(R46,1),TIMEVALUE(R46))>=IF(ISNUMBER(O46),MOD(O46,1),TIMEVALUE(O46)),(IF(ISNUMBER(R46),MOD(R46,1),TIMEVALUE(R46))-IF(ISNUMBER(O46),MOD(O46,1),TIMEVALUE(O46)))*1440,(IF(ISNUMBER(R46),MOD(R46,1),TIMEVALUE(R46))+1-IF(ISNUMBER(O46),MOD(O46,1),TIMEVALUE(O46)))*1440)),"") | AC46: =IFERROR(IF(OR(R46="",S46=""),"",IF(IF(ISNUMBER(S46),MOD(S46,1),TIMEVALUE(S46))>=IF(ISNUMBER(R46),MOD(R46,1),TIMEVALUE(R46)),(IF(ISNUMBER(S46),MOD(S46,1),TIMEVALUE(S46))-IF(ISNUMBER(R46),MOD(R46,1),TIMEVALUE(R46)))*1440,(IF(ISNUMBER(S46),MOD(S46,1),TIMEVALUE(S46))+1-IF(ISNUMBER(R46),MOD(R46,1),TIMEVALUE(R46)))*1440)),"") | AD46: 60 | AE46: =IFERROR(IF(OR(AC46="",AD46=""),"",AC46-AD46),"") | AF46: =IFERROR(IF(AE46="","",IF(ROUND(AE46,0)>15,"Subestimacion",IF(ROUND(AE46,0)<-15,"Sobrestimacion","Asertivo"))),"") | AG46: Sin Suspensión | AM46: I0001188077 | AP46: =IF(A46="","",A46-WEEKDAY(A46,2)+1) | AQ46: =IF(AO46="","",AO46+6) | AR46: =IF(AO46="","","Semana "&TEXT(AO46,"dd-mm-yyyy")&" al "&TEXT(AP46,"dd-mm-yyyy")) | AS46: =IF(A46="","",TEXT(A46,"mmmm yyyy")) | AT46: =IF(A46="","",TEXT(A46,"dddd")) | AU46: =IF(A46="","","CRR-"&TEXT(A46,"yyyymmdd")&"-"&M46&"-"&TEXT(ROW()-3,"0000")) | AV46: =IF(A46="","",IF(OR(B46="",C46="",E46="",F46="",M46="",N46=""),"Revisar campos obligatorios",IF(AND(P46="Atraso primera hora",Q46=""),"Falta justificación atraso primera hora",IF(AND(Z46="No cumple",AA46=""),"Falta justificación recambio >15 min",IF(AND(ISNUMBER(SEARCH("suspend",N46)),OR(AG46="",AH46="")),"Falta causa/motivo suspensión","OK"))))) | AW46: =IF(N46="","",IF(ISNUMBER(SEARCH("suspend",N46)),IF(AND(AG46="",AH46=""),"Sin causa/motivo registrado",IF(AG46="",AH46,IF(AH46="",AG46,AG46&": "&AH46))),""))
A47: 46169 | B47: JOSÉ ABRAHAM | C47: CERDA | D47: 66a 11m 23d | E47: - FACOERESIS EXTRACAPSULAR CON IMPLANTE DE LENTE INTRAOCULAR (NO INCLUYE EL VALOR DE LA PROTESIS) | F47: UNIDAD DE OFTALMOLOGIA | H47: 1202064-10 | J47: =IF(H47<>"",IFERROR(VLOOKUP(IFERROR(LEFT(H47,FIND("-",H47)-1),H47),'Catalogo MINSAL'!A:E,5,FALSE),""),IF(I47<>"",IFERROR(VLOOKUP(IFERROR(LEFT(I47,FIND("-",I47)-1),I47),'Catalogo MINSAL'!A:E,5,FALSE),""),"")) | K47: Diandra Silva Rodriguez | L47: Dr. Arturo Hillerns Eltit | M47: Quirofano 08 | N47: Atendido | O47: 0.58680556 | P47: =IFERROR(IF(OR(O47="",A47="",M47=""),"",IF(SUMPRODUCT(($A$4:$A$500=A47)*($M$4:$M$500=M47)*($O$4:$O$500<>"")*(MOD($O$4:$O$500,1)<MOD(O47,1)))=0,IF(MOD(O47,1)<=TIME(8,15,0),"Ingreso adecuado primera hora","Atraso primera hora"),"No aplica")),"") | R47: 0.59722222 | S47: 0.61736111 | T47: 0.61944444 | U47: =IFERROR(VLOOKUP(M47,'Horario Pabellones'!$A$4:$D$17,2,FALSE),"") | V47: =IFERROR(VLOOKUP(M47,'Horario Pabellones'!$A$4:$D$17,3,FALSE),"") | W47: =IFERROR(VLOOKUP(M47,'Horario Pabellones'!$A$4:$D$17,4,FALSE),"") | X47: =IFERROR(IF(OR(A47="",M47="",W47=""),"",(((_xludf.AGGREGATE(14,6,MOD($S$4:$S$500,1)/(($A$4:$A$500=A47)*($M$4:$M$500=M47)*($R$4:$R$500<>"")*($S$4:$S$500<>"")),1)-_xludf.AGGREGATE(15,6,MOD($R$4:$R$500,1)/(($A$4:$A$500=A47)*($M$4:$M$500=M47)*($R$4:$R$500<>"")*($S$4:$S$500<>"")),1))*1440)/60)/(W47/60)),"") | Y47: =IFERROR(IF(OR(O47="",A47="",M47=""),"",(IF(ISNUMBER(O47),MOD(O47,1),TIMEVALUE(O47))-LOOKUP(2,1/(($A$4:$A$500=A47)*($M$4:$M$500=M47)*($T$4:$T$500<>"")*($T$4:$T$500<IF(ISNUMBER(O47),MOD(O47,1),TIMEVALUE(O47)))),$T$4:$T$500))*1440),"") | Z47: =IFERROR(IF(Y47="","",IF(ROUND(Y47,0)<=15,"Cumple","No cumple")),"") | AB47: =IFERROR(IF(OR(O47="",R47=""),"",IF(IF(ISNUMBER(R47),MOD(R47,1),TIMEVALUE(R47))>=IF(ISNUMBER(O47),MOD(O47,1),TIMEVALUE(O47)),(IF(ISNUMBER(R47),MOD(R47,1),TIMEVALUE(R47))-IF(ISNUMBER(O47),MOD(O47,1),TIMEVALUE(O47)))*1440,(IF(ISNUMBER(R47),MOD(R47,1),TIMEVALUE(R47))+1-IF(ISNUMBER(O47),MOD(O47,1),TIMEVALUE(O47)))*1440)),"") | AC47: =IFERROR(IF(OR(R47="",S47=""),"",IF(IF(ISNUMBER(S47),MOD(S47,1),TIMEVALUE(S47))>=IF(ISNUMBER(R47),MOD(R47,1),TIMEVALUE(R47)),(IF(ISNUMBER(S47),MOD(S47,1),TIMEVALUE(S47))-IF(ISNUMBER(R47),MOD(R47,1),TIMEVALUE(R47)))*1440,(IF(ISNUMBER(S47),MOD(S47,1),TIMEVALUE(S47))+1-IF(ISNUMBER(R47),MOD(R47,1),TIMEVALUE(R47)))*1440)),"") | AD47: 60 | AE47: =IFERROR(IF(OR(AC47="",AD47=""),"",AC47-AD47),"") | AF47: =IFERROR(IF(AE47="","",IF(ROUND(AE47,0)>15,"Subestimacion",IF(ROUND(AE47,0)<-15,"Sobrestimacion","Asertivo"))),"") | AG47: Sin Suspensión | AM47: I0001188071 | AP47: =IF(A47="","",A47-WEEKDAY(A47,2)+1) | AQ47: =IF(AO47="","",AO47+6) | AR47: =IF(AO47="","","Semana "&TEXT(AO47,"dd-mm-yyyy")&" al "&TEXT(AP47,"dd-mm-yyyy")) | AS47: =IF(A47="","",TEXT(A47,"mmmm yyyy")) | AT47: =IF(A47="","",TEXT(A47,"dddd")) | AU47: =IF(A47="","","CRR-"&TEXT(A47,"yyyymmdd")&"-"&M47&"-"&TEXT(ROW()-3,"0000")) | AV47: =IF(A47="","",IF(OR(B47="",C47="",E47="",F47="",M47="",N47=""),"Revisar campos obligatorios",IF(AND(P47="Atraso primera hora",Q47=""),"Falta justificación atraso primera hora",IF(AND(Z47="No cumple",AA47=""),"Falta justificación recambio >15 min",IF(AND(ISNUMBER(SEARCH("suspend",N47)),OR(AG47="",AH47="")),"Falta causa/motivo suspensión","OK"))))) | AW47: =IF(N47="","",IF(ISNUMBER(SEARCH("suspend",N47)),IF(AND(AG47="",AH47=""),"Sin causa/motivo registrado",IF(AG47="",AH47,IF(AH47="",AG47,AG47&": "&AH47))),""))
A48: 46169 | B48: MARÍA INÉS | C48: RÍOS | D48: 67a 6m 12d | E48: - FACOERESIS EXTRACAPSULAR CON IMPLANTE DE LENTE INTRAOCULAR (NO INCLUYE EL VALOR DE LA PROTESIS) | F48: UNIDAD DE OFTALMOLOGIA | H48: 1202064-10 | J48: =IF(H48<>"",IFERROR(VLOOKUP(IFERROR(LEFT(H48,FIND("-",H48)-1),H48),'Catalogo MINSAL'!A:E,5,FALSE),""),IF(I48<>"",IFERROR(VLOOKUP(IFERROR(LEFT(I48,FIND("-",I48)-1),I48),'Catalogo MINSAL'!A:E,5,FALSE),""),"")) | K48: Diandra Silva Rodriguez | L48: Dr. Arturo Hillerns Eltit | M48: Quirofano 08 | N48: Atendido | O48: 0.62152778 | P48: =IFERROR(IF(OR(O48="",A48="",M48=""),"",IF(SUMPRODUCT(($A$4:$A$500=A48)*($M$4:$M$500=M48)*($O$4:$O$500<>"")*(MOD($O$4:$O$500,1)<MOD(O48,1)))=0,IF(MOD(O48,1)<=TIME(8,15,0),"Ingreso adecuado primera hora","Atraso primera hora"),"No aplica")),"") | R48: 0.63055556 | S48: 0.64444444 | T48: 0.64583333 | U48: =IFERROR(VLOOKUP(M48,'Horario Pabellones'!$A$4:$D$17,2,FALSE),"") | V48: =IFERROR(VLOOKUP(M48,'Horario Pabellones'!$A$4:$D$17,3,FALSE),"") | W48: =IFERROR(VLOOKUP(M48,'Horario Pabellones'!$A$4:$D$17,4,FALSE),"") | X48: =IFERROR(IF(OR(A48="",M48="",W48=""),"",(((_xludf.AGGREGATE(14,6,MOD($S$4:$S$500,1)/(($A$4:$A$500=A48)*($M$4:$M$500=M48)*($R$4:$R$500<>"")*($S$4:$S$500<>"")),1)-_xludf.AGGREGATE(15,6,MOD($R$4:$R$500,1)/(($A$4:$A$500=A48)*($M$4:$M$500=M48)*($R$4:$R$500<>"")*($S$4:$S$500<>"")),1))*1440)/60)/(W48/60)),"") | Y48: =IFERROR(IF(OR(O48="",A48="",M48=""),"",(IF(ISNUMBER(O48),MOD(O48,1),TIMEVALUE(O48))-LOOKUP(2,1/(($A$4:$A$500=A48)*($M$4:$M$500=M48)*($T$4:$T$500<>"")*($T$4:$T$500<IF(ISNUMBER(O48),MOD(O48,1),TIMEVALUE(O48)))),$T$4:$T$500))*1440),"") | Z48: =IFERROR(IF(Y48="","",IF(ROUND(Y48,0)<=15,"Cumple","No cumple")),"") | AB48: =IFERROR(IF(OR(O48="",R48=""),"",IF(IF(ISNUMBER(R48),MOD(R48,1),TIMEVALUE(R48))>=IF(ISNUMBER(O48),MOD(O48,1),TIMEVALUE(O48)),(IF(ISNUMBER(R48),MOD(R48,1),TIMEVALUE(R48))-IF(ISNUMBER(O48),MOD(O48,1),TIMEVALUE(O48)))*1440,(IF(ISNUMBER(R48),MOD(R48,1),TIMEVALUE(R48))+1-IF(ISNUMBER(O48),MOD(O48,1),TIMEVALUE(O48)))*1440)),"") | AC48: =IFERROR(IF(OR(R48="",S48=""),"",IF(IF(ISNUMBER(S48),MOD(S48,1),TIMEVALUE(S48))>=IF(ISNUMBER(R48),MOD(R48,1),TIMEVALUE(R48)),(IF(ISNUMBER(S48),MOD(S48,1),TIMEVALUE(S48))-IF(ISNUMBER(R48),MOD(R48,1),TIMEVALUE(R48)))*1440,(IF(ISNUMBER(S48),MOD(S48,1),TIMEVALUE(S48))+1-IF(ISNUMBER(R48),MOD(R48,1),TIMEVALUE(R48)))*1440)),"") | AD48: 60 | AE48: =IFERROR(IF(OR(AC48="",AD48=""),"",AC48-AD48),"") | AF48: =IFERROR(IF(AE48="","",IF(ROUND(AE48,0)>15,"Subestimacion",IF(ROUND(AE48,0)<-15,"Sobrestimacion","Asertivo"))),"") | AG48: Sin Suspensión | AM48: I0001188072 | AP48: =IF(A48="","",A48-WEEKDAY(A48,2)+1) | AQ48: =IF(AO48="","",AO48+6) | AR48: =IF(AO48="","","Semana "&TEXT(AO48,"dd-mm-yyyy")&" al "&TEXT(AP48,"dd-mm-yyyy")) | AS48: =IF(A48="","",TEXT(A48,"mmmm yyyy")) | AT48: =IF(A48="","",TEXT(A48,"dddd")) | AU48: =IF(A48="","","CRR-"&TEXT(A48,"yyyymmdd")&"-"&M48&"-"&TEXT(ROW()-3,"0000")) | AV48: =IF(A48="","",IF(OR(B48="",C48="",E48="",F48="",M48="",N48=""),"Revisar campos obligatorios",IF(AND(P48="Atraso primera hora",Q48=""),"Falta justificación atraso primera hora",IF(AND(Z48="No cumple",AA48=""),"Falta justificación recambio >15 min",IF(AND(ISNUMBER(SEARCH("suspend",N48)),OR(AG48="",AH48="")),"Falta causa/motivo suspensión","OK"))))) | AW48: =IF(N48="","",IF(ISNUMBER(SEARCH("suspend",N48)),IF(AND(AG48="",AH48=""),"Sin causa/motivo registrado",IF(AG48="",AH48,IF(AH48="",AG48,AG48&": "&AH48))),""))
A49: 46169 | B49: TERESA DE LAS MERCEDES | C49: BLANCO | D49: 76a 7m 24d | E49: - FACOERESIS EXTRACAPSULAR CON IMPLANTE DE LENTE INTRAOCULAR (NO INCLUYE EL VALOR DE LA PROTESIS) | F49: UNIDAD DE OFTALMOLOGIA | H49: 1202064-10 | J49: =IF(H49<>"",IFERROR(VLOOKUP(IFERROR(LEFT(H49,FIND("-",H49)-1),H49),'Catalogo MINSAL'!A:E,5,FALSE),""),IF(I49<>"",IFERROR(VLOOKUP(IFERROR(LEFT(I49,FIND("-",I49)-1),I49),'Catalogo MINSAL'!A:E,5,FALSE),""),"")) | K49: Diandra Silva Rodriguez | L49: Dr. Arturo Hillerns Eltit | M49: Quirofano 08 | N49: Recepcionado | O49: 0.65 | P49: =IFERROR(IF(OR(O49="",A49="",M49=""),"",IF(SUMPRODUCT(($A$4:$A$500=A49)*($M$4:$M$500=M49)*($O$4:$O$500<>"")*(MOD($O$4:$O$500,1)<MOD(O49,1)))=0,IF(MOD(O49,1)<=TIME(8,15,0),"Ingreso adecuado primera hora","Atraso primera hora"),"No aplica")),"") | R49: 0.65416667 | S49: 0.66041667 | T49: 0.6625 | U49: =IFERROR(VLOOKUP(M49,'Horario Pabellones'!$A$4:$D$17,2,FALSE),"") | V49: =IFERROR(VLOOKUP(M49,'Horario Pabellones'!$A$4:$D$17,3,FALSE),"") | W49: =IFERROR(VLOOKUP(M49,'Horario Pabellones'!$A$4:$D$17,4,FALSE),"") | X49: =IFERROR(IF(OR(A49="",M49="",W49=""),"",(((_xludf.AGGREGATE(14,6,MOD($S$4:$S$500,1)/(($A$4:$A$500=A49)*($M$4:$M$500=M49)*($R$4:$R$500<>"")*($S$4:$S$500<>"")),1)-_xludf.AGGREGATE(15,6,MOD($R$4:$R$500,1)/(($A$4:$A$500=A49)*($M$4:$M$500=M49)*($R$4:$R$500<>"")*($S$4:$S$500<>"")),1))*1440)/60)/(W49/60)),"") | Y49: =IFERROR(IF(OR(O49="",A49="",M49=""),"",(IF(ISNUMBER(O49),MOD(O49,1),TIMEVALUE(O49))-LOOKUP(2,1/(($A$4:$A$500=A49)*($M$4:$M$500=M49)*($T$4:$T$500<>"")*($T$4:$T$500<IF(ISNUMBER(O49),MOD(O49,1),TIMEVALUE(O49)))),$T$4:$T$500))*1440),"") | Z49: =IFERROR(IF(Y49="","",IF(ROUND(Y49,0)<=15,"Cumple","No cumple")),"") | AB49: =IFERROR(IF(OR(O49="",R49=""),"",IF(IF(ISNUMBER(R49),MOD(R49,1),TIMEVALUE(R49))>=IF(ISNUMBER(O49),MOD(O49,1),TIMEVALUE(O49)),(IF(ISNUMBER(R49),MOD(R49,1),TIMEVALUE(R49))-IF(ISNUMBER(O49),MOD(O49,1),TIMEVALUE(O49)))*1440,(IF(ISNUMBER(R49),MOD(R49,1),TIMEVALUE(R49))+1-IF(ISNUMBER(O49),MOD(O49,1),TIMEVALUE(O49)))*1440)),"") | AC49: =IFERROR(IF(OR(R49="",S49=""),"",IF(IF(ISNUMBER(S49),MOD(S49,1),TIMEVALUE(S49))>=IF(ISNUMBER(R49),MOD(R49,1),TIMEVALUE(R49)),(IF(ISNUMBER(S49),MOD(S49,1),TIMEVALUE(S49))-IF(ISNUMBER(R49),MOD(R49,1),TIMEVALUE(R49)))*1440,(IF(ISNUMBER(S49),MOD(S49,1),TIMEVALUE(S49))+1-IF(ISNUMBER(R49),MOD(R49,1),TIMEVALUE(R49)))*1440)),"") | AD49: 60 | AE49: =IFERROR(IF(OR(AC49="",AD49=""),"",AC49-AD49),"") | AF49: =IFERROR(IF(AE49="","",IF(ROUND(AE49,0)>15,"Subestimacion",IF(ROUND(AE49,0)<-15,"Sobrestimacion","Asertivo"))),"") | AG49: Sin Suspensión | AM49: I0001188078 | AP49: =IF(A49="","",A49-WEEKDAY(A49,2)+1) | AQ49: =IF(AO49="","",AO49+6) | AR49: =IF(AO49="","","Semana "&TEXT(AO49,"dd-mm-yyyy")&" al "&TEXT(AP49,"dd-mm-yyyy")) | AS49: =IF(A49="","",TEXT(A49,"mmmm yyyy")) | AT49: =IF(A49="","",TEXT(A49,"dddd")) | AU49: =IF(A49="","","CRR-"&TEXT(A49,"yyyymmdd")&"-"&M49&"-"&TEXT(ROW()-3,"0000")) | AV49: =IF(A49="","",IF(OR(B49="",C49="",E49="",F49="",M49="",N49=""),"Revisar campos obligatorios",IF(AND(P49="Atraso primera hora",Q49=""),"Falta justificación atraso primera hora",IF(AND(Z49="No cumple",AA49=""),"Falta justificación recambio >15 min",IF(AND(ISNUMBER(SEARCH("suspend",N49)),OR(AG49="",AH49="")),"Falta causa/motivo suspensión","OK"))))) | AW49: =IF(N49="","",IF(ISNUMBER(SEARCH("suspend",N49)),IF(AND(AG49="",AH49=""),"Sin causa/motivo registrado",IF(AG49="",AH49,IF(AH49="",AG49,AG49&": "&AH49))),""))
A50: 46169 | B50: ERNESTO SEGUNDO | C50: MOYA | D50: 64a 7m 2d | E50: - FACOERESIS EXTRACAPSULAR CON IMPLANTE DE LENTE INTRAOCULAR (NO INCLUYE EL VALOR DE LA PROTESIS) | F50: UNIDAD DE OFTALMOLOGIA | H50: 1202064-10 | J50: =IF(H50<>"",IFERROR(VLOOKUP(IFERROR(LEFT(H50,FIND("-",H50)-1),H50),'Catalogo MINSAL'!A:E,5,FALSE),""),IF(I50<>"",IFERROR(VLOOKUP(IFERROR(LEFT(I50,FIND("-",I50)-1),I50),'Catalogo MINSAL'!A:E,5,FALSE),""),"")) | K50: Diandra Silva Rodriguez | L50: Dr. Arturo Hillerns Eltit | M50: Quirofano 08 | N50: Atendido | O50: 0.66666667 | P50: =IFERROR(IF(OR(O50="",A50="",M50=""),"",IF(SUMPRODUCT(($A$4:$A$500=A50)*($M$4:$M$500=M50)*($O$4:$O$500<>"")*(MOD($O$4:$O$500,1)<MOD(O50,1)))=0,IF(MOD(O50,1)<=TIME(8,15,0),"Ingreso adecuado primera hora","Atraso primera hora"),"No aplica")),"") | R50: 0.66944444 | S50: 0.67847222 | T50: 0.68125 | U50: =IFERROR(VLOOKUP(M50,'Horario Pabellones'!$A$4:$D$17,2,FALSE),"") | V50: =IFERROR(VLOOKUP(M50,'Horario Pabellones'!$A$4:$D$17,3,FALSE),"") | W50: =IFERROR(VLOOKUP(M50,'Horario Pabellones'!$A$4:$D$17,4,FALSE),"") | X50: =IFERROR(IF(OR(A50="",M50="",W50=""),"",(((_xludf.AGGREGATE(14,6,MOD($S$4:$S$500,1)/(($A$4:$A$500=A50)*($M$4:$M$500=M50)*($R$4:$R$500<>"")*($S$4:$S$500<>"")),1)-_xludf.AGGREGATE(15,6,MOD($R$4:$R$500,1)/(($A$4:$A$500=A50)*($M$4:$M$500=M50)*($R$4:$R$500<>"")*($S$4:$S$500<>"")),1))*1440)/60)/(W50/60)),"") | Y50: =IFERROR(IF(OR(O50="",A50="",M50=""),"",(IF(ISNUMBER(O50),MOD(O50,1),TIMEVALUE(O50))-LOOKUP(2,1/(($A$4:$A$500=A50)*($M$4:$M$500=M50)*($T$4:$T$500<>"")*($T$4:$T$500<IF(ISNUMBER(O50),MOD(O50,1),TIMEVALUE(O50)))),$T$4:$T$500))*1440),"") | Z50: =IFERROR(IF(Y50="","",IF(ROUND(Y50,0)<=15,"Cumple","No cumple")),"") | AB50: =IFERROR(IF(OR(O50="",R50=""),"",IF(IF(ISNUMBER(R50),MOD(R50,1),TIMEVALUE(R50))>=IF(ISNUMBER(O50),MOD(O50,1),TIMEVALUE(O50)),(IF(ISNUMBER(R50),MOD(R50,1),TIMEVALUE(R50))-IF(ISNUMBER(O50),MOD(O50,1),TIMEVALUE(O50)))*1440,(IF(ISNUMBER(R50),MOD(R50,1),TIMEVALUE(R50))+1-IF(ISNUMBER(O50),MOD(O50,1),TIMEVALUE(O50)))*1440)),"") | AC50: =IFERROR(IF(OR(R50="",S50=""),"",IF(IF(ISNUMBER(S50),MOD(S50,1),TIMEVALUE(S50))>=IF(ISNUMBER(R50),MOD(R50,1),TIMEVALUE(R50)),(IF(ISNUMBER(S50),MOD(S50,1),TIMEVALUE(S50))-IF(ISNUMBER(R50),MOD(R50,1),TIMEVALUE(R50)))*1440,(IF(ISNUMBER(S50),MOD(S50,1),TIMEVALUE(S50))+1-IF(ISNUMBER(R50),MOD(R50,1),TIMEVALUE(R50)))*1440)),"") | AE50: =IFERROR(IF(OR(AC50="",AD50=""),"",AC50-AD50),"") | AF50: =IFERROR(IF(AE50="","",IF(ROUND(AE50,0)>15,"Subestimacion",IF(ROUND(AE50,0)<-15,"Sobrestimacion","Asertivo"))),"") | AG50: Sin Suspensión | AM50: I0001188347 | AP50: =IF(A50="","",A50-WEEKDAY(A50,2)+1) | AQ50: =IF(AO50="","",AO50+6) | AR50: =IF(AO50="","","Semana "&TEXT(AO50,"dd-mm-yyyy")&" al "&TEXT(AP50,"dd-mm-yyyy")) | AS50: =IF(A50="","",TEXT(A50,"mmmm yyyy")) | AT50: =IF(A50="","",TEXT(A50,"dddd")) | AU50: =IF(A50="","","CRR-"&TEXT(A50,"yyyymmdd")&"-"&M50&"-"&TEXT(ROW()-3,"0000")) | AV50: =IF(A50="","",IF(OR(B50="",C50="",E50="",F50="",M50="",N50=""),"Revisar campos obligatorios",IF(AND(P50="Atraso primera hora",Q50=""),"Falta justificación atraso primera hora",IF(AND(Z50="No cumple",AA50=""),"Falta justificación recambio >15 min",IF(AND(ISNUMBER(SEARCH("suspend",N50)),OR(AG50="",AH50="")),"Falta causa/motivo suspensión","OK"))))) | AW50: =IF(N50="","",IF(ISNUMBER(SEARCH("suspend",N50)),IF(AND(AG50="",AH50=""),"Sin causa/motivo registrado",IF(AG50="",AH50,IF(AH50="",AG50,AG50&": "&AH50))),""))
A51: 46170 | B51: JORGE ANTONIO | C51: QUEZADA | D51: 51a 6m 12d | E51: Orquidectomía ampliada por cáncer testicular | F51: SERVICIO DE UROLOGIA | H51: 1902068-6 | J51: =IF(H51<>"",IFERROR(VLOOKUP(IFERROR(LEFT(H51,FIND("-",H51)-1),H51),'Catalogo MINSAL'!A:E,5,FALSE),""),IF(I51<>"",IFERROR(VLOOKUP(IFERROR(LEFT(I51,FIND("-",I51)-1),I51),'Catalogo MINSAL'!A:E,5,FALSE),""),"")) | K51: Ivette Lopez Muñoz | L51: Lucas Martin Arzeno Thome | M51: Quirofano 07 | N51: Atendido | O51: 0.34722222 | P51: =IFERROR(IF(OR(O51="",A51="",M51=""),"",IF(SUMPRODUCT(($A$4:$A$500=A51)*($M$4:$M$500=M51)*($O$4:$O$500<>"")*(MOD($O$4:$O$500,1)<MOD(O51,1)))=0,IF(MOD(O51,1)<=TIME(8,15,0),"Ingreso adecuado primera hora","Atraso primera hora"),"No aplica")),"") | R51: 0.36458333 | S51: 0.41319444 | T51: 0.42013889 | U51: =IFERROR(VLOOKUP(M51,'Horario Pabellones'!$A$4:$D$17,2,FALSE),"") | V51: =IFERROR(VLOOKUP(M51,'Horario Pabellones'!$A$4:$D$17,3,FALSE),"") | W51: =IFERROR(VLOOKUP(M51,'Horario Pabellones'!$A$4:$D$17,4,FALSE),"") | X51: =IFERROR(IF(OR(A51="",M51="",W51=""),"",(((_xludf.AGGREGATE(14,6,MOD($S$4:$S$500,1)/(($A$4:$A$500=A51)*($M$4:$M$500=M51)*($R$4:$R$500<>"")*($S$4:$S$500<>"")),1)-_xludf.AGGREGATE(15,6,MOD($R$4:$R$500,1)/(($A$4:$A$500=A51)*($M$4:$M$500=M51)*($R$4:$R$500<>"")*($S$4:$S$500<>"")),1))*1440)/60)/(W51/60)),"") | Y51: =IFERROR(IF(OR(O51="",A51="",M51=""),"",(IF(ISNUMBER(O51),MOD(O51,1),TIMEVALUE(O51))-LOOKUP(2,1/(($A$4:$A$500=A51)*($M$4:$M$500=M51)*($T$4:$T$500<>"")*($T$4:$T$500<IF(ISNUMBER(O51),MOD(O51,1),TIMEVALUE(O51)))),$T$4:$T$500))*1440),"") | Z51: =IFERROR(IF(Y51="","",IF(ROUND(Y51,0)<=15,"Cumple","No cumple")),"") | AB51: =IFERROR(IF(OR(O51="",R51=""),"",IF(IF(ISNUMBER(R51),MOD(R51,1),TIMEVALUE(R51))>=IF(ISNUMBER(O51),MOD(O51,1),TIMEVALUE(O51)),(IF(ISNUMBER(R51),MOD(R51,1),TIMEVALUE(R51))-IF(ISNUMBER(O51),MOD(O51,1),TIMEVALUE(O51)))*1440,(IF(ISNUMBER(R51),MOD(R51,1),TIMEVALUE(R51))+1-IF(ISNUMBER(O51),MOD(O51,1),TIMEVALUE(O51)))*1440)),"") | AC51: =IFERROR(IF(OR(R51="",S51=""),"",IF(IF(ISNUMBER(S51),MOD(S51,1),TIMEVALUE(S51))>=IF(ISNUMBER(R51),MOD(R51,1),TIMEVALUE(R51)),(IF(ISNUMBER(S51),MOD(S51,1),TIMEVALUE(S51))-IF(ISNUMBER(R51),MOD(R51,1),TIMEVALUE(R51)))*1440,(IF(ISNUMBER(S51),MOD(S51,1),TIMEVALUE(S51))+1-IF(ISNUMBER(R51),MOD(R51,1),TIMEVALUE(R51)))*1440)),"") | AE51: =IFERROR(IF(OR(AC51="",AD51=""),"",AC51-AD51),"") | AF51: =IFERROR(IF(AE51="","",IF(ROUND(AE51,0)>15,"Subestimacion",IF(ROUND(AE51,0)<-15,"Sobrestimacion","Asertivo"))),"") | AG51: Sin Suspensión | AM51: I0001188400 | AP51: =IF(A51="","",A51-WEEKDAY(A51,2)+1) | AQ51: =IF(AO51="","",AO51+6) | AR51: =IF(AO51="","","Semana "&TEXT(AO51,"dd-mm-yyyy")&" al "&TEXT(AP51,"dd-mm-yyyy")) | AS51: =IF(A51="","",TEXT(A51,"mmmm yyyy")) | AT51: =IF(A51="","",TEXT(A51,"dddd")) | AU51: =IF(A51="","","CRR-"&TEXT(A51,"yyyymmdd")&"-"&M51&"-"&TEXT(ROW()-3,"0000")) | AV51: =IF(A51="","",IF(OR(B51="",C51="",E51="",F51="",M51="",N51=""),"Revisar campos obligatorios",IF(AND(P51="Atraso primera hora",Q51=""),"Falta justificación atraso primera hora",IF(AND(Z51="No cumple",AA51=""),"Falta justificación recambio >15 min",IF(AND(ISNUMBER(SEARCH("suspend",N51)),OR(AG51="",AH51="")),"Falta causa/motivo suspensión","OK"))))) | AW51: =IF(N51="","",IF(ISNUMBER(SEARCH("suspend",N51)),IF(AND(AG51="",AH51=""),"Sin causa/motivo registrado",IF(AG51="",AH51,IF(AH51="",AG51,AG51&": "&AH51))),""))
A52: 46170 | B52: MARLON RICARDO | C52: PIRAZAN | D52: 43a 1m 13d | E52: CIRCUNCISION (INCLUYE SECCION DE FRENILLO, Y/O DE SINEQUIAS BALANO-PREPUCIALES, Y/O INCISION DORSAL C/S MEATOTOMIA) | F52: SERVICIO DE UROLOGIA | H52: 1902082-5 | J52: =IF(H52<>"",IFERROR(VLOOKUP(IFERROR(LEFT(H52,FIND("-",H52)-1),H52),'Catalogo MINSAL'!A:E,5,FALSE),""),IF(I52<>"",IFERROR(VLOOKUP(IFERROR(LEFT(I52,FIND("-",I52)-1),I52),'Catalogo MINSAL'!A:E,5,FALSE),""),"")) | K52: Ivette Lopez Muñoz | L52: Lucas Martin Arzeno Thome | M52: Quirofano 07 | N52: Atendido | O52: 0.43055556 | P52: =IFERROR(IF(OR(O52="",A52="",M52=""),"",IF(SUMPRODUCT(($A$4:$A$500=A52)*($M$4:$M$500=M52)*($O$4:$O$500<>"")*(MOD($O$4:$O$500,1)<MOD(O52,1)))=0,IF(MOD(O52,1)<=TIME(8,15,0),"Ingreso adecuado primera hora","Atraso primera hora"),"No aplica")),"") | R52: 0.45486111 | S52: 0.50347222 | T52: 0.51388889 | U52: =IFERROR(VLOOKUP(M52,'Horario Pabellones'!$A$4:$D$17,2,FALSE),"") | V52: =IFERROR(VLOOKUP(M52,'Horario Pabellones'!$A$4:$D$17,3,FALSE),"") | W52: =IFERROR(VLOOKUP(M52,'Horario Pabellones'!$A$4:$D$17,4,FALSE),"") | X52: =IFERROR(IF(OR(A52="",M52="",W52=""),"",(((_xludf.AGGREGATE(14,6,MOD($S$4:$S$500,1)/(($A$4:$A$500=A52)*($M$4:$M$500=M52)*($R$4:$R$500<>"")*($S$4:$S$500<>"")),1)-_xludf.AGGREGATE(15,6,MOD($R$4:$R$500,1)/(($A$4:$A$500=A52)*($M$4:$M$500=M52)*($R$4:$R$500<>"")*($S$4:$S$500<>"")),1))*1440)/60)/(W52/60)),"") | Y52: =IFERROR(IF(OR(O52="",A52="",M52=""),"",(IF(ISNUMBER(O52),MOD(O52,1),TIMEVALUE(O52))-LOOKUP(2,1/(($A$4:$A$500=A52)*($M$4:$M$500=M52)*($T$4:$T$500<>"")*($T$4:$T$500<IF(ISNUMBER(O52),MOD(O52,1),TIMEVALUE(O52)))),$T$4:$T$500))*1440),"") | Z52: =IFERROR(IF(Y52="","",IF(ROUND(Y52,0)<=15,"Cumple","No cumple")),"") | AB52: =IFERROR(IF(OR(O52="",R52=""),"",IF(IF(ISNUMBER(R52),MOD(R52,1),TIMEVALUE(R52))>=IF(ISNUMBER(O52),MOD(O52,1),TIMEVALUE(O52)),(IF(ISNUMBER(R52),MOD(R52,1),TIMEVALUE(R52))-IF(ISNUMBER(O52),MOD(O52,1),TIMEVALUE(O52)))*1440,(IF(ISNUMBER(R52),MOD(R52,1),TIMEVALUE(R52))+1-IF(ISNUMBER(O52),MOD(O52,1),TIMEVALUE(O52)))*1440)),"") | AC52: =IFERROR(IF(OR(R52="",S52=""),"",IF(IF(ISNUMBER(S52),MOD(S52,1),TIMEVALUE(S52))>=IF(ISNUMBER(R52),MOD(R52,1),TIMEVALUE(R52)),(IF(ISNUMBER(S52),MOD(S52,1),TIMEVALUE(S52))-IF(ISNUMBER(R52),MOD(R52,1),TIMEVALUE(R52)))*1440,(IF(ISNUMBER(S52),MOD(S52,1),TIMEVALUE(S52))+1-IF(ISNUMBER(R52),MOD(R52,1),TIMEVALUE(R52)))*1440)),"") | AD52: 30 | AE52: =IFERROR(IF(OR(AC52="",AD52=""),"",AC52-AD52),"") | AF52: =IFERROR(IF(AE52="","",IF(ROUND(AE52,0)>15,"Subestimacion",IF(ROUND(AE52,0)<-15,"Sobrestimacion","Asertivo"))),"") | AG52: Sin Suspensión | AM52: I0001188399 | AP52: =IF(A52="","",A52-WEEKDAY(A52,2)+1) | AQ52: =IF(AO52="","",AO52+6) | AR52: =IF(AO52="","","Semana "&TEXT(AO52,"dd-mm-yyyy")&" al "&TEXT(AP52,"dd-mm-yyyy")) | AS52: =IF(A52="","",TEXT(A52,"mmmm yyyy")) | AT52: =IF(A52="","",TEXT(A52,"dddd")) | AU52: =IF(A52="","","CRR-"&TEXT(A52,"yyyymmdd")&"-"&M52&"-"&TEXT(ROW()-3,"0000")) | AV52: =IF(A52="","",IF(OR(B52="",C52="",E52="",F52="",M52="",N52=""),"Revisar campos obligatorios",IF(AND(P52="Atraso primera hora",Q52=""),"Falta justificación atraso primera hora",IF(AND(Z52="No cumple",AA52=""),"Falta justificación recambio >15 min",IF(AND(ISNUMBER(SEARCH("suspend",N52)),OR(AG52="",AH52="")),"Falta causa/motivo suspensión","OK"))))) | AW52: =IF(N52="","",IF(ISNUMBER(SEARCH("suspend",N52)),IF(AND(AG52="",AH52=""),"Sin causa/motivo registrado",IF(AG52="",AH52,IF(AH52="",AG52,AG52&": "&AH52))),""))
A53: 46170 | B53: JULIO CÉSAR | C53: ESPINOZA | D53: 40a 6m 15d | E53: VASECTOMIA BILATERAL, (PROC. AUT.) (LA VASECTOMIA COMO TIEMPO PREVIO A UNA RESECCION DE PROSTATA ESTA INCLUIDA EN LA PROSTATECTOMIA) | F53: SERVICIO DE UROLOGIA | H53: 1902076 | J53: =IF(H53<>"",IFERROR(VLOOKUP(IFERROR(LEFT(H53,FIND("-",H53)-1),H53),'Catalogo MINSAL'!A:E,5,FALSE),""),IF(I53<>"",IFERROR(VLOOKUP(IFERROR(LEFT(I53,FIND("-",I53)-1),I53),'Catalogo MINSAL'!A:E,5,FALSE),""),"")) | K53: Ivette Lopez Muñoz | L53: Sara Francisca Barria Oyarce | M53: Quirofano 07 | N53: Atendido | O53: 0.52083333 | P53: =IFERROR(IF(OR(O53="",A53="",M53=""),"",IF(SUMPRODUCT(($A$4:$A$500=A53)*($M$4:$M$500=M53)*($O$4:$O$500<>"")*(MOD($O$4:$O$500,1)<MOD(O53,1)))=0,IF(MOD(O53,1)<=TIME(8,15,0),"Ingreso adecuado primera hora","Atraso primera hora"),"No aplica")),"") | R53: 0.54097222 | S53: 0.56041667 | T53: 0.56458333 | U53: =IFERROR(VLOOKUP(M53,'Horario Pabellones'!$A$4:$D$17,2,FALSE),"") | V53: =IFERROR(VLOOKUP(M53,'Horario Pabellones'!$A$4:$D$17,3,FALSE),"") | W53: =IFERROR(VLOOKUP(M53,'Horario Pabellones'!$A$4:$D$17,4,FALSE),"") | X53: =IFERROR(IF(OR(A53="",M53="",W53=""),"",(((_xludf.AGGREGATE(14,6,MOD($S$4:$S$500,1)/(($A$4:$A$500=A53)*($M$4:$M$500=M53)*($R$4:$R$500<>"")*($S$4:$S$500<>"")),1)-_xludf.AGGREGATE(15,6,MOD($R$4:$R$500,1)/(($A$4:$A$500=A53)*($M$4:$M$500=M53)*($R$4:$R$500<>"")*($S$4:$S$500<>"")),1))*1440)/60)/(W53/60)),"") | Y53: =IFERROR(IF(OR(O53="",A53="",M53=""),"",(IF(ISNUMBER(O53),MOD(O53,1),TIMEVALUE(O53))-LOOKUP(2,1/(($A$4:$A$500=A53)*($M$4:$M$500=M53)*($T$4:$T$500<>"")*($T$4:$T$500<IF(ISNUMBER(O53),MOD(O53,1),TIMEVALUE(O53)))),$T$4:$T$500))*1440),"") | Z53: =IFERROR(IF(Y53="","",IF(ROUND(Y53,0)<=15,"Cumple","No cumple")),"") | AB53: =IFERROR(IF(OR(O53="",R53=""),"",IF(IF(ISNUMBER(R53),MOD(R53,1),TIMEVALUE(R53))>=IF(ISNUMBER(O53),MOD(O53,1),TIMEVALUE(O53)),(IF(ISNUMBER(R53),MOD(R53,1),TIMEVALUE(R53))-IF(ISNUMBER(O53),MOD(O53,1),TIMEVALUE(O53)))*1440,(IF(ISNUMBER(R53),MOD(R53,1),TIMEVALUE(R53))+1-IF(ISNUMBER(O53),MOD(O53,1),TIMEVALUE(O53)))*1440)),"") | AC53: =IFERROR(IF(OR(R53="",S53=""),"",IF(IF(ISNUMBER(S53),MOD(S53,1),TIMEVALUE(S53))>=IF(ISNUMBER(R53),MOD(R53,1),TIMEVALUE(R53)),(IF(ISNUMBER(S53),MOD(S53,1),TIMEVALUE(S53))-IF(ISNUMBER(R53),MOD(R53,1),TIMEVALUE(R53)))*1440,(IF(ISNUMBER(S53),MOD(S53,1),TIMEVALUE(S53))+1-IF(ISNUMBER(R53),MOD(R53,1),TIMEVALUE(R53)))*1440)),"") | AE53: =IFERROR(IF(OR(AC53="",AD53=""),"",AC53-AD53),"") | AF53: =IFERROR(IF(AE53="","",IF(ROUND(AE53,0)>15,"Subestimacion",IF(ROUND(AE53,0)<-15,"Sobrestimacion","Asertivo"))),"") | AG53: Sin Suspensión | AM53: I0001188587 | AP53: =IF(A53="","",A53-WEEKDAY(A53,2)+1) | AQ53: =IF(AO53="","",AO53+6) | AR53: =IF(AO53="","","Semana "&TEXT(AO53,"dd-mm-yyyy")&" al "&TEXT(AP53,"dd-mm-yyyy")) | AS53: =IF(A53="","",TEXT(A53,"mmmm yyyy")) | AT53: =IF(A53="","",TEXT(A53,"dddd")) | AU53: =IF(A53="","","CRR-"&TEXT(A53,"yyyymmdd")&"-"&M53&"-"&TEXT(ROW()-3,"0000")) | AV53: =IF(A53="","",IF(OR(B53="",C53="",E53="",F53="",M53="",N53=""),"Revisar campos obligatorios",IF(AND(P53="Atraso primera hora",Q53=""),"Falta justificación atraso primera hora",IF(AND(Z53="No cumple",AA53=""),"Falta justificación recambio >15 min",IF(AND(ISNUMBER(SEARCH("suspend",N53)),OR(AG53="",AH53="")),"Falta causa/motivo suspensión","OK"))))) | AW53: =IF(N53="","",IF(ISNUMBER(SEARCH("suspend",N53)),IF(AND(AG53="",AH53=""),"Sin causa/motivo registrado",IF(AG53="",AH53,IF(AH53="",AG53,AG53&": "&AH53))),""))
A54: 46170 | B54: JUAN IGNACIO | C54: VILLARROEL | D54: 34a 11m 5d | E54: VASECTOMIA BILATERAL, (PROC. AUT.) (LA VASECTOMIA COMO TIEMPO PREVIO A UNA RESECCION DE PROSTATA ESTA INCLUIDA EN LA PROSTATECTOMIA) | F54: SERVICIO DE UROLOGIA | H54: 1902076 | J54: =IF(H54<>"",IFERROR(VLOOKUP(IFERROR(LEFT(H54,FIND("-",H54)-1),H54),'Catalogo MINSAL'!A:E,5,FALSE),""),IF(I54<>"",IFERROR(VLOOKUP(IFERROR(LEFT(I54,FIND("-",I54)-1),I54),'Catalogo MINSAL'!A:E,5,FALSE),""),"")) | K54: Ivette Lopez Muñoz | L54: Sara Francisca Barria Oyarce | M54: Quirofano 07 | N54: Atendido | O54: 0.57569444 | P54: =IFERROR(IF(OR(O54="",A54="",M54=""),"",IF(SUMPRODUCT(($A$4:$A$500=A54)*($M$4:$M$500=M54)*($O$4:$O$500<>"")*(MOD($O$4:$O$500,1)<MOD(O54,1)))=0,IF(MOD(O54,1)<=TIME(8,15,0),"Ingreso adecuado primera hora","Atraso primera hora"),"No aplica")),"") | R54: 0.5875 | S54: 0.60763889 | T54: 0.61527778 | U54: =IFERROR(VLOOKUP(M54,'Horario Pabellones'!$A$4:$D$17,2,FALSE),"") | V54: =IFERROR(VLOOKUP(M54,'Horario Pabellones'!$A$4:$D$17,3,FALSE),"") | W54: =IFERROR(VLOOKUP(M54,'Horario Pabellones'!$A$4:$D$17,4,FALSE),"") | X54: =IFERROR(IF(OR(A54="",M54="",W54=""),"",(((_xludf.AGGREGATE(14,6,MOD($S$4:$S$500,1)/(($A$4:$A$500=A54)*($M$4:$M$500=M54)*($R$4:$R$500<>"")*($S$4:$S$500<>"")),1)-_xludf.AGGREGATE(15,6,MOD($R$4:$R$500,1)/(($A$4:$A$500=A54)*($M$4:$M$500=M54)*($R$4:$R$500<>"")*($S$4:$S$500<>"")),1))*1440)/60)/(W54/60)),"") | Y54: =IFERROR(IF(OR(O54="",A54="",M54=""),"",(IF(ISNUMBER(O54),MOD(O54,1),TIMEVALUE(O54))-LOOKUP(2,1/(($A$4:$A$500=A54)*($M$4:$M$500=M54)*($T$4:$T$500<>"")*($T$4:$T$500<IF(ISNUMBER(O54),MOD(O54,1),TIMEVALUE(O54)))),$T$4:$T$500))*1440),"") | Z54: =IFERROR(IF(Y54="","",IF(ROUND(Y54,0)<=15,"Cumple","No cumple")),"") | AB54: =IFERROR(IF(OR(O54="",R54=""),"",IF(IF(ISNUMBER(R54),MOD(R54,1),TIMEVALUE(R54))>=IF(ISNUMBER(O54),MOD(O54,1),TIMEVALUE(O54)),(IF(ISNUMBER(R54),MOD(R54,1),TIMEVALUE(R54))-IF(ISNUMBER(O54),MOD(O54,1),TIMEVALUE(O54)))*1440,(IF(ISNUMBER(R54),MOD(R54,1),TIMEVALUE(R54))+1-IF(ISNUMBER(O54),MOD(O54,1),TIMEVALUE(O54)))*1440)),"") | AC54: =IFERROR(IF(OR(R54="",S54=""),"",IF(IF(ISNUMBER(S54),MOD(S54,1),TIMEVALUE(S54))>=IF(ISNUMBER(R54),MOD(R54,1),TIMEVALUE(R54)),(IF(ISNUMBER(S54),MOD(S54,1),TIMEVALUE(S54))-IF(ISNUMBER(R54),MOD(R54,1),TIMEVALUE(R54)))*1440,(IF(ISNUMBER(S54),MOD(S54,1),TIMEVALUE(S54))+1-IF(ISNUMBER(R54),MOD(R54,1),TIMEVALUE(R54)))*1440)),"") | AE54: =IFERROR(IF(OR(AC54="",AD54=""),"",AC54-AD54),"") | AF54: =IFERROR(IF(AE54="","",IF(ROUND(AE54,0)>15,"Subestimacion",IF(ROUND(AE54,0)<-15,"Sobrestimacion","Asertivo"))),"") | AG54: Sin Suspensión | AM54: I0001188395 | AP54: =IF(A54="","",A54-WEEKDAY(A54,2)+1) | AQ54: =IF(AO54="","",AO54+6) | AR54: =IF(AO54="","","Semana "&TEXT(AO54,"dd-mm-yyyy")&" al "&TEXT(AP54,"dd-mm-yyyy")) | AS54: =IF(A54="","",TEXT(A54,"mmmm yyyy")) | AT54: =IF(A54="","",TEXT(A54,"dddd")) | AU54: =IF(A54="","","CRR-"&TEXT(A54,"yyyymmdd")&"-"&M54&"-"&TEXT(ROW()-3,"0000")) | AV54: =IF(A54="","",IF(OR(B54="",C54="",E54="",F54="",M54="",N54=""),"Revisar campos obligatorios",IF(AND(P54="Atraso primera hora",Q54=""),"Falta justificación atraso primera hora",IF(AND(Z54="No cumple",AA54=""),"Falta justificación recambio >15 min",IF(AND(ISNUMBER(SEARCH("suspend",N54)),OR(AG54="",AH54="")),"Falta causa/motivo suspensión","OK"))))) | AW54: =IF(N54="","",IF(ISNUMBER(SEARCH("suspend",N54)),IF(AND(AG54="",AH54=""),"Sin causa/motivo registrado",IF(AG54="",AH54,IF(AH54="",AG54,AG54&": "&AH54))),""))
A55: 46170 | B55: DIEGO ALFREDO | C55: ZÚÑIGA | D55: 35a 5m 19d | E55: VASECTOMIA BILATERAL, (PROC. AUT.) (LA VASECTOMIA COMO TIEMPO PREVIO A UNA RESECCION DE PROSTATA ESTA INCLUIDA EN LA PROSTATECTOMIA) | F55: SERVICIO DE UROLOGIA | H55: 1902076 | J55: =IF(H55<>"",IFERROR(VLOOKUP(IFERROR(LEFT(H55,FIND("-",H55)-1),H55),'Catalogo MINSAL'!A:E,5,FALSE),""),IF(I55<>"",IFERROR(VLOOKUP(IFERROR(LEFT(I55,FIND("-",I55)-1),I55),'Catalogo MINSAL'!A:E,5,FALSE),""),"")) | K55: Ivette Lopez Muñoz | L55: Sara Francisca Barria Oyarce | M55: Quirofano 07 | N55: Recepcionado | O55: 0.62569444 | P55: =IFERROR(IF(OR(O55="",A55="",M55=""),"",IF(SUMPRODUCT(($A$4:$A$500=A55)*($M$4:$M$500=M55)*($O$4:$O$500<>"")*(MOD($O$4:$O$500,1)<MOD(O55,1)))=0,IF(MOD(O55,1)<=TIME(8,15,0),"Ingreso adecuado primera hora","Atraso primera hora"),"No aplica")),"") | R55: 0.63541667 | S55: 0.65625 | T55: 0.66111111 | U55: =IFERROR(VLOOKUP(M55,'Horario Pabellones'!$A$4:$D$17,2,FALSE),"") | V55: =IFERROR(VLOOKUP(M55,'Horario Pabellones'!$A$4:$D$17,3,FALSE),"") | W55: =IFERROR(VLOOKUP(M55,'Horario Pabellones'!$A$4:$D$17,4,FALSE),"") | X55: =IFERROR(IF(OR(A55="",M55="",W55=""),"",(((_xludf.AGGREGATE(14,6,MOD($S$4:$S$500,1)/(($A$4:$A$500=A55)*($M$4:$M$500=M55)*($R$4:$R$500<>"")*($S$4:$S$500<>"")),1)-_xludf.AGGREGATE(15,6,MOD($R$4:$R$500,1)/(($A$4:$A$500=A55)*($M$4:$M$500=M55)*($R$4:$R$500<>"")*($S$4:$S$500<>"")),1))*1440)/60)/(W55/60)),"") | Y55: =IFERROR(IF(OR(O55="",A55="",M55=""),"",(IF(ISNUMBER(O55),MOD(O55,1),TIMEVALUE(O55))-LOOKUP(2,1/(($A$4:$A$500=A55)*($M$4:$M$500=M55)*($T$4:$T$500<>"")*($T$4:$T$500<IF(ISNUMBER(O55),MOD(O55,1),TIMEVALUE(O55)))),$T$4:$T$500))*1440),"") | Z55: =IFERROR(IF(Y55="","",IF(ROUND(Y55,0)<=15,"Cumple","No cumple")),"") | AB55: =IFERROR(IF(OR(O55="",R55=""),"",IF(IF(ISNUMBER(R55),MOD(R55,1),TIMEVALUE(R55))>=IF(ISNUMBER(O55),MOD(O55,1),TIMEVALUE(O55)),(IF(ISNUMBER(R55),MOD(R55,1),TIMEVALUE(R55))-IF(ISNUMBER(O55),MOD(O55,1),TIMEVALUE(O55)))*1440,(IF(ISNUMBER(R55),MOD(R55,1),TIMEVALUE(R55))+1-IF(ISNUMBER(O55),MOD(O55,1),TIMEVALUE(O55)))*1440)),"") | AC55: =IFERROR(IF(OR(R55="",S55=""),"",IF(IF(ISNUMBER(S55),MOD(S55,1),TIMEVALUE(S55))>=IF(ISNUMBER(R55),MOD(R55,1),TIMEVALUE(R55)),(IF(ISNUMBER(S55),MOD(S55,1),TIMEVALUE(S55))-IF(ISNUMBER(R55),MOD(R55,1),TIMEVALUE(R55)))*1440,(IF(ISNUMBER(S55),MOD(S55,1),TIMEVALUE(S55))+1-IF(ISNUMBER(R55),MOD(R55,1),TIMEVALUE(R55)))*1440)),"") | AE55: =IFERROR(IF(OR(AC55="",AD55=""),"",AC55-AD55),"") | AF55: =IFERROR(IF(AE55="","",IF(ROUND(AE55,0)>15,"Subestimacion",IF(ROUND(AE55,0)<-15,"Sobrestimacion","Asertivo"))),"") | AG55: Sin Suspensión | AM55: I0001188393 | AP55: =IF(A55="","",A55-WEEKDAY(A55,2)+1) | AQ55: =IF(AO55="","",AO55+6) | AR55: =IF(AO55="","","Semana "&TEXT(AO55,"dd-mm-yyyy")&" al "&TEXT(AP55,"dd-mm-yyyy")) | AS55: =IF(A55="","",TEXT(A55,"mmmm yyyy")) | AT55: =IF(A55="","",TEXT(A55,"dddd")) | AU55: =IF(A55="","","CRR-"&TEXT(A55,"yyyymmdd")&"-"&M55&"-"&TEXT(ROW()-3,"0000")) | AV55: =IF(A55="","",IF(OR(B55="",C55="",E55="",F55="",M55="",N55=""),"Revisar campos obligatorios",IF(AND(P55="Atraso primera hora",Q55=""),"Falta justificación atraso primera hora",IF(AND(Z55="No cumple",AA55=""),"Falta justificación recambio >15 min",IF(AND(ISNUMBER(SEARCH("suspend",N55)),OR(AG55="",AH55="")),"Falta causa/motivo suspensión","OK"))))) | AW55: =IF(N55="","",IF(ISNUMBER(SEARCH("suspend",N55)),IF(AND(AG55="",AH55=""),"Sin causa/motivo registrado",IF(AG55="",AH55,IF(AH55="",AG55,AG55&": "&AH55))),""))
A56: 46170 | B56: HORACIO ALEJANDRO | C56: GAVILÁN | D56: 20a 2m 25d | E56: MEATOTOMIA HOMBRE Y/O SECCION FRENILLO Y/O INCISION DORSAL, (PROC. AUT.) | F56: SERVICIO DE UROLOGIA | H56: 1902084-4 | J56: =IF(H56<>"",IFERROR(VLOOKUP(IFERROR(LEFT(H56,FIND("-",H56)-1),H56),'Catalogo MINSAL'!A:E,5,FALSE),""),IF(I56<>"",IFERROR(VLOOKUP(IFERROR(LEFT(I56,FIND("-",I56)-1),I56),'Catalogo MINSAL'!A:E,5,FALSE),""),"")) | K56: Ivette Lopez Muñoz | L56: Sara Francisca Barria Oyarce | M56: Quirofano 07 | N56: Recepcionado | O56: 0.66666667 | P56: =IFERROR(IF(OR(O56="",A56="",M56=""),"",IF(SUMPRODUCT(($A$4:$A$500=A56)*($M$4:$M$500=M56)*($O$4:$O$500<>"")*(MOD($O$4:$O$500,1)<MOD(O56,1)))=0,IF(MOD(O56,1)<=TIME(8,15,0),"Ingreso adecuado primera hora","Atraso primera hora"),"No aplica")),"") | R56: 0.67361111 | S56: 0.6875 | T56: 0.69097222 | U56: =IFERROR(VLOOKUP(M56,'Horario Pabellones'!$A$4:$D$17,2,FALSE),"") | V56: =IFERROR(VLOOKUP(M56,'Horario Pabellones'!$A$4:$D$17,3,FALSE),"") | W56: =IFERROR(VLOOKUP(M56,'Horario Pabellones'!$A$4:$D$17,4,FALSE),"") | X56: =IFERROR(IF(OR(A56="",M56="",W56=""),"",(((_xludf.AGGREGATE(14,6,MOD($S$4:$S$500,1)/(($A$4:$A$500=A56)*($M$4:$M$500=M56)*($R$4:$R$500<>"")*($S$4:$S$500<>"")),1)-_xludf.AGGREGATE(15,6,MOD($R$4:$R$500,1)/(($A$4:$A$500=A56)*($M$4:$M$500=M56)*($R$4:$R$500<>"")*($S$4:$S$500<>"")),1))*1440)/60)/(W56/60)),"") | Y56: =IFERROR(IF(OR(O56="",A56="",M56=""),"",(IF(ISNUMBER(O56),MOD(O56,1),TIMEVALUE(O56))-LOOKUP(2,1/(($A$4:$A$500=A56)*($M$4:$M$500=M56)*($T$4:$T$500<>"")*($T$4:$T$500<IF(ISNUMBER(O56),MOD(O56,1),TIMEVALUE(O56)))),$T$4:$T$500))*1440),"") | Z56: =IFERROR(IF(Y56="","",IF(ROUND(Y56,0)<=15,"Cumple","No cumple")),"") | AB56: =IFERROR(IF(OR(O56="",R56=""),"",IF(IF(ISNUMBER(R56),MOD(R56,1),TIMEVALUE(R56))>=IF(ISNUMBER(O56),MOD(O56,1),TIMEVALUE(O56)),(IF(ISNUMBER(R56),MOD(R56,1),TIMEVALUE(R56))-IF(ISNUMBER(O56),MOD(O56,1),TIMEVALUE(O56)))*1440,(IF(ISNUMBER(R56),MOD(R56,1),TIMEVALUE(R56))+1-IF(ISNUMBER(O56),MOD(O56,1),TIMEVALUE(O56)))*1440)),"") | AC56: =IFERROR(IF(OR(R56="",S56=""),"",IF(IF(ISNUMBER(S56),MOD(S56,1),TIMEVALUE(S56))>=IF(ISNUMBER(R56),MOD(R56,1),TIMEVALUE(R56)),(IF(ISNUMBER(S56),MOD(S56,1),TIMEVALUE(S56))-IF(ISNUMBER(R56),MOD(R56,1),TIMEVALUE(R56)))*1440,(IF(ISNUMBER(S56),MOD(S56,1),TIMEVALUE(S56))+1-IF(ISNUMBER(R56),MOD(R56,1),TIMEVALUE(R56)))*1440)),"") | AE56: =IFERROR(IF(OR(AC56="",AD56=""),"",AC56-AD56),"") | AF56: =IFERROR(IF(AE56="","",IF(ROUND(AE56,0)>15,"Subestimacion",IF(ROUND(AE56,0)<-15,"Sobrestimacion","Asertivo"))),"") | AG56: Sin Suspensión | AM56: I0001188391 | AP56: =IF(A56="","",A56-WEEKDAY(A56,2)+1) | AQ56: =IF(AO56="","",AO56+6) | AR56: =IF(AO56="","","Semana "&TEXT(AO56,"dd-mm-yyyy")&" al "&TEXT(AP56,"dd-mm-yyyy")) | AS56: =IF(A56="","",TEXT(A56,"mmmm yyyy")) | AT56: =IF(A56="","",TEXT(A56,"dddd")) | AU56: =IF(A56="","","CRR-"&TEXT(A56,"yyyymmdd")&"-"&M56&"-"&TEXT(ROW()-3,"0000")) | AV56: =IF(A56="","",IF(OR(B56="",C56="",E56="",F56="",M56="",N56=""),"Revisar campos obligatorios",IF(AND(P56="Atraso primera hora",Q56=""),"Falta justificación atraso primera hora",IF(AND(Z56="No cumple",AA56=""),"Falta justificación recambio >15 min",IF(AND(ISNUMBER(SEARCH("suspend",N56)),OR(AG56="",AH56="")),"Falta causa/motivo suspensión","OK"))))) | AW56: =IF(N56="","",IF(ISNUMBER(SEARCH("suspend",N56)),IF(AND(AG56="",AH56=""),"Sin causa/motivo registrado",IF(AG56="",AH56,IF(AH56="",AG56,AG56&": "&AH56))),""))
A57: 46170 | B57: JORGE ALEX | C57: NEIRA | D57: 56a 6m 15d | E57: CIRCUNCISION (INCLUYE SECCION DE FRENILLO, Y/O DE SINEQUIAS BALANO-PREPUCIALES, Y/O INCISION DORSAL C/S MEATOTOMIA) | F57: SERVICIO DE UROLOGIA | H57: 1902082-5 | J57: =IF(H57<>"",IFERROR(VLOOKUP(IFERROR(LEFT(H57,FIND("-",H57)-1),H57),'Catalogo MINSAL'!A:E,5,FALSE),""),IF(I57<>"",IFERROR(VLOOKUP(IFERROR(LEFT(I57,FIND("-",I57)-1),I57),'Catalogo MINSAL'!A:E,5,FALSE),""),"")) | K57: Ivette Lopez Muñoz | L57: Sara Francisca Barria Oyarce | M57: Quirofano 07 | N57: Suspendido | P57: =IFERROR(IF(OR(O57="",A57="",M57=""),"",IF(SUMPRODUCT(($A$4:$A$500=A57)*($M$4:$M$500=M57)*($O$4:$O$500<>"")*(MOD($O$4:$O$500,1)<MOD(O57,1)))=0,IF(MOD(O57,1)<=TIME(8,15,0),"Ingreso adecuado primera hora","Atraso primera hora"),"No aplica")),"") | U57: =IFERROR(VLOOKUP(M57,'Horario Pabellones'!$A$4:$D$17,2,FALSE),"") | V57: =IFERROR(VLOOKUP(M57,'Horario Pabellones'!$A$4:$D$17,3,FALSE),"") | W57: =IFERROR(VLOOKUP(M57,'Horario Pabellones'!$A$4:$D$17,4,FALSE),"") | X57: =IFERROR(IF(OR(A57="",M57="",W57=""),"",(((_xludf.AGGREGATE(14,6,MOD($S$4:$S$500,1)/(($A$4:$A$500=A57)*($M$4:$M$500=M57)*($R$4:$R$500<>"")*($S$4:$S$500<>"")),1)-_xludf.AGGREGATE(15,6,MOD($R$4:$R$500,1)/(($A$4:$A$500=A57)*($M$4:$M$500=M57)*($R$4:$R$500<>"")*($S$4:$S$500<>"")),1))*1440)/60)/(W57/60)),"") | Y57: =IFERROR(IF(OR(O57="",A57="",M57=""),"",(IF(ISNUMBER(O57),MOD(O57,1),TIMEVALUE(O57))-LOOKUP(2,1/(($A$4:$A$500=A57)*($M$4:$M$500=M57)*($T$4:$T$500<>"")*($T$4:$T$500<IF(ISNUMBER(O57),MOD(O57,1),TIMEVALUE(O57)))),$T$4:$T$500))*1440),"") | Z57: =IFERROR(IF(Y57="","",IF(ROUND(Y57,0)<=15,"Cumple","No cumple")),"") | AB57: =IFERROR(IF(OR(O57="",R57=""),"",IF(IF(ISNUMBER(R57),MOD(R57,1),TIMEVALUE(R57))>=IF(ISNUMBER(O57),MOD(O57,1),TIMEVALUE(O57)),(IF(ISNUMBER(R57),MOD(R57,1),TIMEVALUE(R57))-IF(ISNUMBER(O57),MOD(O57,1),TIMEVALUE(O57)))*1440,(IF(ISNUMBER(R57),MOD(R57,1),TIMEVALUE(R57))+1-IF(ISNUMBER(O57),MOD(O57,1),TIMEVALUE(O57)))*1440)),"") | AC57: =IFERROR(IF(OR(R57="",S57=""),"",IF(IF(ISNUMBER(S57),MOD(S57,1),TIMEVALUE(S57))>=IF(ISNUMBER(R57),MOD(R57,1),TIMEVALUE(R57)),(IF(ISNUMBER(S57),MOD(S57,1),TIMEVALUE(S57))-IF(ISNUMBER(R57),MOD(R57,1),TIMEVALUE(R57)))*1440,(IF(ISNUMBER(S57),MOD(S57,1),TIMEVALUE(S57))+1-IF(ISNUMBER(R57),MOD(R57,1),TIMEVALUE(R57)))*1440)),"") | AE57: =IFERROR(IF(OR(AC57="",AD57=""),"",AC57-AD57),"") | AF57: =IFERROR(IF(AE57="","",IF(ROUND(AE57,0)>15,"Subestimacion",IF(ROUND(AE57,0)<-15,"Sobrestimacion","Asertivo"))),"") | AG57: Error de programación | AM57: I0001188397 | AP57: =IF(A57="","",A57-WEEKDAY(A57,2)+1) | AQ57: =IF(AO57="","",AO57+6) | AR57: =IF(AO57="","","Semana "&TEXT(AO57,"dd-mm-yyyy")&" al "&TEXT(AP57,"dd-mm-yyyy")) | AS57: =IF(A57="","",TEXT(A57,"mmmm yyyy")) | AT57: =IF(A57="","",TEXT(A57,"dddd")) | AU57: =IF(A57="","","CRR-"&TEXT(A57,"yyyymmdd")&"-"&M57&"-"&TEXT(ROW()-3,"0000")) | AV57: =IF(A57="","",IF(OR(B57="",C57="",E57="",F57="",M57="",N57=""),"Revisar campos obligatorios",IF(AND(P57="Atraso primera hora",Q57=""),"Falta justificación atraso primera hora",IF(AND(Z57="No cumple",AA57=""),"Falta justificación recambio >15 min",IF(AND(ISNUMBER(SEARCH("suspend",N57)),OR(AG57="",AH57="")),"Falta causa/motivo suspensión","OK"))))) | AW57: =IF(N57="","",IF(ISNUMBER(SEARCH("suspend",N57)),IF(AND(AG57="",AH57=""),"Sin causa/motivo registrado",IF(AG57="",AH57,IF(AH57="",AG57,AG57&": "&AH57))),""))
A58: 46170 | B58: MARÍA ELIANA | C58: NÚÑEZ | D58: 75a 7m 19d | E58: - FACOERESIS EXTRACAPSULAR CON IMPLANTE DE LENTE INTRAOCULAR (NO INCLUYE EL VALOR DE LA PROTESIS) | F58: UNIDAD DE OFTALMOLOGIA | H58: 1202064-10 | J58: =IF(H58<>"",IFERROR(VLOOKUP(IFERROR(LEFT(H58,FIND("-",H58)-1),H58),'Catalogo MINSAL'!A:E,5,FALSE),""),IF(I58<>"",IFERROR(VLOOKUP(IFERROR(LEFT(I58,FIND("-",I58)-1),I58),'Catalogo MINSAL'!A:E,5,FALSE),""),"")) | K58: Isidora Fernanda Gonzalez Arenas | L58: Sebastian Aceituno Arroyo | M58: Quirofano 08 | N58: Recepcionado | O58: 0.38194444 | P58: =IFERROR(IF(OR(O58="",A58="",M58=""),"",IF(SUMPRODUCT(($A$4:$A$500=A58)*($M$4:$M$500=M58)*($O$4:$O$500<>"")*(MOD($O$4:$O$500,1)<MOD(O58,1)))=0,IF(MOD(O58,1)<=TIME(8,15,0),"Ingreso adecuado primera hora","Atraso primera hora"),"No aplica")),"") | R58: 0.38888889 | S58: 0.41180556 | T58: 0.41319444 | U58: =IFERROR(VLOOKUP(M58,'Horario Pabellones'!$A$4:$D$17,2,FALSE),"") | V58: =IFERROR(VLOOKUP(M58,'Horario Pabellones'!$A$4:$D$17,3,FALSE),"") | W58: =IFERROR(VLOOKUP(M58,'Horario Pabellones'!$A$4:$D$17,4,FALSE),"") | X58: =IFERROR(IF(OR(A58="",M58="",W58=""),"",(((_xludf.AGGREGATE(14,6,MOD($S$4:$S$500,1)/(($A$4:$A$500=A58)*($M$4:$M$500=M58)*($R$4:$R$500<>"")*($S$4:$S$500<>"")),1)-_xludf.AGGREGATE(15,6,MOD($R$4:$R$500,1)/(($A$4:$A$500=A58)*($M$4:$M$500=M58)*($R$4:$R$500<>"")*($S$4:$S$500<>"")),1))*1440)/60)/(W58/60)),"") | Y58: =IFERROR(IF(OR(O58="",A58="",M58=""),"",(IF(ISNUMBER(O58),MOD(O58,1),TIMEVALUE(O58))-LOOKUP(2,1/(($A$4:$A$500=A58)*($M$4:$M$500=M58)*($T$4:$T$500<>"")*($T$4:$T$500<IF(ISNUMBER(O58),MOD(O58,1),TIMEVALUE(O58)))),$T$4:$T$500))*1440),"") | Z58: =IFERROR(IF(Y58="","",IF(ROUND(Y58,0)<=15,"Cumple","No cumple")),"") | AB58: =IFERROR(IF(OR(O58="",R58=""),"",IF(IF(ISNUMBER(R58),MOD(R58,1),TIMEVALUE(R58))>=IF(ISNUMBER(O58),MOD(O58,1),TIMEVALUE(O58)),(IF(ISNUMBER(R58),MOD(R58,1),TIMEVALUE(R58))-IF(ISNUMBER(O58),MOD(O58,1),TIMEVALUE(O58)))*1440,(IF(ISNUMBER(R58),MOD(R58,1),TIMEVALUE(R58))+1-IF(ISNUMBER(O58),MOD(O58,1),TIMEVALUE(O58)))*1440)),"") | AC58: =IFERROR(IF(OR(R58="",S58=""),"",IF(IF(ISNUMBER(S58),MOD(S58,1),TIMEVALUE(S58))>=IF(ISNUMBER(R58),MOD(R58,1),TIMEVALUE(R58)),(IF(ISNUMBER(S58),MOD(S58,1),TIMEVALUE(S58))-IF(ISNUMBER(R58),MOD(R58,1),TIMEVALUE(R58)))*1440,(IF(ISNUMBER(S58),MOD(S58,1),TIMEVALUE(S58))+1-IF(ISNUMBER(R58),MOD(R58,1),TIMEVALUE(R58)))*1440)),"") | AE58: =IFERROR(IF(OR(AC58="",AD58=""),"",AC58-AD58),"") | AF58: =IFERROR(IF(AE58="","",IF(ROUND(AE58,0)>15,"Subestimacion",IF(ROUND(AE58,0)<-15,"Sobrestimacion","Asertivo"))),"") | AG58: Sin Suspensión | AM58: I0001188442 | AP58: =IF(A58="","",A58-WEEKDAY(A58,2)+1) | AQ58: =IF(AO58="","",AO58+6) | AR58: =IF(AO58="","","Semana "&TEXT(AO58,"dd-mm-yyyy")&" al "&TEXT(AP58,"dd-mm-yyyy")) | AS58: =IF(A58="","",TEXT(A58,"mmmm yyyy")) | AT58: =IF(A58="","",TEXT(A58,"dddd")) | AU58: =IF(A58="","","CRR-"&TEXT(A58,"yyyymmdd")&"-"&M58&"-"&TEXT(ROW()-3,"0000")) | AV58: =IF(A58="","",IF(OR(B58="",C58="",E58="",F58="",M58="",N58=""),"Revisar campos obligatorios",IF(AND(P58="Atraso primera hora",Q58=""),"Falta justificación atraso primera hora",IF(AND(Z58="No cumple",AA58=""),"Falta justificación recambio >15 min",IF(AND(ISNUMBER(SEARCH("suspend",N58)),OR(AG58="",AH58="")),"Falta causa/motivo suspensión","OK"))))) | AW58: =IF(N58="","",IF(ISNUMBER(SEARCH("suspend",N58)),IF(AND(AG58="",AH58=""),"Sin causa/motivo registrado",IF(AG58="",AH58,IF(AH58="",AG58,AG58&": "&AH58))),""))
A59: 46170 | B59: GABRIEL BERNARDO | C59: COLOMA | D59: 70a 7m 24d | E59: - FACOERESIS EXTRACAPSULAR CON IMPLANTE DE LENTE INTRAOCULAR (NO INCLUYE EL VALOR DE LA PROTESIS) | F59: UNIDAD DE OFTALMOLOGIA | H59: 1202064-10 | J59: =IF(H59<>"",IFERROR(VLOOKUP(IFERROR(LEFT(H59,FIND("-",H59)-1),H59),'Catalogo MINSAL'!A:E,5,FALSE),""),IF(I59<>"",IFERROR(VLOOKUP(IFERROR(LEFT(I59,FIND("-",I59)-1),I59),'Catalogo MINSAL'!A:E,5,FALSE),""),"")) | K59: Isidora Fernanda Gonzalez Arenas | L59: Sebastian Aceituno Arroyo | M59: Quirofano 08 | N59: Atendido | O59: 0.41875 | P59: =IFERROR(IF(OR(O59="",A59="",M59=""),"",IF(SUMPRODUCT(($A$4:$A$500=A59)*($M$4:$M$500=M59)*($O$4:$O$500<>"")*(MOD($O$4:$O$500,1)<MOD(O59,1)))=0,IF(MOD(O59,1)<=TIME(8,15,0),"Ingreso adecuado primera hora","Atraso primera hora"),"No aplica")),"") | R59: 0.42152778 | S59: 0.43958333 | T59: 0.44097222 | U59: =IFERROR(VLOOKUP(M59,'Horario Pabellones'!$A$4:$D$17,2,FALSE),"") | V59: =IFERROR(VLOOKUP(M59,'Horario Pabellones'!$A$4:$D$17,3,FALSE),"") | W59: =IFERROR(VLOOKUP(M59,'Horario Pabellones'!$A$4:$D$17,4,FALSE),"") | X59: =IFERROR(IF(OR(A59="",M59="",W59=""),"",(((_xludf.AGGREGATE(14,6,MOD($S$4:$S$500,1)/(($A$4:$A$500=A59)*($M$4:$M$500=M59)*($R$4:$R$500<>"")*($S$4:$S$500<>"")),1)-_xludf.AGGREGATE(15,6,MOD($R$4:$R$500,1)/(($A$4:$A$500=A59)*($M$4:$M$500=M59)*($R$4:$R$500<>"")*($S$4:$S$500<>"")),1))*1440)/60)/(W59/60)),"") | Y59: =IFERROR(IF(OR(O59="",A59="",M59=""),"",(IF(ISNUMBER(O59),MOD(O59,1),TIMEVALUE(O59))-LOOKUP(2,1/(($A$4:$A$500=A59)*($M$4:$M$500=M59)*($T$4:$T$500<>"")*($T$4:$T$500<IF(ISNUMBER(O59),MOD(O59,1),TIMEVALUE(O59)))),$T$4:$T$500))*1440),"") | Z59: =IFERROR(IF(Y59="","",IF(ROUND(Y59,0)<=15,"Cumple","No cumple")),"") | AB59: =IFERROR(IF(OR(O59="",R59=""),"",IF(IF(ISNUMBER(R59),MOD(R59,1),TIMEVALUE(R59))>=IF(ISNUMBER(O59),MOD(O59,1),TIMEVALUE(O59)),(IF(ISNUMBER(R59),MOD(R59,1),TIMEVALUE(R59))-IF(ISNUMBER(O59),MOD(O59,1),TIMEVALUE(O59)))*1440,(IF(ISNUMBER(R59),MOD(R59,1),TIMEVALUE(R59))+1-IF(ISNUMBER(O59),MOD(O59,1),TIMEVALUE(O59)))*1440)),"") | AC59: =IFERROR(IF(OR(R59="",S59=""),"",IF(IF(ISNUMBER(S59),MOD(S59,1),TIMEVALUE(S59))>=IF(ISNUMBER(R59),MOD(R59,1),TIMEVALUE(R59)),(IF(ISNUMBER(S59),MOD(S59,1),TIMEVALUE(S59))-IF(ISNUMBER(R59),MOD(R59,1),TIMEVALUE(R59)))*1440,(IF(ISNUMBER(S59),MOD(S59,1),TIMEVALUE(S59))+1-IF(ISNUMBER(R59),MOD(R59,1),TIMEVALUE(R59)))*1440)),"") | AE59: =IFERROR(IF(OR(AC59="",AD59=""),"",AC59-AD59),"") | AF59: =IFERROR(IF(AE59="","",IF(ROUND(AE59,0)>15,"Subestimacion",IF(ROUND(AE59,0)<-15,"Sobrestimacion","Asertivo"))),"") | AG59: Sin Suspensión | AM59: I0001188444 | AP59: =IF(A59="","",A59-WEEKDAY(A59,2)+1) | AQ59: =IF(AO59="","",AO59+6) | AR59: =IF(AO59="","","Semana "&TEXT(AO59,"dd-mm-yyyy")&" al "&TEXT(AP59,"dd-mm-yyyy")) | AS59: =IF(A59="","",TEXT(A59,"mmmm yyyy")) | AT59: =IF(A59="","",TEXT(A59,"dddd")) | AU59: =IF(A59="","","CRR-"&TEXT(A59,"yyyymmdd")&"-"&M59&"-"&TEXT(ROW()-3,"0000")) | AV59: =IF(A59="","",IF(OR(B59="",C59="",E59="",F59="",M59="",N59=""),"Revisar campos obligatorios",IF(AND(P59="Atraso primera hora",Q59=""),"Falta justificación atraso primera hora",IF(AND(Z59="No cumple",AA59=""),"Falta justificación recambio >15 min",IF(AND(ISNUMBER(SEARCH("suspend",N59)),OR(AG59="",AH59="")),"Falta causa/motivo suspensión","OK"))))) | AW59: =IF(N59="","",IF(ISNUMBER(SEARCH("suspend",N59)),IF(AND(AG59="",AH59=""),"Sin causa/motivo registrado",IF(AG59="",AH59,IF(AH59="",AG59,AG59&": "&AH59))),""))
A60: 46170 | B60: EMA MARÍA | C60: DE LA FUENTE | D60: 75a 7m 25d | E60: - FACOERESIS EXTRACAPSULAR CON IMPLANTE DE LENTE INTRAOCULAR (NO INCLUYE EL VALOR DE LA PROTESIS) | F60: UNIDAD DE OFTALMOLOGIA | H60: 1202064-10 | J60: =IF(H60<>"",IFERROR(VLOOKUP(IFERROR(LEFT(H60,FIND("-",H60)-1),H60),'Catalogo MINSAL'!A:E,5,FALSE),""),IF(I60<>"",IFERROR(VLOOKUP(IFERROR(LEFT(I60,FIND("-",I60)-1),I60),'Catalogo MINSAL'!A:E,5,FALSE),""),"")) | K60: Isidora Fernanda Gonzalez Arenas | L60: Sebastian Aceituno Arroyo | M60: Quirofano 08 | N60: Recepcionado | O60: 0.44444444 | P60: =IFERROR(IF(OR(O60="",A60="",M60=""),"",IF(SUMPRODUCT(($A$4:$A$500=A60)*($M$4:$M$500=M60)*($O$4:$O$500<>"")*(MOD($O$4:$O$500,1)<MOD(O60,1)))=0,IF(MOD(O60,1)<=TIME(8,15,0),"Ingreso adecuado primera hora","Atraso primera hora"),"No aplica")),"") | R60: 0.44722222 | S60: 0.46180556 | T60: 0.46319444 | U60: =IFERROR(VLOOKUP(M60,'Horario Pabellones'!$A$4:$D$17,2,FALSE),"") | V60: =IFERROR(VLOOKUP(M60,'Horario Pabellones'!$A$4:$D$17,3,FALSE),"") | W60: =IFERROR(VLOOKUP(M60,'Horario Pabellones'!$A$4:$D$17,4,FALSE),"") | X60: =IFERROR(IF(OR(A60="",M60="",W60=""),"",(((_xludf.AGGREGATE(14,6,MOD($S$4:$S$500,1)/(($A$4:$A$500=A60)*($M$4:$M$500=M60)*($R$4:$R$500<>"")*($S$4:$S$500<>"")),1)-_xludf.AGGREGATE(15,6,MOD($R$4:$R$500,1)/(($A$4:$A$500=A60)*($M$4:$M$500=M60)*($R$4:$R$500<>"")*($S$4:$S$500<>"")),1))*1440)/60)/(W60/60)),"") | Y60: =IFERROR(IF(OR(O60="",A60="",M60=""),"",(IF(ISNUMBER(O60),MOD(O60,1),TIMEVALUE(O60))-LOOKUP(2,1/(($A$4:$A$500=A60)*($M$4:$M$500=M60)*($T$4:$T$500<>"")*($T$4:$T$500<IF(ISNUMBER(O60),MOD(O60,1),TIMEVALUE(O60)))),$T$4:$T$500))*1440),"") | Z60: =IFERROR(IF(Y60="","",IF(ROUND(Y60,0)<=15,"Cumple","No cumple")),"") | AB60: =IFERROR(IF(OR(O60="",R60=""),"",IF(IF(ISNUMBER(R60),MOD(R60,1),TIMEVALUE(R60))>=IF(ISNUMBER(O60),MOD(O60,1),TIMEVALUE(O60)),(IF(ISNUMBER(R60),MOD(R60,1),TIMEVALUE(R60))-IF(ISNUMBER(O60),MOD(O60,1),TIMEVALUE(O60)))*1440,(IF(ISNUMBER(R60),MOD(R60,1),TIMEVALUE(R60))+1-IF(ISNUMBER(O60),MOD(O60,1),TIMEVALUE(O60)))*1440)),"") | AC60: =IFERROR(IF(OR(R60="",S60=""),"",IF(IF(ISNUMBER(S60),MOD(S60,1),TIMEVALUE(S60))>=IF(ISNUMBER(R60),MOD(R60,1),TIMEVALUE(R60)),(IF(ISNUMBER(S60),MOD(S60,1),TIMEVALUE(S60))-IF(ISNUMBER(R60),MOD(R60,1),TIMEVALUE(R60)))*1440,(IF(ISNUMBER(S60),MOD(S60,1),TIMEVALUE(S60))+1-IF(ISNUMBER(R60),MOD(R60,1),TIMEVALUE(R60)))*1440)),"") | AE60: =IFERROR(IF(OR(AC60="",AD60=""),"",AC60-AD60),"") | AF60: =IFERROR(IF(AE60="","",IF(ROUND(AE60,0)>15,"Subestimacion",IF(ROUND(AE60,0)<-15,"Sobrestimacion","Asertivo"))),"") | AG60: Patología crónica descompensada | AM60: I0001188445 | AP60: =IF(A60="","",A60-WEEKDAY(A60,2)+1) | AQ60: =IF(AO60="","",AO60+6) | AR60: =IF(AO60="","","Semana "&TEXT(AO60,"dd-mm-yyyy")&" al "&TEXT(AP60,"dd-mm-yyyy")) | AS60: =IF(A60="","",TEXT(A60,"mmmm yyyy")) | AT60: =IF(A60="","",TEXT(A60,"dddd")) | AU60: =IF(A60="","","CRR-"&TEXT(A60,"yyyymmdd")&"-"&M60&"-"&TEXT(ROW()-3,"0000")) | AV60: =IF(A60="","",IF(OR(B60="",C60="",E60="",F60="",M60="",N60=""),"Revisar campos obligatorios",IF(AND(P60="Atraso primera hora",Q60=""),"Falta justificación atraso primera hora",IF(AND(Z60="No cumple",AA60=""),"Falta justificación recambio >15 min",IF(AND(ISNUMBER(SEARCH("suspend",N60)),OR(AG60="",AH60="")),"Falta causa/motivo suspensión","OK"))))) | AW60: =IF(N60="","",IF(ISNUMBER(SEARCH("suspend",N60)),IF(AND(AG60="",AH60=""),"Sin causa/motivo registrado",IF(AG60="",AH60,IF(AH60="",AG60,AG60&": "&AH60))),""))
A61: 46170 | B61: ALICIA DEL CARMEN | C61: VERGARA | D61: 75a 9m 25d | E61: - FACOERESIS EXTRACAPSULAR CON IMPLANTE DE LENTE INTRAOCULAR (NO INCLUYE EL VALOR DE LA PROTESIS) | F61: UNIDAD DE OFTALMOLOGIA | H61: 1202064-10 | J61: =IF(H61<>"",IFERROR(VLOOKUP(IFERROR(LEFT(H61,FIND("-",H61)-1),H61),'Catalogo MINSAL'!A:E,5,FALSE),""),IF(I61<>"",IFERROR(VLOOKUP(IFERROR(LEFT(I61,FIND("-",I61)-1),I61),'Catalogo MINSAL'!A:E,5,FALSE),""),"")) | K61: Isidora Fernanda Gonzalez Arenas | L61: Sebastian Aceituno Arroyo | M61: Quirofano 08 | N61: Atendido | O61: 0.47222222 | P61: =IFERROR(IF(OR(O61="",A61="",M61=""),"",IF(SUMPRODUCT(($A$4:$A$500=A61)*($M$4:$M$500=M61)*($O$4:$O$500<>"")*(MOD($O$4:$O$500,1)<MOD(O61,1)))=0,IF(MOD(O61,1)<=TIME(8,15,0),"Ingreso adecuado primera hora","Atraso primera hora"),"No aplica")),"") | R61: 0.47638889 | S61: 0.49097222 | T61: 0.49305556 | U61: =IFERROR(VLOOKUP(M61,'Horario Pabellones'!$A$4:$D$17,2,FALSE),"") | V61: =IFERROR(VLOOKUP(M61,'Horario Pabellones'!$A$4:$D$17,3,FALSE),"") | W61: =IFERROR(VLOOKUP(M61,'Horario Pabellones'!$A$4:$D$17,4,FALSE),"") | X61: =IFERROR(IF(OR(A61="",M61="",W61=""),"",(((_xludf.AGGREGATE(14,6,MOD($S$4:$S$500,1)/(($A$4:$A$500=A61)*($M$4:$M$500=M61)*($R$4:$R$500<>"")*($S$4:$S$500<>"")),1)-_xludf.AGGREGATE(15,6,MOD($R$4:$R$500,1)/(($A$4:$A$500=A61)*($M$4:$M$500=M61)*($R$4:$R$500<>"")*($S$4:$S$500<>"")),1))*1440)/60)/(W61/60)),"") | Y61: =IFERROR(IF(OR(O61="",A61="",M61=""),"",(IF(ISNUMBER(O61),MOD(O61,1),TIMEVALUE(O61))-LOOKUP(2,1/(($A$4:$A$500=A61)*($M$4:$M$500=M61)*($T$4:$T$500<>"")*($T$4:$T$500<IF(ISNUMBER(O61),MOD(O61,1),TIMEVALUE(O61)))),$T$4:$T$500))*1440),"") | Z61: =IFERROR(IF(Y61="","",IF(ROUND(Y61,0)<=15,"Cumple","No cumple")),"") | AB61: =IFERROR(IF(OR(O61="",R61=""),"",IF(IF(ISNUMBER(R61),MOD(R61,1),TIMEVALUE(R61))>=IF(ISNUMBER(O61),MOD(O61,1),TIMEVALUE(O61)),(IF(ISNUMBER(R61),MOD(R61,1),TIMEVALUE(R61))-IF(ISNUMBER(O61),MOD(O61,1),TIMEVALUE(O61)))*1440,(IF(ISNUMBER(R61),MOD(R61,1),TIMEVALUE(R61))+1-IF(ISNUMBER(O61),MOD(O61,1),TIMEVALUE(O61)))*1440)),"") | AC61: =IFERROR(IF(OR(R61="",S61=""),"",IF(IF(ISNUMBER(S61),MOD(S61,1),TIMEVALUE(S61))>=IF(ISNUMBER(R61),MOD(R61,1),TIMEVALUE(R61)),(IF(ISNUMBER(S61),MOD(S61,1),TIMEVALUE(S61))-IF(ISNUMBER(R61),MOD(R61,1),TIMEVALUE(R61)))*1440,(IF(ISNUMBER(S61),MOD(S61,1),TIMEVALUE(S61))+1-IF(ISNUMBER(R61),MOD(R61,1),TIMEVALUE(R61)))*1440)),"") | AD61: 60 | AE61: =IFERROR(IF(OR(AC61="",AD61=""),"",AC61-AD61),"") | AF61: =IFERROR(IF(AE61="","",IF(ROUND(AE61,0)>15,"Subestimacion",IF(ROUND(AE61,0)<-15,"Sobrestimacion","Asertivo"))),"") | AG61: Sin Suspensión | AM61: I0001188424 | AP61: =IF(A61="","",A61-WEEKDAY(A61,2)+1) | AQ61: =IF(AO61="","",AO61+6) | AR61: =IF(AO61="","","Semana "&TEXT(AO61,"dd-mm-yyyy")&" al "&TEXT(AP61,"dd-mm-yyyy")) | AS61: =IF(A61="","",TEXT(A61,"mmmm yyyy")) | AT61: =IF(A61="","",TEXT(A61,"dddd")) | AU61: =IF(A61="","","CRR-"&TEXT(A61,"yyyymmdd")&"-"&M61&"-"&TEXT(ROW()-3,"0000")) | AV61: =IF(A61="","",IF(OR(B61="",C61="",E61="",F61="",M61="",N61=""),"Revisar campos obligatorios",IF(AND(P61="Atraso primera hora",Q61=""),"Falta justificación atraso primera hora",IF(AND(Z61="No cumple",AA61=""),"Falta justificación recambio >15 min",IF(AND(ISNUMBER(SEARCH("suspend",N61)),OR(AG61="",AH61="")),"Falta causa/motivo suspensión","OK"))))) | AW61: =IF(N61="","",IF(ISNUMBER(SEARCH("suspend",N61)),IF(AND(AG61="",AH61=""),"Sin causa/motivo registrado",IF(AG61="",AH61,IF(AH61="",AG61,AG61&": "&AH61))),""))
A62: 46170 | B62: GUILLERMINA DEL CARM | C62: CEA | D62: 73a 11m 3d | E62: - FACOERESIS EXTRACAPSULAR CON IMPLANTE DE LENTE INTRAOCULAR (NO INCLUYE EL VALOR DE LA PROTESIS) | F62: UNIDAD DE OFTALMOLOGIA | H62: 1202064-10 | J62: =IF(H62<>"",IFERROR(VLOOKUP(IFERROR(LEFT(H62,FIND("-",H62)-1),H62),'Catalogo MINSAL'!A:E,5,FALSE),""),IF(I62<>"",IFERROR(VLOOKUP(IFERROR(LEFT(I62,FIND("-",I62)-1),I62),'Catalogo MINSAL'!A:E,5,FALSE),""),"")) | K62: Isidora Fernanda Gonzalez Arenas | L62: Sebastian Aceituno Arroyo | M62: Quirofano 08 | N62: Atendido | O62: 0.49861111 | P62: =IFERROR(IF(OR(O62="",A62="",M62=""),"",IF(SUMPRODUCT(($A$4:$A$500=A62)*($M$4:$M$500=M62)*($O$4:$O$500<>"")*(MOD($O$4:$O$500,1)<MOD(O62,1)))=0,IF(MOD(O62,1)<=TIME(8,15,0),"Ingreso adecuado primera hora","Atraso primera hora"),"No aplica")),"") | R62: 0.50347222 | S62: 0.51527778 | T62: 0.51875 | U62: =IFERROR(VLOOKUP(M62,'Horario Pabellones'!$A$4:$D$17,2,FALSE),"") | V62: =IFERROR(VLOOKUP(M62,'Horario Pabellones'!$A$4:$D$17,3,FALSE),"") | W62: =IFERROR(VLOOKUP(M62,'Horario Pabellones'!$A$4:$D$17,4,FALSE),"") | X62: =IFERROR(IF(OR(A62="",M62="",W62=""),"",(((_xludf.AGGREGATE(14,6,MOD($S$4:$S$500,1)/(($A$4:$A$500=A62)*($M$4:$M$500=M62)*($R$4:$R$500<>"")*($S$4:$S$500<>"")),1)-_xludf.AGGREGATE(15,6,MOD($R$4:$R$500,1)/(($A$4:$A$500=A62)*($M$4:$M$500=M62)*($R$4:$R$500<>"")*($S$4:$S$500<>"")),1))*1440)/60)/(W62/60)),"") | Y62: =IFERROR(IF(OR(O62="",A62="",M62=""),"",(IF(ISNUMBER(O62),MOD(O62,1),TIMEVALUE(O62))-LOOKUP(2,1/(($A$4:$A$500=A62)*($M$4:$M$500=M62)*($T$4:$T$500<>"")*($T$4:$T$500<IF(ISNUMBER(O62),MOD(O62,1),TIMEVALUE(O62)))),$T$4:$T$500))*1440),"") | Z62: =IFERROR(IF(Y62="","",IF(ROUND(Y62,0)<=15,"Cumple","No cumple")),"") | AB62: =IFERROR(IF(OR(O62="",R62=""),"",IF(IF(ISNUMBER(R62),MOD(R62,1),TIMEVALUE(R62))>=IF(ISNUMBER(O62),MOD(O62,1),TIMEVALUE(O62)),(IF(ISNUMBER(R62),MOD(R62,1),TIMEVALUE(R62))-IF(ISNUMBER(O62),MOD(O62,1),TIMEVALUE(O62)))*1440,(IF(ISNUMBER(R62),MOD(R62,1),TIMEVALUE(R62))+1-IF(ISNUMBER(O62),MOD(O62,1),TIMEVALUE(O62)))*1440)),"") | AC62: =IFERROR(IF(OR(R62="",S62=""),"",IF(IF(ISNUMBER(S62),MOD(S62,1),TIMEVALUE(S62))>=IF(ISNUMBER(R62),MOD(R62,1),TIMEVALUE(R62)),(IF(ISNUMBER(S62),MOD(S62,1),TIMEVALUE(S62))-IF(ISNUMBER(R62),MOD(R62,1),TIMEVALUE(R62)))*1440,(IF(ISNUMBER(S62),MOD(S62,1),TIMEVALUE(S62))+1-IF(ISNUMBER(R62),MOD(R62,1),TIMEVALUE(R62)))*1440)),"") | AD62: 60 | AE62: =IFERROR(IF(OR(AC62="",AD62=""),"",AC62-AD62),"") | AF62: =IFERROR(IF(AE62="","",IF(ROUND(AE62,0)>15,"Subestimacion",IF(ROUND(AE62,0)<-15,"Sobrestimacion","Asertivo"))),"") | AG62: Sin Suspensión | AM62: I0001188427 | AP62: =IF(A62="","",A62-WEEKDAY(A62,2)+1) | AQ62: =IF(AO62="","",AO62+6) | AR62: =IF(AO62="","","Semana "&TEXT(AO62,"dd-mm-yyyy")&" al "&TEXT(AP62,"dd-mm-yyyy")) | AS62: =IF(A62="","",TEXT(A62,"mmmm yyyy")) | AT62: =IF(A62="","",TEXT(A62,"dddd")) | AU62: =IF(A62="","","CRR-"&TEXT(A62,"yyyymmdd")&"-"&M62&"-"&TEXT(ROW()-3,"0000")) | AV62: =IF(A62="","",IF(OR(B62="",C62="",E62="",F62="",M62="",N62=""),"Revisar campos obligatorios",IF(AND(P62="Atraso primera hora",Q62=""),"Falta justificación atraso primera hora",IF(AND(Z62="No cumple",AA62=""),"Falta justificación recambio >15 min",IF(AND(ISNUMBER(SEARCH("suspend",N62)),OR(AG62="",AH62="")),"Falta causa/motivo suspensión","OK"))))) | AW62: =IF(N62="","",IF(ISNUMBER(SEARCH("suspend",N62)),IF(AND(AG62="",AH62=""),"Sin causa/motivo registrado",IF(AG62="",AH62,IF(AH62="",AG62,AG62&": "&AH62))),""))
